Workbook

Sheet Dashboard
B1: =Assumptions!$D$5 -> Sample Aqua Ltd.
B2: Fish Farming and Hatchery Project: Dashboard
B3: ="Scenario: "&Assumptions!$D$11&" | BDT million unless stated" -> Scenario: Base case | BDT million unless stated
B5: PROFITABILITY | I5: INVESTMENT
B6: BDT million | C6: ='Income Statement'!E4 -> FY2026-27 | D6: ='Income Statement'!F4 -> FY2027-28 | E6: ='Income Statement'!G4 -> FY2028-29 | F6: ='Income Statement'!H4 -> FY2029-30 | G6: ='Income Statement'!I4 -> FY2030-31 | I6: Project cost and funding (BDT million)
B7: Revenue | C7: ='Income Statement'!E10/1000000 -> 12.08 | D7: ='Income Statement'!F10/1000000 -> 49.7175 | E7: ='Income Statement'!G10/1000000 -> 66.8115 | F7: ='Income Statement'!H10/1000000 -> 83.059594 | G7: ='Income Statement'!I10/1000000 -> 75.543713 | I7: Fixed assets (project cost) | J7: =Funding!D11/1000000 -> 45.792242
B8: Revenue growth | D8: ='Income Statement'!F11 -> 3.1156871 | E8: ='Income Statement'!G11 -> 0.3438226 | F8: ='Income Statement'!H11 -> 0.24319307 | G8: ='Income Statement'!I11 -> -0.090487805 | I8: Opening cash for Year 1 working capital | J8: =Funding!D12/1000000 -> 2.4199453
B9: Cost of goods sold (COGS) | C9: =-'Income Statement'!E18/1000000 -> 8.681334 | D9: =-'Income Statement'!F18/1000000 -> 22.562346 | E9: =-'Income Statement'!G18/1000000 -> 29.776102 | F9: =-'Income Statement'!H18/1000000 -> 30.865272 | G9: =-'Income Statement'!I18/1000000 -> 32.009687 | I9: Total funds needed | J9: =Funding!D13/1000000 -> 48.212188
B10: Gross profit | C10: ='Income Statement'!E19/1000000 -> 3.398666 | D10: ='Income Statement'!F19/1000000 -> 27.155154 | E10: ='Income Statement'!G19/1000000 -> 37.035398 | F10: ='Income Statement'!H19/1000000 -> 52.194322 | G10: ='Income Statement'!I19/1000000 -> 43.534027 | I10: Bank term loan | J10: =Funding!D16/1000000 -> 22.896121
B11: Gross margin | C11: ='Income Statement'!E20 -> 0.28134652 | D11: ='Income Statement'!F20 -> 0.54618906 | E11: ='Income Statement'!G20 -> 0.5543267 | F11: ='Income Statement'!H20 -> 0.62839607 | G11: ='Income Statement'!I20 -> 0.57627597 | I11: Owner equity | J11: =Funding!D17/1000000 -> 25.316066
B12: Operating expenses | C12: =-'Income Statement'!E27/1000000 -> 2.60655 | D12: =-'Income Statement'!F27/1000000 -> 5.043665 | E12: =-'Income Statement'!G27/1000000 -> 6.7408482 | F12: =-'Income Statement'!H27/1000000 -> 8.3542738 | G12: =-'Income Statement'!I27/1000000 -> 7.5923209 | I12: Owner share of total funds | J12: =Funding!D20 -> 0.52509682
B13: EBITDA | C13: ='Income Statement'!E28/1000000 -> 0.79211599 | D13: ='Income Statement'!F28/1000000 -> 22.111489 | E13: ='Income Statement'!G28/1000000 -> 30.29455 | F13: ='Income Statement'!H28/1000000 -> 43.840048 | G13: ='Income Statement'!I28/1000000 -> 35.941706
B14: EBITDA margin | C14: ='Income Statement'!E29 -> 0.065572516 | D14: ='Income Statement'!F29 -> 0.44474259 | E14: ='Income Statement'!G29 -> 0.45343317 | F14: ='Income Statement'!H29 -> 0.52781438 | G14: ='Income Statement'!I29 -> 0.47577362 | I14: Value of the project
B15: Depreciation and interest | C15: =-('Income Statement'!E30+'Income Statement'!E32)/1000000 -> 5.8464117 | D15: =-('Income Statement'!F30+'Income Statement'!F32)/1000000 -> 5.8464117 | E15: =-('Income Statement'!G30+'Income Statement'!G32)/1000000 -> 5.3595281 | F15: =-('Income Statement'!H30+'Income Statement'!H32)/1000000 -> 4.6726445 | G15: =-('Income Statement'!I30+'Income Statement'!I32)/1000000 -> 3.9857608 | I15: Discount rate = WACC | J15: ='Investment Analysis'!D16 -> 0.14633594
B16: Net profit after tax | C16: ='Income Statement'!E35/1000000 -> -5.0542957 | D16: ='Income Statement'!F35/1000000 -> 13.182113 | E16: ='Income Statement'!G35/1000000 -> 18.077891 | F16: ='Income Statement'!H35/1000000 -> 28.396368 | G16: ='Income Statement'!I35/1000000 -> 23.16806 | I16: NPV incl. recovery value (BDT million) | J16: ='Investment Analysis'!D44/1000000 -> 30.651569
B17: Net profit margin | C17: ='Income Statement'!E36 -> -0.41840196 | D17: ='Income Statement'!F36 -> 0.2651403 | E17: ='Income Statement'!G36 -> 0.27058053 | F17: ='Income Statement'!H36 -> 0.34187944 | G17: ='Income Statement'!I36 -> 0.30668416 | I17: IRR incl. recovery value | J17: ='Investment Analysis'!D45 -> 0.29333206
B18: Return on equity | C18: =Ratios!E12 -> -0.22248772 | D18: =Ratios!F12 -> 0.36903344 | E18: =Ratios!G12 -> 0.42088783 | F18: =Ratios!H12 -> 0.52285371 | G18: =Ratios!I12 -> 0.36440617 | I18: Payback period | J18: ='Investment Analysis'!D42 -> 3.6618855
B19: Profit before tax by unit, Year 4 | I19: Discounted payback period | J19: ='Investment Analysis'!D43 -> 4.7764457
B20: Hatchery | C20: ='Segment Analysis'!H38/1000000 -> 27.90562 | I20: Profitability index | J20: ='Investment Analysis'!D41 -> 1.0675609
B21: Farming | C21: ='Segment Analysis'!H41/1000000 -> 11.261784 | I21: NPV, 5 years only (BDT million) | J21: ='Investment Analysis'!D38/1000000 -> 3.093767
B22: COGS = feed, stock, hormone and factory overheads. Operating expenses = administrative, marketing, selling and distribution.
I23: Owner
I24: Total invested by the owner (BDT million) | J24: ='Owner Returns'!D29/1000000 -> 27.771485
B25: CASH FLOW STATEMENT | I25: Dividends in 5 years (BDT million) | J25: ='Owner Returns'!D30/1000000 -> 41.964048
B26: BDT million | C26: =C6 -> FY2026-27 | D26: =D6 -> FY2027-28 | E26: =E6 -> FY2028-29 | F26: =F6 -> FY2029-30 | G26: =G6 -> FY2030-31 | I26: Dividends as % of owner investment | J26: ='Owner Returns'!D31 -> 1.511048
B27: Cash flow from operations | C27: ='Cash Flow'!E13/1000000 -> -4.3753639 | D27: ='Cash Flow'!F13/1000000 -> 10.905687 | E27: ='Cash Flow'!G13/1000000 -> 18.785959 | F27: ='Cash Flow'!H13/1000000 -> 30.180743 | G27: ='Cash Flow'!I13/1000000 -> 26.896558 | I27: Owner IRR incl. book equity at end of Year 5 | J27: ='Owner Returns'!D35 -> 0.34750685
B28: Cash flow from investing | C28: ='Cash Flow'!E17/1000000 -> 0 | D28: ='Cash Flow'!F17/1000000 -> -5.003 | E28: ='Cash Flow'!G17/1000000 -> 0 | F28: ='Cash Flow'!H17/1000000 -> 0 | G28: ='Cash Flow'!I17/1000000 -> 0
B29: Cash flow from financing | C29: ='Cash Flow'!E24/1000000 -> 2.4554185 | D29: ='Cash Flow'!F24/1000000 -> -5.9026866 | E29: ='Cash Flow'!G24/1000000 -> -16.570765 | F29: ='Cash Flow'!H24/1000000 -> -22.761851 | G29: ='Cash Flow'!I24/1000000 -> -19.624866 | I29: Lender view
B30: Net change in cash | C30: ='Cash Flow'!E28/1000000 -> -1.9199453 | D30: ='Cash Flow'!F28/1000000 -> 0 | E30: ='Cash Flow'!G28/1000000 -> 2.215194 | F30: ='Cash Flow'!H28/1000000 -> 7.4188926 | G30: ='Cash Flow'!I28/1000000 -> 7.2716915 | I30: Minimum Debt Service Coverage Ratio (DSCR) | J30: ='Loan Analysis'!E35 -> 1.6116528
B31: Closing cash | C31: ='Cash Flow'!E30/1000000 -> 0.5 | D31: ='Cash Flow'!F30/1000000 -> 0.5 | E31: ='Cash Flow'!G30/1000000 -> 2.715194 | F31: ='Cash Flow'!H30/1000000 -> 10.134087 | G31: ='Cash Flow'!I30/1000000 -> 17.405778 | I31: Average Debt Service Coverage Ratio (DSCR) | J31: ='Loan Analysis'!E36 -> 3.2594516
I32: Minimum interest cover | J32: ='Loan Analysis'!E37 -> 6.9198811
B33: WORKING CAPITAL | I33: Collateral cover at drawdown | J33: ='Loan Analysis'!E39 -> 1.2997812
B34: BDT million | C34: =C6 -> FY2026-27 | D34: =D6 -> FY2027-28 | E34: =E6 -> FY2028-29 | F34: =F6 -> FY2029-30 | G34: =G6 -> FY2030-31 | I34: Lending benchmarks met | J34: ='Loan Analysis'!D43&" of "&'Loan Analysis'!E43 -> 8 of 8
B35: Net working capital | C35: ='Working Capital'!E15/1000000 -> 2.4199453 | D35: ='Working Capital'!F15/1000000 -> 7.7952486 | E35: ='Working Capital'!G15/1000000 -> 10.386058 | F35: ='Working Capital'!H15/1000000 -> 11.900559 | G35: ='Working Capital'!I15/1000000 -> 11.470939
B36: Net working capital as % of revenue | C36: ='Working Capital'!E17 -> 0.2003266 | D36: ='Working Capital'!F17 -> 0.15679084 | E36: ='Working Capital'!G17 -> 0.15545315 | F36: ='Working Capital'!H17 -> 0.14327736 | G36: ='Working Capital'!I17 -> 0.15184505 | I36: ='Investment Analysis'!D46 -> ACCEPT: NPV is positive and IRR is above the required return
B37: Cash conversion cycle (days) | C37: ='Working Capital'!E24 -> 90 | D37: ='Working Capital'!F24 -> 90 | E37: ='Working Capital'!G24 -> 90 | F37: ='Working Capital'!H24 -> 90 | G37: ='Working Capital'!I24 -> 90
I38: ='Loan Analysis'!B44 -> Result: the project meets all 8 lending benchmarks in the Base case.
B39: CASH FLOW GENERATION
B40: BDT million (outflows in brackets) | C40: =C6 -> FY2026-27 | D40: =D6 -> FY2027-28 | E40: =E6 -> FY2028-29 | F40: =F6 -> FY2029-30 | G40: =G6 -> FY2030-31
B41: EBITDA | C41: ='Cash Flow'!E37/1000000 -> 0.79211599 | D41: ='Cash Flow'!F37/1000000 -> 22.111489 | E41: ='Cash Flow'!G37/1000000 -> 30.29455 | F41: ='Cash Flow'!H37/1000000 -> 43.840048 | G41: ='Cash Flow'!I37/1000000 -> 35.941706
B42: Interest | C42: ='Cash Flow'!E38/1000000 -> -2.7475345 | D42: ='Cash Flow'!F38/1000000 -> -2.7475345 | E42: ='Cash Flow'!G38/1000000 -> -2.0606509 | F42: ='Cash Flow'!H38/1000000 -> -1.3737673 | G42: ='Cash Flow'!I38/1000000 -> -0.68688363
B43: Income tax | C43: ='Cash Flow'!E39/1000000 -> 0 | D43: ='Cash Flow'!F39/1000000 -> -3.0829651 | E43: ='Cash Flow'!G39/1000000 -> -6.857131 | F43: ='Cash Flow'!H39/1000000 -> -10.771036 | G43: ='Cash Flow'!I39/1000000 -> -8.7878848
B44: Working capital changes
B45: Inventory | C45: ='Cash Flow'!E41/1000000 -> -2.1406029 | D45: ='Cash Flow'!F41/1000000 -> -3.4227152 | E45: ='Cash Flow'!G41/1000000 -> -1.7787344 | F45: ='Cash Flow'!H41/1000000 -> -0.26856249 | G45: ='Cash Flow'!I41/1000000 -> -0.28218454
B46: Receivable | C46: ='Cash Flow'!E42/1000000 -> -0.99287671 | D46: ='Cash Flow'!F42/1000000 -> -3.0934932 | E46: ='Cash Flow'!G42/1000000 -> -1.4049863 | F46: ='Cash Flow'!H42/1000000 -> -1.3354598 | G46: ='Cash Flow'!I42/1000000 -> 0.61774359
B47: Payable | C47: ='Cash Flow'!E43/1000000 -> 0.7135343 | D47: ='Cash Flow'!F43/1000000 -> 1.1409051 | E47: ='Cash Flow'!G43/1000000 -> 0.59291147 | F47: ='Cash Flow'!H43/1000000 -> 0.089520829 | G47: ='Cash Flow'!I43/1000000 -> 0.094061514
B48: Capex | C48: ='Cash Flow'!E44/1000000 -> 0 | D48: ='Cash Flow'!F44/1000000 -> -5.003 | E48: ='Cash Flow'!G44/1000000 -> 0 | F48: ='Cash Flow'!H44/1000000 -> 0 | G48: ='Cash Flow'!I44/1000000 -> 0
B49: Net cash generated | C49: =SUM(C41:C48) -> -4.3753639 | D49: =SUM(D41:D48) -> 5.9026866 | E49: =SUM(E41:E48) -> 18.785959 | F49: =SUM(F41:F48) -> 30.180743 | G49: =SUM(G41:G48) -> 26.896558
B50: Before loan repayment, owner funding and dividends. Details are on the Cash Flow sheet.
B86: SHEET GUIDE (click a name to open it)
B87: Assumptions | I87: Balance Sheet
B88: Farming | I88: Segment Analysis
B89: Hatchery | I89: Investment Analysis
B90: FA Schedule | I90: Owner Returns
B91: Operations | I91: Loan Analysis
B92: Working Capital | I92: Ratios
B93: Funding | I93: Scenarios and Risk
B94: Income Statement | I94: Sensitivity and Break-even
B95: Cash Flow | I95: Checks

Sheet Assumptions
B1: Assumptions
B2: Inputs are the blue cells on this sheet and on the Farming, Hatchery, Operations and FA Schedule sheets.
B4: 1. General
B5: Company | C5: text | D5: Sample Aqua Ltd. | H5: Fish farming and hatchery project (one site: farming and hatchery)
B6: Currency | C6: text | D6: Bangladesh Taka (BDT)
B7: First financial year starts in | C7: year | D7: 2026 | H7: Year 1 = FY2026-27
B9: 2. Scenario selector
B10: Active scenario (1 Base, 2 Downside, 3 Upside) | C10: 1-3 | D10: 1 | H10: Change this one cell and the whole model re-runs
B11: Active scenario name | C11: text | D11: =CHOOSE(D10,"Base case","Downside case","Upside case") -> Base case
B13: Scenario factor | C13: Unit | D13: Base | E13: Downside | F13: Upside | G13: Active
B14: Selling price factor | C14: x | D14: 1 | E14: 0.9 | F14: 1.05 | G14: =CHOOSE($D$10,D14,E14,F14) -> 1
B15: Yield / volume factor | C15: x | D15: 1 | E15: 0.85 | F15: 1 | G15: =CHOOSE($D$10,D15,E15,F15) -> 1
B16: Feed price factor | C16: x | D16: 1 | E16: 1.1 | F16: 0.95 | G16: =CHOOSE($D$10,D16,E16,F16) -> 1
B17: Capital cost factor (land excluded) | C17: x | D17: 1 | E17: 1.1 | F17: 1 | G17: =CHOOSE($D$10,D17,E17,F17) -> 1
B18: Interest rate add-on | C18: pp | D18: 0 | E18: 0.02 | F18: 0 | G18: =CHOOSE($D$10,D18,E18,F18) -> 0
B20: 3. Yearly price and cost increases (Year 1 is the base year)
B21: Selling price increase per year: fish, fry and broodfish | C21: % a year | D21: 0.05
B22: Feed price increase per year | C22: % a year | D22: 0.05
B23: Salary increase per year | C23: % a year | D23: 0.05
B24: Two festival bonus equivalent to one months gross salary
B25: Administrative and other fixed cost increase per year | C25: % a year | D25: 0.1
B26: Fuel cost increase per year | C26: % a year | D26: 0.1
B27: Other operating cost increase per year | C27: % a year | D27: 0.05 | H27: Lime, entertainment, conveyance, parcelling materials, electricity, telephone and labour
B29: Selling price plan (BDT per unit) | C29: Unit | D29: Year 1 | E29: Increase a year | F29: Year 5
B30: Tilapia (grow-out fish) | C30: Tk per kg | D30: =Farming!C58 -> 110 | E30: =$D$21 -> 0.05 | F30: =D30*(1+E30)^4 -> 133.70569
B31: Carp (grow-out fish) | C31: Tk per kg | D31: =Farming!C59 -> 180 | E31: =$D$21 -> 0.05 | F31: =D31*(1+E31)^4 -> 218.79112
B32: Tilapia fry | C32: Tk per piece | D32: =Hatchery!C52 -> 0.8 | E32: =$D$21 -> 0.05 | F32: =D32*(1+E32)^4 -> 0.972405
B33: Carp fry | C33: Tk per kg | D33: =Hatchery!C53 -> 3500 | E33: =$D$21 -> 0.05 | F33: =D33*(1+E33)^4 -> 4254.2719
B34: Tilapia broodfish | C34: Tk per kg | D34: =Hatchery!C54 -> 150 | E34: =$D$21 -> 0.05 | F34: =D34*(1+E34)^4 -> 182.32594
B35: Carp broodfish | C35: Tk per kg | D35: =Hatchery!C55 -> 300 | E35: =$D$21 -> 0.05 | F35: =D35*(1+E35)^4 -> 364.65188
B36: Feed price (farming) | C36: Tk per kg | D36: =Farming!C50 -> 40 | E36: =$D$22 -> 0.05 | F36: =D36*(1+E36)^4 -> 48.62025
B38: 4. Tax, financing and dividends
B39: Corporate income tax rate | C39: % | D39: 0.275 | H39: Current rate used for this project: 27.5%. Tax losses are carried forward
B40: Interest rate on the term loan | C40: % | D40: 0.12 | H40: Interest charged on the opening loan balance
B41: Term loan as % of fixed assets cost | C41: % | D41: 0.5 | H41: Bank finances this share of the Year 0 fixed assets; the owner funds the rest plus the working capital reserve
B42: Loan tenor (including grace) | C42: years | D42: 5
B43: Grace period (interest only) | C43: years | D43: 1 | H43: No principal repaid in the grace years
B44: Minimum cash balance | C44: BDT | D44: 500000 | H44: If cash would fall below this, the owner injects the shortfall
B45: Dividend payout ratio | C45: % of profit | D45: 0.6 | H45: Paid only from profit after tax and only if the cash balance stays above the minimum
B47: 5. Discount rate (WACC) and bank benchmarks
B48: Cost of equity (owner required return) | C48: % | D48: 0.2
B49: Discount rate = WACC (formula, from Investment Analysis) | C49: % | D49: ='Investment Analysis'!D16 -> 0.14633594 | H49: Cost of debt after tax = loan interest x (1 - tax rate)
B50: Minimum Debt Service Coverage Ratio, DSCR (loan covenant) | C50: x | D50: 1.25 | H50: Typical bank requirement: cash available for debt service / (interest + principal)
B51: Minimum interest cover (EBIT / interest) | C51: x | D51: 2
B52: Maximum debt to equity | C52: x | D52: 2
B53: Minimum collateral cover (security / loan) | C53: x | D53: 1.25
B54: Minimum current ratio | C54: x | D54: 1.2
B55: Minimum owner contribution | C55: % of project cost | D55: 0.3
B56: Forced-sale discount on security | C56: % | D56: 0.25 | H56: Land, ponds and buildings are valued at cost less this discount
B58: 6. Operating assumptions
B59: Hatchery share of common cost, depreciation and interest | C59: % | D59: 0.7 | H59: 70% hatchery and 30% farming
B60: Farming share (100% less hatchery share) | C60: % | D60: =1-D59 -> 0.3
B61: Marketing expense | C61: % of hatchery sales | D61: 0.02 | H61: Share of hatchery sales
B62: Selling expense | C62: % of hatchery sales | D62: 0.08 | H62: Share of hatchery sales
B63: Distribution expense (hatchery), per year | C63: BDT | D63: 500000 | H63: Kept flat
B64: Receivable days | C64: days of sales | D64: 30 | H64: Working Capital tab. Receivables = revenue x days / 365
B65: Inventory days | C65: days of cost of sales | D65: 90 | H65: Feed, fingerlings and stock on hand
B66: Payable days | C66: days of cost of sales | D66: 30 | H66: Supplier credit
B67: Year 2 construction | C67: BDT | D67: 2000000 | H67: Construction cost in Year 2
B68: Year 2 land purchase: quantity | C68: decimal | D68: 143 | H68: Land bought in Year 2
B69: Year 2 land purchase: rate | C69: BDT per decimal | D69: 21000 | H69: Land bought in Year 2
B70: Tilapia broodfish stock | C70: pieces | D70: =Hatchery!B28 -> 60000 | H70: From the Hatchery sheet. All broodfish are sold once, in Year 4
B71: Carp broodfish stock | C71: pieces | D71: =Hatchery!B29 -> 5000 | H71: From the Hatchery sheet
B72: Tilapia size at sale | C72: kg per piece | D72: 0.5 | H72: Average weight after 3 years
B73: Carp size at sale | C73: kg per piece | D73: 5 | H73: Average weight after 3 years
B74: Broodfish mortality before sale | C74: % | D74: 0.2 | H74: Share of the stock lost before the Year 4 sale
B75: Tilapia broodfish sold in Year 4 | C75: kg | D75: =D70*D72*(1-D74) -> 24000 | H75: Pieces x size x (1 - mortality)
B76: Carp broodfish sold in Year 4 | C76: kg | D76: =D71*D73*(1-D74) -> 20000 | H76: Pieces x size x (1 - mortality)
B77: Depreciation rate: buildings | C77: % p.a. | D77: 0.1 | H77: Straight line on cost, starting the year after purchase
B78: Depreciation rate: overhead tank | C78: % p.a. | D78: 0.2
B79: Depreciation rate: equipment | C79: % p.a. | D79: 0.2
B80: Depreciation rate: vehicles | C80: % p.a. | D80: 0.2
B81: Depreciation rate: furniture and fixtures | C81: % p.a. | D81: 0.2
B82: Land value change: value recovered at the end of Year 5 | C82: % | D82: -0.1 | H82: Land is taken 10% below its cost when the project value is recovered. Enter 0% for no reduction
B83: Recovery value at end of Year 5: land, ponds and buildings | C83: % of cost | D83: 1 | H83: Land is further adjusted by the line above
B84: Recovery value: furniture and fixtures | C84: % of cost | D84: 0.05
B85: Recovery value: vehicles | C85: % of cost | D85: 0.1
B86: Recovery value: overhead tank | C86: % of cost | D86: 0
B87: Recovery value: equipment | C87: % of cost | D87: 0.05

Sheet Farming
D2: FISH PROJECT - Farming
D3: LAND AREA : 600 DECIMAL
I4: Fish Housing: 600 decimal x 250 pcs = 150,000 pcs
A5: Fish production and Feed Requirement Chart:
A6: FISH HOUSING: 150,000 PCS X 3 BATCH + 30% EXTRA = 585,000 PCS
A7: FINGERLING RELEASE DATE | B7: 2026 - 2027 | E7: 2027 - 2028 | H7: 2028 - 2029 | K7: 2029 - 2030
B8: Rearing Period | C8: Feed Requirement (KG) | D8: Fish Production (Kg) | E8: Rearing Period | F8: Feed Requirement (KG) | G8: Fish Production (Kg) | H8: Rearing Period | I8: Feed Requirement (KG) | J8: Fish Production (Kg) | K8: Rearing Period | L8: Feed Requirement (KG) | M8: Fish Production (Kg)
A9: 01.04.27 | B9: 01.04.27~15.07.27 | C9: =E29 -> 72500 | D9: =D29 -> 50000
A10: 01.07.27 | E10: 01.07.27~15.11.27 | F10: =E29 -> 72500 | G10: =D29 -> 50000
A11: 01.10.27 | E11: 01.10.27~31.03.28 | F11: =E29 -> 72500 | G11: =D29 -> 50000
A13: 01.04.28 | E13: 01.04.28~15.07.28 | F13: =E29 -> 72500 | G13: =D29 -> 50000
A14: 01.07.28 | H14: 01.07.28~15.11.28 | I14: =E29 -> 72500 | J14: =D29 -> 50000
A15: 01.10.28 | H15: 01.10.28~31.03.29 | I15: =E29 -> 72500 | J15: =D29 -> 50000
A17: 01.04.29 | H17: 01.04.29~15.07.29 | I17: =E29 -> 72500 | J17: =D29 -> 50000
A18: 01.07.29 | K18: 01.07.29~15.11.29 | L18: =E29 -> 72500 | M18: =D29 -> 50000
A19: 01.10.29 | K19: 01.10.29~31.03.30 | L19: =E29 -> 72500 | M19: =D29 -> 50000
A21: 01.04.30 | K21: 01.04.30~15.07.30 | L21: =E29 -> 72500 | M21: =D29 -> 50000
C22: =SUM(C9:C21) -> 72500 | D22: =SUM(D9:D21) -> 50000 | F22: =SUM(F9:F21) -> 217500 | G22: =SUM(G9:G21) -> 150000 | I22: =SUM(I9:I21) -> 217500 | J22: =SUM(J9:J21) -> 150000 | L22: =SUM(L9:L21) -> 217500 | M22: =SUM(M9:M21) -> 150000
A25: Feed Requirement in per cycle
A26: Fish Name | B26: Fingerling Qty (pcs) per cycle | C26: FCR | D26: Fish Production (kg) | E26: Feed Requirement | F26: ="Note: "&D26 -> Note: Fish Production (kg)
A27: Talapia | B27: 100000 | C27: 1.3 | D27: =B27/4 -> 25000 | E27: =C27*D27 -> 32500 | F27: If we provide all facilities, excepted production will be found.
A28: Carp | B28: 50000 | C28: 1.6 | D28: =B28/2 -> 25000 | E28: =C28*D28 -> 40000 | F28: If we provide all facilities, excepted production will be found.
B29: =SUM(B27:B28) -> 150000 | D29: =SUM(D27:D28) -> 50000 | E29: =SUM(E27:E28) -> 72500
A31: Feed Requirement circle wise
A32: Name of Feed | E32: Qty
A33: Nursery Feed | E33: =E29*5% -> 3625
A34: Starter Feed | E34: =E29*15% -> 10875
A35: Grower Feed | E35: =E29*80% -> 58000
A36: Total Feed per circle | E36: =SUM(E33:E35) -> 72500 | F36: 3 | G36: =E36*F36 -> 217500
A38: Feed Requirement Year Wise: | E38: Qty (kg)
A39: Name of Feed | E39: 2026 - 2027 | F39: 2027 - 2028 | G39: 2028 - 2029 | H39: 2029 - 2030
A40: Nursery Feed | E40: =C22*5% -> 3625 | F40: =F22*5% -> 10875 | G40: =I22*5% -> 10875 | H40: =L22*5% -> 10875
A41: Stater Feed | E41: =C22*15% -> 10875 | F41: =F22*15% -> 32625 | G41: =I22*15% -> 32625 | H41: =L22*15% -> 32625
A42: Grower Feed | E42: =C22*80% -> 58000 | F42: =F22*80% -> 174000 | G42: =I22*80% -> 174000 | H42: =L22*80% -> 174000
A43: Total Feed per circle | E43: =SUM(E40:E42) -> 72500 | F43: =SUM(F40:F42) -> 217500 | G43: =SUM(G40:G42) -> 217500 | H43: =SUM(H40:H42) -> 217500
A46: Variable cost estimation:
A47: Particulars | B47: 2026 - 2027 | E47: 2027 - 2028 | H47: 2028 - 2029 | K47: 2029 - 2030 | N47: 2030 - 2031
B48: Qty | C48: Unit cost | D48: Amt (Tk.) | E48: Qty | F48: Unit cost | G48: Amt (Tk.) | H48: Qty | I48: Unit cost | J48: Amt (Tk.) | K48: Qty | L48: Unit cost | M48: Amt (Tk.) | N48: Qty | O48: Unit cost | P48: Amt (Tk.)
A49: Fry / Fingerling | B49: =B29+(B29*$D$52) -> 195000 | C49: =D49/B49 -> 4 | D49: =B53*($B$27*$B$52+$B$28*$C$52)*(1+$D$52) -> 780000 | E49: =(B29*3)+(B29*3)*$D$52 -> 585000 | F49: =G49/E49 -> 2 | G49: =E53*($B$27*$B$52+$B$28*$C$52)*(1+$D$52) -> 1170000 | H49: =E49 -> 585000 | I49: =J49/H49 -> 2 | J49: =H53*($B$27*$B$52+$B$28*$C$52)*(1+$D$52) -> 1170000 | K49: =H49 -> 585000 | L49: =M49/K49 -> 2 | M49: =K53*($B$27*$B$52+$B$28*$C$52)*(1+$D$52) -> 1170000 | N49: =K49 -> 585000 | O49: =P49/N49 -> 2 | P49: =N53*($B$27*$B$52+$B$28*$C$52)*(1+$D$52) -> 1170000
A50: Feed | B50: =E43 -> 72500 | C50: 40 | D50: =B50*C50 -> 2900000 | E50: =F43 -> 217500 | F50: =C50*(1+Assumptions!$D$22) -> 42 | G50: =E50*F50 -> 9135000 | H50: =G43 -> 217500 | I50: =F50*(1+Assumptions!$D$22) -> 44.1 | J50: =H50*I50 -> 9591750 | K50: =H43 -> 217500 | L50: =I50*(1+Assumptions!$D$22) -> 46.305 | M50: =K50*L50 -> 10071338 | N50: =K50 -> 217500 | O50: =L50*(1+Assumptions!$D$22) -> 48.62025 | P50: =N50*O50 -> 10574904
A51: Total | D51: =SUM(D49:D50) -> 3680000 | G51: =SUM(G49:G50) -> 10305000 | J51: =SUM(J49:J50) -> 10761750 | M51: =SUM(M49:M50) -> 11241338 | P51: =SUM(P49:P50) -> 11744904
A52: Fingerling rate (Tk per pc): Tilapia / Carp / extra stock % | B52: 1 | C52: 4 | D52: 0.3
A53: Cycles stocked in the year | B53: 2 | E53: 3 | H53: 3 | K53: 3 | N53: =K53 -> 3
A55: Revenue: selling rate rises every year (increase set on the Assumptions sheet)
A56: Particulars | B56: 2026 - 2027 | E56: 2027 - 2028 | H56: 2028 - 2029 | K56: 2029 - 2030 | N56: 2030 - 2031
B57: Qty | C57: Selling rate (Tk) | D57: Amt (Tk.) | E57: Qty | F57: Selling rate (Tk) | G57: Amt (Tk.) | H57: Qty | I57: Selling rate (Tk) | J57: Amt (Tk.) | K57: Qty | L57: Selling rate (Tk) | M57: Amt (Tk.) | N57: Qty | O57: Selling rate (Tk) | P57: Amt (Tk.)
A58: Tilapia (kg) | B58: =I74 -> 8000 | C58: 110 | D58: =B58*C58 -> 880000 | E58: =V74 -> 75000 | F58: =C58*(1+Assumptions!$D$21) -> 115.5 | G58: =E58*F58 -> 8662500 | H58: =AI74 -> 75000 | I58: =F58*(1+Assumptions!$D$21) -> 121.275 | J58: =H58*I58 -> 9095625 | K58: =AV74 -> 75000 | L58: =I58*(1+Assumptions!$D$21) -> 127.33875 | M58: =K58*L58 -> 9550406.2 | N58: =K58 -> 75000 | O58: =L58*(1+Assumptions!$D$21) -> 133.70569 | P58: =N58*O58 -> 10027927
A59: Carp (kg) | B59: =I75 -> 10000 | C59: 180 | D59: =B59*C59 -> 1800000 | E59: =V75 -> 75000 | F59: =C59*(1+Assumptions!$D$21) -> 189 | G59: =E59*F59 -> 14175000 | H59: =AI75 -> 75000 | I59: =F59*(1+Assumptions!$D$21) -> 198.45 | J59: =H59*I59 -> 14883750 | K59: =AV75 -> 75000 | L59: =I59*(1+Assumptions!$D$21) -> 208.3725 | M59: =K59*L59 -> 15627938 | N59: =K59 -> 75000 | O59: =L59*(1+Assumptions!$D$21) -> 218.79113 | P59: =N59*O59 -> 16409334
A60: Total revenue | D60: =SUM(D58:D59) -> 2680000 | G60: =SUM(G58:G59) -> 22837500 | J60: =SUM(J58:J59) -> 23979375 | M60: =SUM(M58:M59) -> 25178344 | P60: =SUM(P58:P59) -> 26437261
A62: Year 1 is a part year (harvest in Jan-Mar 2027 only); from Year 2 there are three harvests a year. Quantities come from the harvest calendar below. Year 5 repeats the Year 4 quantity at the Year 5 rate.
A64: Month-wise revenue (Tk) = harvest kg x selling rate of that year
A65: Item | C65: 2026 - 2027 | J65: 2027 - 2028 | W65: 2028 - 2029 | AJ65: 2029 - 2030
C66: 46388 | D66: 46419 | E66: 46447 | F66: 46478 | G66: 46508 | H66: 46539 | I66: Total | J66: 46569 | K66: 46600 | L66: 46631 | M66: 46661 | N66: 46692 | O66: 46722 | P66: 46753 | Q66: 46784 | R66: 46813 | S66: 46844 | T66: 46874 | U66: 46905 | V66: Total | W66: 46935 | X66: 46966 | Y66: 46997 | Z66: 47027 | AA66: 47058 | AB66: 47088 | AC66: 47119 | AD66: 47150 | AE66: 47178 | AF66: 47209 | AG66: 47239 | AH66: 47270 | AI66: Total | AJ66: 47300 | AK66: 47331 | AL66: 47362 | AM66: 47392 | AN66: 47423 | AO66: 47453 | AP66: 47484 | AQ66: 47515 | AR66: 47543 | AS66: 47574 | AT66: 47604 | AU66: 47635 | AV66: Total
A67: Tilapia (Tk.) | B67: Tk | C67: =C74*$C$58 -> 330000 | D67: =D74*$C$58 -> 330000 | E67: =E74*$C$58 -> 220000 | I67: =SUM(C67:H67) -> 880000 | J67: =J74*$F$58 -> 2887500 | N67: =N74*$F$58 -> 2887500 | R67: =R74*$F$58 -> 2887500 | V67: =SUM(J67:U67) -> 8662500 | W67: =W74*$I$58 -> 3031875 | AA67: =AA74*$I$58 -> 3031875 | AE67: =AE74*$I$58 -> 3031875 | AI67: =SUM(W67:AH67) -> 9095625 | AJ67: =AJ74*$L$58 -> 3183468.8 | AN67: =AN74*$L$58 -> 3183468.8 | AR67: =AR74*$L$58 -> 3183468.8 | AV67: =SUM(AJ67:AU67) -> 9550406.2
A68: Carp (Tk.) | B68: Tk | D68: =D75*$C$59 -> 900000 | E68: =E75*$C$59 -> 900000 | I68: =SUM(C68:H68) -> 1800000 | J68: =J75*$F$59 -> 4725000 | N68: =N75*$F$59 -> 4725000 | R68: =R75*$F$59 -> 4725000 | V68: =SUM(J68:U68) -> 14175000 | W68: =W75*$I$59 -> 4961250 | AA68: =AA75*$I$59 -> 4961250 | AE68: =AE75*$I$59 -> 4961250 | AI68: =SUM(W68:AH68) -> 14883750 | AJ68: =AJ75*$L$59 -> 5209312.5 | AN68: =AN75*$L$59 -> 5209312.5 | AR68: =AR75*$L$59 -> 5209312.5 | AV68: =SUM(AJ68:AU68) -> 15627938
A69: Farming total (Tk.) | C69: =C67+C68 -> 330000 | D69: =D67+D68 -> 1230000 | E69: =E67+E68 -> 1120000 | F69: =F67+F68 -> 0 | G69: =G67+G68 -> 0 | H69: =H67+H68 -> 0 | I69: =I67+I68 -> 2680000 | J69: =J67+J68 -> 7612500 | ... AV69: =AV67+AV68 -> 25178344
A71: Harvest calendar (kg)
A72: Item | C72: 2026 - 2027 | J72: 2027 - 2028 | W72: 2028 - 2029 | AJ72: 2029 - 2030
C73: 46388 | D73: 46419 | E73: 46447 | F73: 46478 | G73: 46508 | H73: 46539 | I73: Total | J73: 46569 | K73: 46600 | L73: 46631 | M73: 46661 | N73: 46692 | O73: 46722 | P73: 46753 | Q73: 46784 | R73: 46813 | S73: 46844 | T73: 46874 | U73: 46905 | V73: Total | W73: 46935 | X73: 46966 | Y73: 46997 | Z73: 47027 | AA73: 47058 | AB73: 47088 | AC73: 47119 | AD73: 47150 | AE73: 47178 | AF73: 47209 | AG73: 47239 | AH73: 47270 | AI73: Total | AJ73: 47300 | AK73: 47331 | AL73: 47362 | AM73: 47392 | AN73: 47423 | AO73: 47453 | AP73: 47484 | AQ73: 47515 | AR73: 47543 | AS73: 47574 | AT73: 47604 | AU73: 47635 | AV73: Total
A74: Tilapia (kg) | B74: kg | C74: =3000 -> 3000 | D74: =3000 -> 3000 | E74: =2000 -> 2000 | I74: =SUM(C74:H74) -> 8000 | J74: =D27 -> 25000 | N74: =J74 -> 25000 | R74: =J74 -> 25000 | V74: =SUM(J74:U74) -> 75000 | W74: =J74 -> 25000 | AA74: =J74 -> 25000 | AE74: =J74 -> 25000 | AI74: =SUM(W74:AH74) -> 75000 | AJ74: =J74 -> 25000 | AN74: =J74 -> 25000 | AR74: =J74 -> 25000 | AV74: =SUM(AJ74:AU74) -> 75000
A75: Carp (kg) | B75: kg | D75: 5000 | E75: 5000 | I75: =SUM(C75:H75) -> 10000 | J75: =D28 -> 25000 | N75: =J75 -> 25000 | R75: =J75 -> 25000 | V75: =SUM(J75:U75) -> 75000 | W75: =J75 -> 25000 | AA75: =J75 -> 25000 | AE75: =J75 -> 25000 | AI75: =SUM(W75:AH75) -> 75000 | AJ75: =J75 -> 25000 | AN75: =J75 -> 25000 | AR75: =J75 -> 25000 | AV75: =SUM(AJ75:AU75) -> 75000
A76: Farming total (kg) | C76: =C74+C75 -> 3000 | D76: =D74+D75 -> 8000 | E76: =E74+E75 -> 7000 | F76: =F74+F75 -> 0 | G76: =G74+G75 -> 0 | H76: =H74+H75 -> 0 | I76: =I74+I75 -> 18000 | J76: =J74+J75 -> 50000 | ... AV76: =AV74+AV75 -> 150000
A78: Colour code: blue on yellow = input, black = formula.

Sheet Hatchery
D2: FISH PROJECT - Hatchery
D3: Hatchery Shed: 2 Shed
A4: Tilapia Fry
A5: EGG COLLECTION DATE | B5: 2026 - 2027 | D5: 2027 - 2028 | F5: 2028 - 2029 | H5: 2029 - 2030
B6: Rearing Period | C6: Fish Fry Production (Pc) | D6: Rearing Period | E6: Fish Fry Production (Pc) | F6: Rearing Period | G6: Fish Fry Production (Pc) | H6: Rearing Period | I6: Fish Fry Production (Pc)
D7: 01.07.27~31.07.27 | E7: 4000000 | F7: 01.07.28~31.07.28 | G7: =E7*1.5 -> 6000000 | H7: 01.07.29~31.07.29 | I7: =E7*2 -> 8000000
D8: 01.08.27~31.08.27 | E8: 4000000 | F8: 01.08.28~31.08.28 | G8: =E8*1.5 -> 6000000 | H8: 01.08.29~31.08.29 | I8: =E8*2 -> 8000000
D9: 01.09.27~30.09.27 | E9: 2000000 | F9: 01.09.28~30.09.28 | G9: =E9*1.5 -> 3000000 | H9: 01.09.29~30.09.29 | I9: =E9*2 -> 4000000
A10: 01.04.27 | B10: 01.04.27~30.04.27 | C10: 2000000 | D10: 01.04.28~30.04.28 | E10: =C10*1.5 -> 3000000 | F10: 01.04.29~30.04.29 | G10: =C10*2 -> 4000000 | H10: 01.04.30~30.04.30 | I10: =G10 -> 4000000
A11: 01.05.27 | B11: 01.05.27~31.05.27 | C11: 4000000 | D11: 01.05.28~31.05.28 | E11: =C11*1.5 -> 6000000 | F11: 01.05.29~31.05.29 | G11: =C11*2 -> 8000000 | H11: 01.05.30~31.05.30 | I11: =G11 -> 8000000
A12: 01.06.27 | B12: 01.06.27~30.06.27 | C12: 4000000 | D12: 01.06.28~30.06.28 | E12: =C12*1.5 -> 6000000 | F12: 01.06.29~30.06.29 | G12: =C12*2 -> 8000000 | H12: 01.06.30~30.06.30 | I12: =G12 -> 8000000
A13: Total | C13: =SUM(C7:C12) -> 10000000 | E13: =SUM(E7:E12) -> 25000000 | G13: =SUM(G7:G12) -> 35000000 | I13: =SUM(I7:I12) -> 40000000
A16: Carp Fry
A17: EGG COLLECTION DATE | B17: Year 2027 | D17: Year 2028 | F17: Year 2029
B18: Rearing Period | C18: Fish Fry Production (Kg) | D18: Rearing Period | E18: Fish Fry Production (Pc) | F18: Rearing Period | G18: Fish Fry Production (Pc)
A19: 01.03.27 | B19: 01.03.27~31.12.27 | C19: 1000 | E19: =C19*2.5 -> 2500 | G19: =E19*1.6 -> 4000
A21: Total | C21: =SUM(C19:C20) -> 1000 | E21: =SUM(E19:E20) -> 2500 | G21: =SUM(G19:G20) -> 4000
A25: Feed Requirement for Tilapia
A26: Fish Name | B26: Qty (pcs) | C26: FCR | D26: Fry Production (kg) | E26: Feed Requirement | F26: Rate | G26: Amt (Tk.) | H26: ="Note: "&D26 -> Note: Fry Production (kg)
A27: Tilapia - Fry | B27: 20000000 | C27: 1 | D27: =B27/3333 -> 6000.6001 | E27: =C27*D27 -> 6000.6001 | F27: 70 | G27: =E27*F27 -> 420042 | H27: If we provide all facilities, excepted production will be found.
A28: Tilapia - Broodfish | B28: 60000 | C28: 1.3 | D28: =B28/4 -> 15000 | E28: =B28*0.25*C28 -> 19500 | F28: 40 | G28: =E28*F28 -> 780000 | H28: This fish will be sold after 3rd year on the year of 2030
A29: Carp - Broodfish | B29: 5000 | C29: 1.6 | D29: =B29*2 -> 10000 | E29: =C29*D29 -> 16000 | F29: 40 | G29: =E29*F29 -> 640000
A30: Carp - Fry | B30: 1000 | D30: =B30 -> 1000 | E30: 0 | F30: - | G30: 0 | H30: No feed is required for Carp fry
E32: =SUM(E27:E31) -> 41500.6 | G32: =SUM(G27:G31) -> 1840042
A34: Note: Cycle 5 days, 1st day brood collection, 2nd day egg collection, 3rd day egg fertilization, 4th and 5th fry rearing
A37: Variable cost estimation:
A38: Particulars | B38: 2026 - 2027 | E38: 2027 - 2028 | H38: 2028 - 2029 | K38: 2029 - 2030 | N38: 2030 - 2031
B39: Qty | C39: Unit cost | D39: Amt (Tk.) | E39: Qty | F39: Unit cost | G39: Amt (Tk.) | H39: Qty | I39: Unit cost | J39: Amt (Tk.) | K39: Qty | L39: Unit cost | M39: Amt (Tk.) | N39: Qty | O39: Unit cost | P39: Amt (Tk.)
A40: Brood Tilapia | B40: =B28 -> 60000 | C40: 2 | D40: =B40*C40 -> 120000 | E40: =B40*2.5 -> 150000 | F40: 2 | G40: =E40*F40 -> 300000 | H40: =E40*1.6 -> 240000 | I40: =F40 -> 2 | J40: =H40*I40 -> 480000 | K40: =H40 -> 240000 | L40: =I40 -> 2 | M40: =K40*L40 -> 480000 | N40: =K40 -> 240000 | O40: =L40 -> 2 | P40: =N40*O40 -> 480000
A41: Brood Carp | B41: =B29 -> 5000 | C41: 5 | D41: =B41*C41 -> 25000 | E41: =B41*2.5 -> 12500 | F41: 5 | G41: =E41*F41 -> 62500 | H41: =E41*1.6 -> 20000 | I41: =F41 -> 5 | J41: =H41*I41 -> 100000 | K41: =H41 -> 20000 | L41: =I41 -> 5 | M41: =K41*L41 -> 100000 | N41: =K41 -> 20000 | O41: =L41 -> 5 | P41: =N41*O41 -> 100000
A42: Total Brood | D42: =SUBTOTAL(9,D40:D41) -> 145000 | G42: =SUBTOTAL(9,G40:G41) -> 362500 | J42: =SUBTOTAL(9,J40:J41) -> 580000 | M42: =SUBTOTAL(9,M40:M41) -> 580000 | P42: =SUBTOTAL(9,P40:P41) -> 580000
A43: Feed | B43: =E32 -> 41500.6 | C43: =D43/B43 -> 44.33772 | D43: =G32 -> 1840042 | E43: =B43*2.5 -> 103751.5 | F43: =C43*(1+Assumptions!$D$22) -> 46.554606 | G43: =E43*F43 -> 4830110.3 | H43: =E43*1.6 -> 166002.4 | I43: =F43*(1+Assumptions!$D$22) -> 48.882337 | J43: =H43*I43 -> 8114585.2 | K43: =H43 -> 166002.4 | L43: =I43*(1+Assumptions!$D$22) -> 51.326454 | M43: =K43*L43 -> 8520314.5 | N43: =K43 -> 166002.4 | O43: =L43*(1+Assumptions!$D$22) -> 53.892776 | P43: =N43*O43 -> 8946330.2
A44: Feed for fry (kg) | B44: =E27 -> 6000.6001 | C44: 70 | D44: =B44*C44 -> 420042 | E44: =B44*2.5 -> 15001.5 | F44: =C44*(1+Assumptions!$D$22) -> 73.5 | G44: =E44*F44 -> 1102610.3 | H44: =E44*1.6 -> 24002.4 | I44: =F44*(1+Assumptions!$D$22) -> 77.175 | J44: =H44*I44 -> 1852385.2 | K44: =H44 -> 24002.4 | L44: =I44*(1+Assumptions!$D$22) -> 81.03375 | M44: =K44*L44 -> 1945004.5 | N44: =K44 -> 24002.4 | O44: =L44*(1+Assumptions!$D$22) -> 85.085437 | P44: =N44*O44 -> 2042254.7
A45: Total Feed | D45: =SUBTOTAL(9,D43:D44) -> 2260084 | G45: =SUBTOTAL(9,G43:G44) -> 5932720.5 | J45: =SUBTOTAL(9,J43:J44) -> 9966970.5 | M45: =SUBTOTAL(9,M43:M44) -> 10465319 | P45: =SUBTOTAL(9,P43:P44) -> 10988585
A46: Hormone 10ml recipient of oval prim | B46: 40 | C46: 40000 | D46: =B46*C46 -> 1600000 | E46: =B46*2.5 -> 100 | F46: =C46 -> 40000 | G46: =E46*F46 -> 4000000 | H46: =E46*1.6 -> 160 | I46: =F46 -> 40000 | J46: =H46*I46 -> 6400000 | K46: =H46 -> 160 | L46: =I46 -> 40000 | M46: =K46*L46 -> 6400000 | N46: =K46 -> 160 | O46: =L46 -> 40000 | P46: =N46*O46 -> 6400000
A47: Total | D47: =SUBTOTAL(9,D40:D46) -> 4005084 | G47: =SUBTOTAL(9,G40:G46) -> 10295221 | J47: =SUBTOTAL(9,J40:J46) -> 16946970 | M47: =SUBTOTAL(9,M40:M46) -> 17445319 | P47: =SUBTOTAL(9,P40:P46) -> 17968585
A49: Revenue: selling rate rises every year (increase set on the Assumptions sheet)
A50: Particulars | B50: 2026 - 2027 | E50: 2027 - 2028 | H50: 2028 - 2029 | K50: 2029 - 2030 | N50: 2030 - 2031
B51: Qty | C51: Selling rate (Tk) | D51: Amt (Tk.) | E51: Qty | F51: Selling rate (Tk) | G51: Amt (Tk.) | H51: Qty | I51: Selling rate (Tk) | J51: Amt (Tk.) | K51: Qty | L51: Selling rate (Tk) | M51: Amt (Tk.) | N51: Qty | O51: Selling rate (Tk) | P51: Amt (Tk.)
A52: Tilapia fry (pcs) | B52: =I72 -> 10000000 | C52: 0.8 | D52: =B52*C52 -> 8000000 | E52: =V72 -> 25000000 | F52: =C52*(1+Assumptions!$D$21) -> 0.84 | G52: =E52*F52 -> 21000000 | H52: =AI72 -> 35000000 | I52: =F52*(1+Assumptions!$D$21) -> 0.882 | J52: =H52*I52 -> 30870000 | K52: =AV72 -> 40000000 | L52: =I52*(1+Assumptions!$D$21) -> 0.9261 | M52: =K52*L52 -> 37044000 | N52: =K52 -> 40000000 | O52: =L52*(1+Assumptions!$D$21) -> 0.972405 | P52: =N52*O52 -> 38896200
A53: Carp fry (kg) | B53: =I73 -> 400 | C53: 3500 | D53: =B53*C53 -> 1400000 | E53: =V73 -> 1600 | F53: =C53*(1+Assumptions!$D$21) -> 3675 | G53: =E53*F53 -> 5880000 | H53: =AI73 -> 3100 | I53: =F53*(1+Assumptions!$D$21) -> 3858.75 | J53: =H53*I53 -> 11962125 | K53: =AV73 -> 2400 | L53: =I53*(1+Assumptions!$D$21) -> 4051.6875 | M53: =K53*L53 -> 9724050 | N53: =K53 -> 2400 | O53: =L53*(1+Assumptions!$D$21) -> 4254.2719 | P53: =N53*O53 -> 10210252
A54: Tilapia broodfish (kg) | B54: =I74 -> 0 | C54: 150 | D54: =B54*C54 -> 0 | E54: =V74 -> 0 | F54: =C54*(1+Assumptions!$D$21) -> 157.5 | G54: =E54*F54 -> 0 | H54: =AI74 -> 0 | I54: =F54*(1+Assumptions!$D$21) -> 165.375 | J54: =H54*I54 -> 0 | K54: =AV74 -> 24000 | L54: =I54*(1+Assumptions!$D$21) -> 173.64375 | M54: =K54*L54 -> 4167450 | N54: 0 | O54: =L54*(1+Assumptions!$D$21) -> 182.32594 | P54: =N54*O54 -> 0
A55: Carp broodfish (kg) | B55: =I75 -> 0 | C55: 300 | D55: =B55*C55 -> 0 | E55: =V75 -> 0 | F55: =C55*(1+Assumptions!$D$21) -> 315 | G55: =E55*F55 -> 0 | H55: =AI75 -> 0 | I55: =F55*(1+Assumptions!$D$21) -> 330.75 | J55: =H55*I55 -> 0 | K55: =AV75 -> 20000 | L55: =I55*(1+Assumptions!$D$21) -> 347.2875 | M55: =K55*L55 -> 6945750 | N55: 0 | O55: =L55*(1+Assumptions!$D$21) -> 364.65188 | P55: =N55*O55 -> 0
A56: Total revenue | D56: =SUM(D52:D55) -> 9400000 | G56: =SUM(G52:G55) -> 26880000 | J56: =SUM(J52:J55) -> 42832125 | M56: =SUM(M52:M55) -> 57881250 | P56: =SUM(P52:P55) -> 49106453
A58: Broodfish are sold once, after 3 years (Year 4). Quantities come from the production calendar below. The quantity sold is worked out on the Assumptions sheet (stock x size x (1 - mortality)). Year 5 broodfish quantity is zero because the old stock is sold only once.
A60: Month-wise revenue (Tk) = quantity x selling rate of that year
A61: Item | C61: 2026 - 2027 | J61: 2027 - 2028 | W61: 2028 - 2029 | AJ61: 2029 - 2030
C62: 46388 | D62: 46419 | E62: 46447 | F62: 46478 | G62: 46508 | H62: 46539 | I62: Total | J62: 46569 | K62: 46600 | L62: 46631 | M62: 46661 | N62: 46692 | O62: 46722 | P62: 46753 | Q62: 46784 | R62: 46813 | S62: 46844 | T62: 46874 | U62: 46905 | V62: Total | W62: 46935 | X62: 46966 | Y62: 46997 | Z62: 47027 | AA62: 47058 | AB62: 47088 | AC62: 47119 | AD62: 47150 | AE62: 47178 | AF62: 47209 | AG62: 47239 | AH62: 47270 | AI62: Total | AJ62: 47300 | AK62: 47331 | AL62: 47362 | AM62: 47392 | AN62: 47423 | AO62: 47453 | AP62: 47484 | AQ62: 47515 | AR62: 47543 | AS62: 47574 | AT62: 47604 | AU62: 47635 | AV62: Total
A63: Tilapia fry (Tk.) | B63: Tk | F63: =F72*$C$52 -> 1600000 | G63: =G72*$C$52 -> 3200000 | H63: =H72*$C$52 -> 3200000 | I63: =SUM(C63:H63) -> 8000000 | J63: =J72*$F$52 -> 3360000 | K63: =K72*$F$52 -> 3360000 | L63: =L72*$F$52 -> 1680000 | S63: =S72*$F$52 -> 2520000 | T63: =T72*$F$52 -> 5040000 | U63: =U72*$F$52 -> 5040000 | V63: =SUM(J63:U63) -> 21000000 | W63: =W72*$I$52 -> 5292000 | X63: =X72*$I$52 -> 5292000 | Y63: =Y72*$I$52 -> 2646000 | AF63: =AF72*$I$52 -> 3528000 | AG63: =AG72*$I$52 -> 7056000 | AH63: =AH72*$I$52 -> 7056000 | AI63: =SUM(W63:AH63) -> 30870000 | AJ63: =AJ72*$L$52 -> 7408800 | AK63: =AK72*$L$52 -> 7408800 | AL63: =AL72*$L$52 -> 3704400 | AS63: =AS72*$L$52 -> 3704400 | AT63: =AT72*$L$52 -> 7408800 | AU63: =AU72*$L$52 -> 7408800 | AV63: =SUM(AJ63:AU63) -> 37044000
A64: Carp fry (Tk.) | B64: Tk | F64: =F73*$C$53 -> 350000 | G64: =G73*$C$53 -> 350000 | H64: =H73*$C$53 -> 700000 | I64: =SUM(C64:H64) -> 1400000 | J64: =J73*$F$53 -> 1102500 | K64: =K73*$F$53 -> 1102500 | S64: =S73*$F$53 -> 918750 | T64: =T73*$F$53 -> 918750 | U64: =U73*$F$53 -> 1837500 | V64: =SUM(J64:U64) -> 5880000 | W64: =W73*$I$53 -> 2894062.5 | X64: =X73*$I$53 -> 2894062.5 | AF64: =AF73*$I$53 -> 1543500 | AG64: =AG73*$I$53 -> 1543500 | AH64: =AH73*$I$53 -> 3087000 | AI64: =SUM(W64:AH64) -> 11962125 | AJ64: =AJ73*$L$53 -> 4862025 | AK64: =AK73*$L$53 -> 4862025 | AV64: =SUM(AJ64:AU64) -> 9724050
A65: Tilapia broodfish (Tk.) | B65: Tk | I65: =SUM(C65:H65) -> 0 | V65: =SUM(J65:U65) -> 0 | AI65: =SUM(W65:AH65) -> 0 | AO65: =AO74*$L$54 -> 4167450 | AV65: =SUM(AJ65:AU65) -> 4167450
A66: Carp broodfish (Tk.) | B66: Tk | I66: =SUM(C66:H66) -> 0 | V66: =SUM(J66:U66) -> 0 | AI66: =SUM(W66:AH66) -> 0 | AP66: =AP75*$L$55 -> 6945750 | AV66: =SUM(AJ66:AU66) -> 6945750
A67: Hatchery total (Tk.) | C67: =C63+C64+C65+C66 -> 0 | D67: =D63+D64+D65+D66 -> 0 | E67: =E63+E64+E65+E66 -> 0 | F67: =F63+F64+F65+F66 -> 1950000 | G67: =G63+G64+G65+G66 -> 3550000 | H67: =H63+H64+H65+H66 -> 3900000 | I67: =I63+I64+I65+I66 -> 9400000 | J67: =J63+J64+J65+J66 -> 4462500 | ... AV67: =AV63+AV64+AV65+AV66 -> 57881250
A69: Production and sales calendar (tilapia fry in pcs; carp fry and broodfish in kg)
A70: Item | C70: 2026 - 2027 | J70: 2027 - 2028 | W70: 2028 - 2029 | AJ70: 2029 - 2030
C71: 46388 | D71: 46419 | E71: 46447 | F71: 46478 | G71: 46508 | H71: 46539 | I71: Total | J71: 46569 | K71: 46600 | L71: 46631 | M71: 46661 | N71: 46692 | O71: 46722 | P71: 46753 | Q71: 46784 | R71: 46813 | S71: 46844 | T71: 46874 | U71: 46905 | V71: Total | W71: 46935 | X71: 46966 | Y71: 46997 | Z71: 47027 | AA71: 47058 | AB71: 47088 | AC71: 47119 | AD71: 47150 | AE71: 47178 | AF71: 47209 | AG71: 47239 | AH71: 47270 | AI71: Total | AJ71: 47300 | AK71: 47331 | AL71: 47362 | AM71: 47392 | AN71: 47423 | AO71: 47453 | AP71: 47484 | AQ71: 47515 | AR71: 47543 | AS71: 47574 | AT71: 47604 | AU71: 47635 | AV71: Total
A72: Tilapia fry (pcs) | B72: pcs | F72: =C10 -> 2000000 | G72: =C11 -> 4000000 | H72: =C12 -> 4000000 | I72: =SUM(C72:H72) -> 10000000 | J72: =E7 -> 4000000 | K72: =E8 -> 4000000 | L72: =E9 -> 2000000 | S72: =E10 -> 3000000 | T72: =E11 -> 6000000 | U72: =E12 -> 6000000 | V72: =SUM(J72:U72) -> 25000000 | W72: =G7 -> 6000000 | X72: =G8 -> 6000000 | Y72: =G9 -> 3000000 | AF72: =G10 -> 4000000 | AG72: =G11 -> 8000000 | AH72: =G12 -> 8000000 | AI72: =SUM(W72:AH72) -> 35000000 | AJ72: =I7 -> 8000000 | AK72: =I8 -> 8000000 | AL72: =I9 -> 4000000 | AS72: =I10 -> 4000000 | AT72: =I11 -> 8000000 | AU72: =I12 -> 8000000 | AV72: =SUM(AJ72:AU72) -> 40000000
A73: Carp fry (kg) | B73: kg | F73: 100 | G73: 100 | H73: 200 | I73: =SUM(C73:H73) -> 400 | J73: 300 | K73: 300 | S73: =F73*2.5 -> 250 | T73: =G73*2.5 -> 250 | U73: =H73*2.5 -> 500 | V73: =SUM(J73:U73) -> 1600 | W73: =J73*2.5 -> 750 | X73: =K73*2.5 -> 750 | AF73: =S73*1.6 -> 400 | AG73: =T73*1.6 -> 400 | AH73: =U73*1.6 -> 800 | AI73: =SUM(W73:AH73) -> 3100 | AJ73: =W73*1.6 -> 1200 | AK73: =X73*1.6 -> 1200 | AV73: =SUM(AJ73:AU73) -> 2400
A74: Tilapia broodfish (kg) | B74: kg | I74: =SUM(C74:H74) -> 0 | V74: =SUM(J74:U74) -> 0 | AI74: =SUM(W74:AH74) -> 0 | AO74: =Assumptions!$D$75 -> 24000 | AV74: =SUM(AJ74:AU74) -> 24000
A75: Carp broodfish (kg) | B75: kg | I75: =SUM(C75:H75) -> 0 | V75: =SUM(J75:U75) -> 0 | AI75: =SUM(W75:AH75) -> 0 | AP75: =Assumptions!$D$76 -> 20000 | AV75: =SUM(AJ75:AU75) -> 20000
A78: Colour code: blue on yellow = input, black = formula.

Sheet FA Schedule
B1: Capital Expenditure and Depreciation
B2: Straight-line depreciation starts in the year after purchase
B3: ="Scenario: "&Assumptions!$D$11&" | BDT'000 unless stated" -> Scenario: Base case | BDT'000 unless stated
B4: Financial year | C4: Unit | D4: Opening | E4: ="FY"&(Assumptions!$D$7+E5-1)&"-"&TEXT(MOD(Assumptions!$D$7+E5,100),"00") -> FY2026-27 | F4: ="FY"&(Assumptions!$D$7+F5-1)&"-"&TEXT(MOD(Assumptions!$D$7+F5,100),"00") -> FY2027-28 | G4: ="FY"&(Assumptions!$D$7+G5-1)&"-"&TEXT(MOD(Assumptions!$D$7+G5,100),"00") -> FY2028-29 | H4: ="FY"&(Assumptions!$D$7+H5-1)&"-"&TEXT(MOD(Assumptions!$D$7+H5,100),"00") -> FY2029-30 | I4: ="FY"&(Assumptions!$D$7+I5-1)&"-"&TEXT(MOD(Assumptions!$D$7+I5,100),"00") -> FY2030-31
D5: 0 | E5: 1 | F5: 2 | G5: 3 | H5: 4 | I5: 5
B7: Capital expenditure
B8: Land | C8: BDT | D8: =$E$62 -> 17080078 | E8: 0 | F8: =Assumptions!$D$68*Assumptions!$D$69 -> 3003000 | G8: 0 | H8: 0 | I8: 0
B9: Ponds and earthworks | C9: BDT | D9: =$E$63*Assumptions!$G$17 -> 3835704.8 | E9: 0 | F9: 0 | G9: 0 | H9: 0 | I9: 0
B10: Buildings and civil works | C10: BDT | D10: =$E$64*Assumptions!$G$17 -> 18764147 | E10: 0 | F10: =Assumptions!$D$67*Assumptions!$G$17 -> 2000000 | G10: 0 | H10: 0 | I10: 0
B11: Overhead water tanks | C11: BDT | D11: =$E$67*Assumptions!$G$17 -> 1000000 | E11: 0 | F11: 0 | G11: 0 | H11: 0 | I11: 0
B12: Equipment (including 5% contingency) | C12: BDT | D12: =$E$82*Assumptions!$G$17 -> 1912312.5 | E12: 0 | F12: 0 | G12: 0 | H12: 0 | I12: 0
B13: Vehicles | C13: BDT | D13: =$E$66*Assumptions!$G$17 -> 3000000 | E13: 0 | F13: 0 | G13: 0 | H13: 0 | I13: 0
B14: Furniture and fixtures | C14: BDT | D14: =$E$65*Assumptions!$G$17 -> 200000 | E14: 0 | F14: 0 | G14: 0 | H14: 0 | I14: 0
B15: Total capital expenditure | C15: BDT | D15: =SUM(D8:D14) -> 45792242 | E15: =SUM(E8:E14) -> 0 | F15: =SUM(F8:F14) -> 5003000 | G15: =SUM(G8:G14) -> 0 | H15: =SUM(H8:H14) -> 0 | I15: =SUM(I8:I14) -> 0
B16: of which depreciable | C16: BDT | D16: =D15-D8-D9 -> 24876459 | E16: =E15-E8-E9 -> 0 | F16: =F15-F8-F9 -> 2000000 | G16: =G15-G8-G9 -> 0 | H16: =H15-H8-H9 -> 0 | I16: =I15-I8-I9 -> 0
B18: Depreciation (rate in column C, straight line on cost)
B19: Buildings and civil works | C19: =Assumptions!$D$77 -> 0.1 | E19: =MIN($C19*SUM($D10:D10),SUM($D10:D10)-SUM($D19:D19)) -> 1876414.7 | F19: =MIN($C19*SUM($D10:E10),SUM($D10:E10)-SUM($D19:E19)) -> 1876414.7 | G19: =MIN($C19*SUM($D10:F10),SUM($D10:F10)-SUM($D19:F19)) -> 2076414.7 | H19: =MIN($C19*SUM($D10:G10),SUM($D10:G10)-SUM($D19:G19)) -> 2076414.7 | I19: =MIN($C19*SUM($D10:H10),SUM($D10:H10)-SUM($D19:H19)) -> 2076414.7
B20: Overhead water tanks | C20: =Assumptions!$D$78 -> 0.2 | E20: =MIN($C20*SUM($D11:D11),SUM($D11:D11)-SUM($D20:D20)) -> 200000 | F20: =MIN($C20*SUM($D11:E11),SUM($D11:E11)-SUM($D20:E20)) -> 200000 | G20: =MIN($C20*SUM($D11:F11),SUM($D11:F11)-SUM($D20:F20)) -> 200000 | H20: =MIN($C20*SUM($D11:G11),SUM($D11:G11)-SUM($D20:G20)) -> 200000 | I20: =MIN($C20*SUM($D11:H11),SUM($D11:H11)-SUM($D20:H20)) -> 200000
B21: Equipment | C21: =Assumptions!$D$79 -> 0.2 | E21: =MIN($C21*SUM($D12:D12),SUM($D12:D12)-SUM($D21:D21)) -> 382462.5 | F21: =MIN($C21*SUM($D12:E12),SUM($D12:E12)-SUM($D21:E21)) -> 382462.5 | G21: =MIN($C21*SUM($D12:F12),SUM($D12:F12)-SUM($D21:F21)) -> 382462.5 | H21: =MIN($C21*SUM($D12:G12),SUM($D12:G12)-SUM($D21:G21)) -> 382462.5 | I21: =MIN($C21*SUM($D12:H12),SUM($D12:H12)-SUM($D21:H21)) -> 382462.5
B22: Vehicles | C22: =Assumptions!$D$80 -> 0.2 | E22: =MIN($C22*SUM($D13:D13),SUM($D13:D13)-SUM($D22:D22)) -> 600000 | F22: =MIN($C22*SUM($D13:E13),SUM($D13:E13)-SUM($D22:E22)) -> 600000 | G22: =MIN($C22*SUM($D13:F13),SUM($D13:F13)-SUM($D22:F22)) -> 600000 | H22: =MIN($C22*SUM($D13:G13),SUM($D13:G13)-SUM($D22:G22)) -> 600000 | I22: =MIN($C22*SUM($D13:H13),SUM($D13:H13)-SUM($D22:H22)) -> 600000
B23: Furniture and fixtures | C23: =Assumptions!$D$81 -> 0.2 | E23: =MIN($C23*SUM($D14:D14),SUM($D14:D14)-SUM($D23:D23)) -> 40000 | F23: =MIN($C23*SUM($D14:E14),SUM($D14:E14)-SUM($D23:E23)) -> 40000 | G23: =MIN($C23*SUM($D14:F14),SUM($D14:F14)-SUM($D23:F23)) -> 40000 | H23: =MIN($C23*SUM($D14:G14),SUM($D14:G14)-SUM($D23:G23)) -> 40000 | I23: =MIN($C23*SUM($D14:H14),SUM($D14:H14)-SUM($D23:H23)) -> 40000
B24: Total depreciation | C24: BDT | E24: =SUM(E19:E23) -> 3098877.2 | F24: =SUM(F19:F23) -> 3098877.2 | G24: =SUM(G19:G23) -> 3298877.2 | H24: =SUM(H19:H23) -> 3298877.2 | I24: =SUM(I19:I23) -> 3298877.2
B25: of which hatchery share | C25: BDT | E25: =E24*Assumptions!$D$59 -> 2169214 | F25: =F24*Assumptions!$D$59 -> 2169214 | G25: =G24*Assumptions!$D$59 -> 2309214 | H25: =H24*Assumptions!$D$59 -> 2309214 | I25: =I24*Assumptions!$D$59 -> 2309214
B27: Net book value
B28: Depreciable assets at cost, closing | C28: BDT | D28: =SUM($D10:D10)+SUM($D11:D11)+SUM($D12:D12)+SUM($D13:D13)+SUM($D14:D14) -> 24876459 | E28: =SUM($D10:E10)+SUM($D11:E11)+SUM($D12:E12)+SUM($D13:E13)+SUM($D14:E14) -> 24876459 | F28: =SUM($D10:F10)+SUM($D11:F11)+SUM($D12:F12)+SUM($D13:F13)+SUM($D14:F14) -> 26876459 | G28: =SUM($D10:G10)+SUM($D11:G11)+SUM($D12:G12)+SUM($D13:G13)+SUM($D14:G14) -> 26876459 | H28: =SUM($D10:H10)+SUM($D11:H11)+SUM($D12:H12)+SUM($D13:H13)+SUM($D14:H14) -> 26876459 | I28: =SUM($D10:I10)+SUM($D11:I11)+SUM($D12:I12)+SUM($D13:I13)+SUM($D14:I14) -> 26876459
B29: Accumulated depreciation, closing | C29: BDT | D29: =SUM($D24:D24) -> 0 | E29: =SUM($D24:E24) -> 3098877.2 | F29: =SUM($D24:F24) -> 6197754.4 | G29: =SUM($D24:G24) -> 9496631.6 | H29: =SUM($D24:H24) -> 12795509 | I29: =SUM($D24:I24) -> 16094386
B30: Net book value, depreciable assets | C30: BDT | D30: =D28-D29 -> 24876459 | E30: =E28-E29 -> 21777582 | F30: =F28-F29 -> 20678705 | G30: =G28-G29 -> 17379828 | H30: =H28-H29 -> 14080951 | I30: =I28-I29 -> 10782073
B31: Land and ponds at cost (not depreciated) | C31: BDT | D31: =SUM($D8:D8)+SUM($D9:D9) -> 20915783 | E31: =SUM($D8:E8)+SUM($D9:E9) -> 20915783 | F31: =SUM($D8:F8)+SUM($D9:F9) -> 23918783 | G31: =SUM($D8:G8)+SUM($D9:G9) -> 23918783 | H31: =SUM($D8:H8)+SUM($D9:H9) -> 23918783 | I31: =SUM($D8:I8)+SUM($D9:I9) -> 23918783
B32: Total fixed assets, net | C32: BDT | D32: =D30+D31 -> 45792242 | E32: =E30+E31 -> 42693365 | F32: =F30+F31 -> 44597488 | G32: =G30+G31 -> 41298611 | H32: =H30+H31 -> 37999733 | I32: =I30+I31 -> 34700856
B33: Fixed assets at cost, closing | C33: BDT | D33: =D28+D31 -> 45792242 | E33: =E28+E31 -> 45792242 | F33: =F28+F31 -> 50795242 | G33: =G28+G31 -> 50795242 | H33: =H28+H31 -> 50795242 | I33: =I28+I31 -> 50795242
B34: Security: land, ponds and buildings at cost | C34: BDT | D34: =SUM($D8:D8)+SUM($D9:D9)+SUM($D10:D10) -> 39679930 | E34: =SUM($D8:E8)+SUM($D9:E9)+SUM($D10:E10) -> 39679930 | F34: =SUM($D8:F8)+SUM($D9:F9)+SUM($D10:F10) -> 44682930 | G34: =SUM($D8:G8)+SUM($D9:G9)+SUM($D10:G10) -> 44682930 | H34: =SUM($D8:H8)+SUM($D9:H9)+SUM($D10:H10) -> 44682930 | I34: =SUM($D8:I8)+SUM($D9:I9)+SUM($D10:I10) -> 44682930
B58: List of assets (figures in Taka)
B60: Land and Building
B61: Particulars | C61: Qty | D61: Cost | E61: Amt (Tk.)
B62: Land | C62: 1589 | D62: =E62/C62 -> 10748.948 | E62: 17080078
B63: Ponds | C63: 17 | D63: =E63/C63 -> 225629.69 | E63: 3835704.8
B64: Building | E64: 18764147
B65: Furniture & Fixtures | E65: 200000
B66: Vehicle | E66: 3000000
B67: Overhead tank. | C67: 10 | D67: =E67/C67 -> 100000 | E67: 1000000
B68: Total | E68: =SUM(E62:E67) -> 43879930
B70: Equipment
B71: Particulars | C71: Qty | D71: Cost | E71: Amt (Tk.)
B72: Pump | C72: 4 | D72: 15000 | E72: =C72*D72 -> 60000
B73: Water parameter measuring instrument (multimetre) | C73: 0 | E73: 25000
B74: Microscope | C74: 1 | D74: 80000 | E74: =C74*D74 -> 80000
B75: Refrigerator | C75: 1 | D75: 20000 | E75: =C75*D75 -> 20000
B76: Scale balance | C76: 2 | D76: 2000 | E76: =C76*D76 -> 4000
B77: Computer | C77: 2 | D77: 35000 | E77: =C77*D77 -> 70000
B78: Electric generator | C78: 1 | D78: 345000 | E78: =C78*D78 -> 345000
B79: Wheel barrows | C79: 20 | D79: 60800 | E79: =C79*D79 -> 1216000
B80: Spades | C80: 5 | D80: 250 | E80: =C80*D80 -> 1250
B81: Contingency | C81: 0.05 | E81: =SUM(E72:E80)*C81 -> 91062.5
B82: Total | E82: =SUM(E72:E81) -> 1912312.5
B84: Grand Total | E84: =E82+E68 -> 45792242

Sheet Operations
B1: Operations: Revenue and Operating Costs
B2: Revenue and direct costs are picked up from the Farming and Hatchery sheets; overheads come from the cost build-up at the bottom of this sheet.
B3: ="Scenario: "&Assumptions!$D$11&" | BDT '000 unless stated" -> Scenario: Base case | BDT '000 unless stated
B4: Financial year | C4: Unit | D4: Opening | E4: ="FY"&(Assumptions!$D$7+E5-1)&"-"&TEXT(MOD(Assumptions!$D$7+E5,100),"00") -> FY2026-27 | F4: ="FY"&(Assumptions!$D$7+F5-1)&"-"&TEXT(MOD(Assumptions!$D$7+F5,100),"00") -> FY2027-28 | G4: ="FY"&(Assumptions!$D$7+G5-1)&"-"&TEXT(MOD(Assumptions!$D$7+G5,100),"00") -> FY2028-29 | H4: ="FY"&(Assumptions!$D$7+H5-1)&"-"&TEXT(MOD(Assumptions!$D$7+H5,100),"00") -> FY2029-30 | I4: ="FY"&(Assumptions!$D$7+I5-1)&"-"&TEXT(MOD(Assumptions!$D$7+I5,100),"00") -> FY2030-31
D5: 0 | E5: 1 | F5: 2 | G5: 3 | H5: 4 | I5: 5
B7: A. Revenue (BDT thousand): picked up from the Hatchery and Farming sheets
B8: Hatchery: tilapia fry | C8: BDT | E8: =Hatchery!D52*Assumptions!$G$14*Assumptions!$G$15 -> 8000000 | F8: =Hatchery!G52*Assumptions!$G$14*Assumptions!$G$15 -> 21000000 | G8: =Hatchery!J52*Assumptions!$G$14*Assumptions!$G$15 -> 30870000 | H8: =Hatchery!M52*Assumptions!$G$14*Assumptions!$G$15 -> 37044000 | I8: =Hatchery!P52*Assumptions!$G$14*Assumptions!$G$15 -> 38896200
B9: Hatchery: carp fry | C9: BDT | E9: =Hatchery!D53*Assumptions!$G$14*Assumptions!$G$15 -> 1400000 | F9: =Hatchery!G53*Assumptions!$G$14*Assumptions!$G$15 -> 5880000 | G9: =Hatchery!J53*Assumptions!$G$14*Assumptions!$G$15 -> 11962125 | H9: =Hatchery!M53*Assumptions!$G$14*Assumptions!$G$15 -> 9724050 | I9: =Hatchery!P53*Assumptions!$G$14*Assumptions!$G$15 -> 10210252
B10: Hatchery: tilapia broodfish | C10: BDT | E10: =Hatchery!D54*Assumptions!$G$14*Assumptions!$G$15 -> 0 | F10: =Hatchery!G54*Assumptions!$G$14*Assumptions!$G$15 -> 0 | G10: =Hatchery!J54*Assumptions!$G$14*Assumptions!$G$15 -> 0 | H10: =Hatchery!M54*Assumptions!$G$14*Assumptions!$G$15 -> 4167450 | I10: =Hatchery!P54*Assumptions!$G$14*Assumptions!$G$15 -> 0
B11: Hatchery: carp broodfish | C11: BDT | E11: =Hatchery!D55*Assumptions!$G$14*Assumptions!$G$15 -> 0 | F11: =Hatchery!G55*Assumptions!$G$14*Assumptions!$G$15 -> 0 | G11: =Hatchery!J55*Assumptions!$G$14*Assumptions!$G$15 -> 0 | H11: =Hatchery!M55*Assumptions!$G$14*Assumptions!$G$15 -> 6945750 | I11: =Hatchery!P55*Assumptions!$G$14*Assumptions!$G$15 -> 0
B12: Hatchery revenue | C12: BDT | E12: =E8+E9+E10+E11 -> 9400000 | F12: =F8+F9+F10+F11 -> 26880000 | G12: =G8+G9+G10+G11 -> 42832125 | H12: =H8+H9+H10+H11 -> 57881250 | I12: =I8+I9+I10+I11 -> 49106453
B13: Farming: tilapia | C13: BDT | E13: =Farming!D58*Assumptions!$G$14*Assumptions!$G$15 -> 880000 | F13: =Farming!G58*Assumptions!$G$14*Assumptions!$G$15 -> 8662500 | G13: =Farming!J58*Assumptions!$G$14*Assumptions!$G$15 -> 9095625 | H13: =Farming!M58*Assumptions!$G$14*Assumptions!$G$15 -> 9550406.2 | I13: =Farming!P58*Assumptions!$G$14*Assumptions!$G$15 -> 10027927
B14: Farming: carp | C14: BDT | E14: =Farming!D59*Assumptions!$G$14*Assumptions!$G$15 -> 1800000 | F14: =Farming!G59*Assumptions!$G$14*Assumptions!$G$15 -> 14175000 | G14: =Farming!J59*Assumptions!$G$14*Assumptions!$G$15 -> 14883750 | H14: =Farming!M59*Assumptions!$G$14*Assumptions!$G$15 -> 15627938 | I14: =Farming!P59*Assumptions!$G$14*Assumptions!$G$15 -> 16409334
B15: Farming revenue | C15: BDT | E15: =E13+E14 -> 2680000 | F15: =F13+F14 -> 22837500 | G15: =G13+G14 -> 23979375 | H15: =H13+H14 -> 25178344 | I15: =I13+I14 -> 26437261
B16: Total revenue | C16: BDT | E16: =E12+E15 -> 12080000 | F16: =F12+F15 -> 49717500 | G16: =G12+G15 -> 66811500 | H16: =H12+H15 -> 83059594 | I16: =I12+I15 -> 75543713
B18: B. Selling rates used (BDT per unit): they rise every year by the price increase on the Assumptions sheet
B19: Tilapia (per kg) | C19: BDT | E19: =Farming!C58*Assumptions!$G$14 -> 110 | F19: =Farming!F58*Assumptions!$G$14 -> 115.5 | G19: =Farming!I58*Assumptions!$G$14 -> 121.275 | H19: =Farming!L58*Assumptions!$G$14 -> 127.33875 | I19: =Farming!O58*Assumptions!$G$14 -> 133.70569
B20: Carp (per kg) | C20: BDT | E20: =Farming!C59*Assumptions!$G$14 -> 180 | F20: =Farming!F59*Assumptions!$G$14 -> 189 | G20: =Farming!I59*Assumptions!$G$14 -> 198.45 | H20: =Farming!L59*Assumptions!$G$14 -> 208.3725 | I20: =Farming!O59*Assumptions!$G$14 -> 218.79113
B21: Tilapia fry (per piece) | C21: BDT | E21: =Hatchery!C52*Assumptions!$G$14 -> 0.8 | F21: =Hatchery!F52*Assumptions!$G$14 -> 0.84 | G21: =Hatchery!I52*Assumptions!$G$14 -> 0.882 | H21: =Hatchery!L52*Assumptions!$G$14 -> 0.9261 | I21: =Hatchery!O52*Assumptions!$G$14 -> 0.972405
B22: Carp fry (per kg) | C22: BDT | E22: =Hatchery!C53*Assumptions!$G$14 -> 3500 | F22: =Hatchery!F53*Assumptions!$G$14 -> 3675 | G22: =Hatchery!I53*Assumptions!$G$14 -> 3858.75 | H22: =Hatchery!L53*Assumptions!$G$14 -> 4051.6875 | I22: =Hatchery!O53*Assumptions!$G$14 -> 4254.2719
B23: Tilapia broodfish (per kg, sold in Year 4) | C23: BDT | E23: =Hatchery!C54*Assumptions!$G$14 -> 150 | F23: =Hatchery!F54*Assumptions!$G$14 -> 157.5 | G23: =Hatchery!I54*Assumptions!$G$14 -> 165.375 | H23: =Hatchery!L54*Assumptions!$G$14 -> 173.64375 | I23: =Hatchery!O54*Assumptions!$G$14 -> 182.32594
B24: Carp broodfish (per kg, sold in Year 4) | C24: BDT | E24: =Hatchery!C55*Assumptions!$G$14 -> 300 | F24: =Hatchery!F55*Assumptions!$G$14 -> 315 | G24: =Hatchery!I55*Assumptions!$G$14 -> 330.75 | H24: =Hatchery!L55*Assumptions!$G$14 -> 347.2875 | I24: =Hatchery!O55*Assumptions!$G$14 -> 364.65188
B25: Yearly increase in the selling rate | C25: % | F25: =IFERROR(F19/E19-1,0) -> 0.05 | G25: =IFERROR(G19/F19-1,0) -> 0.05 | H25: =IFERROR(H19/G19-1,0) -> 0.05 | I25: =IFERROR(I19/H19-1,0) -> 0.05
B27: C. Variable costs (BDT thousand): they move with production and sales
B28: Feed: hatchery | C28: BDT | E28: =Hatchery!D45*Assumptions!$G$15*Assumptions!$G$16 -> 2260084 | F28: =Hatchery!G45*Assumptions!$G$15*Assumptions!$G$16 -> 5932720.5 | G28: =Hatchery!J45*Assumptions!$G$15*Assumptions!$G$16 -> 9966970.5 | H28: =Hatchery!M45*Assumptions!$G$15*Assumptions!$G$16 -> 10465319 | I28: =Hatchery!P45*Assumptions!$G$15*Assumptions!$G$16 -> 10988585
B29: Feed: farming | C29: BDT | E29: =Farming!D50*Assumptions!$G$15*Assumptions!$G$16 -> 2900000 | F29: =Farming!G50*Assumptions!$G$15*Assumptions!$G$16 -> 9135000 | G29: =Farming!J50*Assumptions!$G$15*Assumptions!$G$16 -> 9591750 | H29: =Farming!M50*Assumptions!$G$15*Assumptions!$G$16 -> 10071338 | I29: =Farming!P50*Assumptions!$G$15*Assumptions!$G$16 -> 10574904
B30: Feed total | C30: BDT | E30: =E28+E29 -> 5160084 | F30: =F28+F29 -> 15067721 | G30: =G28+G29 -> 19558720 | H30: =H28+H29 -> 20536657 | I30: =I28+I29 -> 21563489
B31: Broodstock: hatchery | C31: BDT | E31: =Hatchery!D42*Assumptions!$G$15 -> 145000 | F31: =Hatchery!G42*Assumptions!$G$15 -> 362500 | G31: =Hatchery!J42*Assumptions!$G$15 -> 580000 | H31: =Hatchery!M42*Assumptions!$G$15 -> 580000 | I31: =Hatchery!P42*Assumptions!$G$15 -> 580000
B32: Fingerlings: farming | C32: BDT | E32: =Farming!D49*Assumptions!$G$15 -> 780000 | F32: =Farming!G49*Assumptions!$G$15 -> 1170000 | G32: =Farming!J49*Assumptions!$G$15 -> 1170000 | H32: =Farming!M49*Assumptions!$G$15 -> 1170000 | I32: =Farming!P49*Assumptions!$G$15 -> 1170000
B33: Broodstock and fingerlings total | C33: BDT | E33: =E31+E32 -> 925000 | F33: =F31+F32 -> 1532500 | G33: =G31+G32 -> 1750000 | H33: =H31+H32 -> 1750000 | I33: =I31+I32 -> 1750000
B34: Hormone: hatchery | C34: BDT | E34: =Hatchery!D46*Assumptions!$G$15 -> 1600000 | F34: =Hatchery!G46*Assumptions!$G$15 -> 4000000 | G34: =Hatchery!J46*Assumptions!$G$15 -> 6400000 | H34: =Hatchery!M46*Assumptions!$G$15 -> 6400000 | I34: =Hatchery!P46*Assumptions!$G$15 -> 6400000
B35: Direct costs (feed, stock, hormone) | C35: BDT | E35: =E30+E33+E34 -> 7685084 | F35: =F30+F33+F34 -> 20600221 | G35: =G30+G33+G34 -> 27708720 | H35: =H30+H33+H34 -> 28686657 | I35: =I30+I33+I34 -> 29713489
B36: Factory overheads (fuel, lime, utilities, packing, labour) | C36: BDT | E36: =E64*Assumptions!$G$15 -> 996250 | F36: =F64*Assumptions!$G$15 -> 1962125 | G36: =G64*Assumptions!$G$15 -> 2067381.2 | H36: =H64*Assumptions!$G$15 -> 2178615.3 | I36: =I64*Assumptions!$G$15 -> 2296197.6
B37: Marketing (% of hatchery revenue) | C37: BDT | E37: =Assumptions!$D$61*E12 -> 188000 | F37: =Assumptions!$D$61*F12 -> 537600 | G37: =Assumptions!$D$61*G12 -> 856642.5 | H37: =Assumptions!$D$61*H12 -> 1157625 | I37: =Assumptions!$D$61*I12 -> 982129.05
B38: Selling (% of hatchery revenue) | C38: BDT | E38: =Assumptions!$D$62*E12 -> 752000 | F38: =Assumptions!$D$62*F12 -> 2150400 | G38: =Assumptions!$D$62*G12 -> 3426570 | H38: =Assumptions!$D$62*H12 -> 4630500 | I38: =Assumptions!$D$62*I12 -> 3928516.2
B39: Total variable costs | C39: BDT | E39: =E35+E36+E37+E38 -> 9621334 | F39: =F35+F36+F37+F38 -> 25250346 | G39: =G35+G36+G37+G38 -> 34059314 | H39: =H35+H36+H37+H38 -> 36653397 | I39: =I35+I36+I37+I38 -> 36920332
B40: Contribution (revenue less variable costs) | C40: BDT | E40: =E16-E39 -> 2458666 | F40: =F16-F39 -> 24467154 | G40: =G16-G39 -> 32752186 | H40: =H16-H39 -> 46406197 | I40: =I16-I39 -> 38623381
B41: Contribution margin | C41: % | E41: =IFERROR(E40/E16,0) -> 0.20353195 | F41: =IFERROR(F40/F16,0) -> 0.49212359 | G41: =IFERROR(G40/G16,0) -> 0.49021779 | H41: =IFERROR(H40/H16,0) -> 0.55870965 | I41: =IFERROR(I40/I16,0) -> 0.51127194
B43: D. Fixed costs (BDT thousand): they do not change with production
B44: Salaries and festival bonus | C44: BDT | E44: =E67+E68+E69+E70 -> 936000 | F44: =F67+F68+F69+F70 -> 1392300 | G44: =G67+G68+G69+G70 -> 1461915 | H44: =H67+H68+H69+H70 -> 1535010.8 | I44: =I67+I68+I69+I70 -> 1611761.3
B45: Other administrative (office, maintenance, administration, contingency) | C45: BDT | E45: =E73-E44 -> 230550 | F45: =F73-F44 -> 463365 | G45: =G73-G44 -> 495720.75 | H45: =H73-H44 -> 531138.04 | I45: =I73-I44 -> 569914.31
B46: Administrative expenses | C46: BDT | E46: =E44+E45 -> 1166550 | F46: =F44+F45 -> 1855665 | G46: =G44+G45 -> 1957635.8 | H46: =H44+H45 -> 2066148.8 | I46: =I44+I45 -> 2181675.6
B47: Distribution (hatchery) | C47: BDT | E47: =Assumptions!$D$63 -> 500000 | F47: =Assumptions!$D$63 -> 500000 | G47: =Assumptions!$D$63 -> 500000 | H47: =Assumptions!$D$63 -> 500000 | I47: =Assumptions!$D$63 -> 500000
B48: Total fixed costs | C48: BDT | E48: =E46+E47 -> 1666550 | F48: =F46+F47 -> 2355665 | G48: =G46+G47 -> 2457635.8 | H48: =H46+H47 -> 2566148.8 | I48: =I46+I47 -> 2681675.6
B49: Total operating costs before depreciation and interest | C49: BDT | E49: =E39+E48 -> 11287884 | F49: =F39+F48 -> 27606011 | G49: =G39+G48 -> 36516950 | H49: =H39+H48 -> 39219546 | I49: =I39+I48 -> 39602008
B51: EBITDA (contribution less fixed costs) | C51: BDT | E51: =E40-E48 -> 792115.99 | F51: =F40-F48 -> 22111489 | G51: =G40-G48 -> 30294550 | H51: =H40-H48 -> 43840048 | I51: =I40-I48 -> 35941706
B52: EBITDA margin | C52: % | E52: =IFERROR(E51/E16,0) -> 0.065572516 | F52: =IFERROR(F51/F16,0) -> 0.44474259 | G52: =IFERROR(G51/G16,0) -> 0.45343317 | H52: =IFERROR(H51/H16,0) -> 0.52781438 | I52: =IFERROR(I51/I16,0) -> 0.47577362
B54: E. Cost build-up (BDT, full Taka)
B55: Particulars | C55: Type | D55: Year 2 step-up (x) | J55: Increase a year
B56: Fuel | C56: Variable | D56: 1 | E56: =400*5*65 -> 130000 | F56: =E56*$D56*(1+$J56) -> 143000 | G56: =F56*(1+$J56) -> 157300 | H56: =G56*(1+$J56) -> 173030 | I56: =H56*(1+$J56) -> 190333 | J56: =Assumptions!$D$26 -> 0.1 | K56: 400 litres x 6 months at Tk 65 in Year 1; fuel rises 10% a year
B57: Lime | C57: Variable | D57: 2 | E57: =750*15 -> 11250 | F57: =E57*$D57*(1+$J57) -> 23625 | G57: =F57*(1+$J57) -> 24806.25 | H57: =G57*(1+$J57) -> 26046.562 | I57: =H57*(1+$J57) -> 27348.891 | J57: =Assumptions!$D$27 -> 0.05 | K57: Year 2: full year
B58: Entertainment | C58: Variable | D58: 2 | E58: 25000 | F58: =E58*$D58*(1+$J58) -> 52500 | G58: =F58*(1+$J58) -> 55125 | H58: =G58*(1+$J58) -> 57881.25 | I58: =H58*(1+$J58) -> 60775.312 | J58: =Assumptions!$D$27 -> 0.05
B59: Local conveyance | C59: Variable | D59: 2 | E59: 25000 | F59: =E59*$D59*(1+$J59) -> 52500 | G59: =F59*(1+$J59) -> 55125 | H59: =G59*(1+$J59) -> 57881.25 | I59: =H59*(1+$J59) -> 60775.312 | J59: =Assumptions!$D$27 -> 0.05
B60: Materials for parcelling | C60: Variable | D60: 2 | E60: 500000 | F60: =E60*$D60*(1+$J60) -> 1050000 | G60: =F60*(1+$J60) -> 1102500 | H60: =G60*(1+$J60) -> 1157625 | I60: =H60*(1+$J60) -> 1215506.2 | J60: =Assumptions!$D$27 -> 0.05 | K60: Distribution cost
B61: Electricity bills | C61: Variable | D61: 2 | E61: 250000 | F61: =E61*$D61*(1+$J61) -> 525000 | G61: =F61*(1+$J61) -> 551250 | H61: =G61*(1+$J61) -> 578812.5 | I61: =H61*(1+$J61) -> 607753.12 | J61: =Assumptions!$D$27 -> 0.05
B62: Internet and telephone bills | C62: Variable | D62: 2 | E62: 30000 | F62: =E62*$D62*(1+$J62) -> 63000 | G62: =F62*(1+$J62) -> 66150 | H62: =G62*(1+$J62) -> 69457.5 | I62: =H62*(1+$J62) -> 72930.375 | J62: =Assumptions!$D$27 -> 0.05
B63: Labour | C63: Variable | D63: 2 | E63: 25000 | F63: =E63*$D63*(1+$J63) -> 52500 | G63: =F63*(1+$J63) -> 55125 | H63: =G63*(1+$J63) -> 57881.25 | I63: =H63*(1+$J63) -> 60775.312 | J63: =Assumptions!$D$27 -> 0.05
B64: Total variable overheads | E64: =SUM(E56:E63) -> 996250 | F64: =SUM(F56:F63) -> 1962125 | G64: =SUM(G56:G63) -> 2067381.2 | H64: =SUM(H56:H63) -> 2178615.3 | I64: =SUM(I56:I63) -> 2296197.6
B65: Office materials | C65: Fixed | D65: 2 | E65: 25000 | F65: =E65*$D65*(1+$J65) -> 55000 | G65: =F65*(1+$J65) -> 60500 | H65: =G65*(1+$J65) -> 66550 | I65: =H65*(1+$J65) -> 73205 | J65: =Assumptions!$D$25 -> 0.1
B66: Maintenance cost | C66: Fixed | D66: 2 | E66: 100000 | F66: =E66*$D66*(1+$J66) -> 220000 | G66: =F66*(1+$J66) -> 242000 | H66: =G66*(1+$J66) -> 266200 | I66: =H66*(1+$J66) -> 292820 | J66: =Assumptions!$D$25 -> 0.1
B67: Salary for hatchery manager | C67: Fixed | D67: 2 | E67: =60000*6 -> 360000 | F67: =E67*$D67*(1+$J67) -> 756000 | G67: =F67*(1+$J67) -> 793800 | H67: =G67*(1+$J67) -> 833490 | I67: =H67*(1+$J67) -> 875164.5 | J67: =Assumptions!$D$23 -> 0.05
B68: Salary for 4 technicians | C68: Fixed | D68: 1 | E68: =15000*4*6 -> 360000 | F68: =E68*$D68*(1+$J68) -> 378000 | G68: =F68*(1+$J68) -> 396900 | H68: =G68*(1+$J68) -> 416745 | I68: =H68*(1+$J68) -> 437582.25 | J68: =Assumptions!$D$23 -> 0.05
B69: Salary for night watchman | C69: Fixed | D69: 1 | E69: =8000*3*6 -> 144000 | F69: =E69*$D69*(1+$J69) -> 151200 | G69: =F69*(1+$J69) -> 158760 | H69: =G69*(1+$J69) -> 166698 | I69: =H69*(1+$J69) -> 175032.9 | J69: =Assumptions!$D$23 -> 0.05
B70: Festival bonus | C70: Fixed | E70: =SUM(E67:E69)/12 -> 72000 | F70: =SUM(F67:F69)/12 -> 107100 | G70: =SUM(G67:G69)/12 -> 112455 | H70: =SUM(H67:H69)/12 -> 118077.75 | I70: =SUM(I67:I69)/12 -> 123981.64
B71: Administration | C71: Fixed | D71: 2 | E71: 50000 | F71: =E71*$D71*(1+$J71) -> 100000 | G71: =F71*(1+$J71) -> 100000 | H71: =G71*(1+$J71) -> 100000 | I71: =H71*(1+$J71) -> 100000
B72: Contingency (% of the fixed items above) | C72: Fixed | D72: 0.05 | E72: =SUM(E65:E71)*$D72 -> 55550 | F72: =SUM(F65:F71)*$D72 -> 88365 | G72: =SUM(G65:G71)*$D72 -> 93220.75 | H72: =SUM(H65:H71)*$D72 -> 98388.038 | I72: =SUM(I65:I71)*$D72 -> 103889.31
B73: Total fixed overheads | E73: =SUM(E65:E72) -> 1166550 | F73: =SUM(F65:F72) -> 1855665 | G73: =SUM(G65:G72) -> 1957635.8 | H73: =SUM(H65:H72) -> 2066148.8 | I73: =SUM(I65:I72) -> 2181675.6
B75: Year 5 repeats Year 4 quantities.

Sheet Working Capital
B1: Working Capital and Cash Cycle
B2: Receivables, inventory and payables are driven by days.
B3: ="Scenario: "&Assumptions!$D$11&" | BDT '000 unless stated" -> Scenario: Base case | BDT '000 unless stated
B4: Financial year | C4: Unit | D4: Opening | E4: ="FY"&(Assumptions!$D$7+E5-1)&"-"&TEXT(MOD(Assumptions!$D$7+E5,100),"00") -> FY2026-27 | F4: ="FY"&(Assumptions!$D$7+F5-1)&"-"&TEXT(MOD(Assumptions!$D$7+F5,100),"00") -> FY2027-28 | G4: ="FY"&(Assumptions!$D$7+G5-1)&"-"&TEXT(MOD(Assumptions!$D$7+G5,100),"00") -> FY2028-29 | H4: ="FY"&(Assumptions!$D$7+H5-1)&"-"&TEXT(MOD(Assumptions!$D$7+H5,100),"00") -> FY2029-30 | I4: ="FY"&(Assumptions!$D$7+I5-1)&"-"&TEXT(MOD(Assumptions!$D$7+I5,100),"00") -> FY2030-31
D5: 0 | E5: 1 | F5: 2 | G5: 3 | H5: 4 | I5: 5
B7: Base for the calculation
B8: Revenue | C8: BDT | E8: =Operations!E16 -> 12080000 | F8: =Operations!F16 -> 49717500 | G8: =Operations!G16 -> 66811500 | H8: =Operations!H16 -> 83059594 | I8: =Operations!I16 -> 75543713
B9: Cost of sales (direct costs and factory overheads) | C9: BDT | E9: =Operations!E35+Operations!E36 -> 8681334 | F9: =Operations!F35+Operations!F36 -> 22562346 | G9: =Operations!G35+Operations!G36 -> 29776102 | H9: =Operations!H35+Operations!H36 -> 30865272 | I9: =Operations!I35+Operations!I36 -> 32009687
B11: Working capital balances
B12: Trade receivables | C12: BDT | D12: 0 | E12: =E8*Assumptions!$D$64/365 -> 992876.71 | F12: =F8*Assumptions!$D$64/365 -> 4086369.9 | G12: =G8*Assumptions!$D$64/365 -> 5491356.2 | H12: =H8*Assumptions!$D$64/365 -> 6826815.9 | I12: =I8*Assumptions!$D$64/365 -> 6209072.3
B13: Inventory (feed, fingerlings, stock on hand) | C13: BDT | D13: 0 | E13: =E9*Assumptions!$D$65/365 -> 2140602.9 | F13: =F9*Assumptions!$D$65/365 -> 5563318.1 | G13: =G9*Assumptions!$D$65/365 -> 7342052.5 | H13: =H9*Assumptions!$D$65/365 -> 7610615 | I13: =I9*Assumptions!$D$65/365 -> 7892799.5
B14: Trade payables | C14: BDT | D14: 0 | E14: =E9*Assumptions!$D$66/365 -> 713534.3 | F14: =F9*Assumptions!$D$66/365 -> 1854439.4 | G14: =G9*Assumptions!$D$66/365 -> 2447350.8 | H14: =H9*Assumptions!$D$66/365 -> 2536871.7 | I14: =I9*Assumptions!$D$66/365 -> 2630933.2
B15: Net working capital | C15: BDT | D15: =D12+D13-D14 -> 0 | E15: =E12+E13-E14 -> 2419945.3 | F15: =F12+F13-F14 -> 7795248.6 | G15: =G12+G13-G14 -> 10386058 | H15: =H12+H13-H14 -> 11900559 | I15: =I12+I13-I14 -> 11470939
B16: Increase in net working capital (cash outflow) | C16: BDT | E16: =E15-D15 -> 2419945.3 | F16: =F15-E15 -> 5375303.3 | G16: =G15-F15 -> 2590809.2 | H16: =H15-G15 -> 1514501.4 | I16: =I15-H15 -> -429620.56
B17: Net working capital as % of revenue | C17: % | E17: =IFERROR(E15/E8,0) -> 0.2003266 | F17: =IFERROR(F15/F8,0) -> 0.15679084 | G17: =IFERROR(G15/G8,0) -> 0.15545315 | H17: =IFERROR(H15/H8,0) -> 0.14327736 | I17: =IFERROR(I15/I8,0) -> 0.15184505
B19: Cash conversion cycle (days)
B20: Receivable days (DSO) | C20: days | E20: =Assumptions!$D$64 -> 30 | F20: =Assumptions!$D$64 -> 30 | G20: =Assumptions!$D$64 -> 30 | H20: =Assumptions!$D$64 -> 30 | I20: =Assumptions!$D$64 -> 30
B21: Inventory days (DIO) | C21: days | E21: =Assumptions!$D$65 -> 90 | F21: =Assumptions!$D$65 -> 90 | G21: =Assumptions!$D$65 -> 90 | H21: =Assumptions!$D$65 -> 90 | I21: =Assumptions!$D$65 -> 90
B22: Operating cycle (DSO + DIO) | C22: days | E22: =E20+E21 -> 120 | F22: =F20+F21 -> 120 | G22: =G20+G21 -> 120 | H22: =H20+H21 -> 120 | I22: =I20+I21 -> 120
B23: Payable days (DPO) | C23: days | E23: =Assumptions!$D$66 -> 30 | F23: =Assumptions!$D$66 -> 30 | G23: =Assumptions!$D$66 -> 30 | H23: =Assumptions!$D$66 -> 30 | I23: =Assumptions!$D$66 -> 30
B24: Cash conversion cycle (DSO + DIO - DPO) | C24: days | E24: =E22-E23 -> 90 | F24: =F22-F23 -> 90 | G24: =G22-G23 -> 90 | H24: =H22-H23 -> 90 | I24: =I22-I23 -> 90
B28: Chart data (Year 4)
B29: DSO | D29: =H20 -> 30
B30: DIO | D30: =H21 -> 90
B31: DPO | D31: =H23 -> 30
B32: Cycle | D32: =H24 -> 90

Sheet Funding
B1: Funding and Term Loan
B2: Sources and uses of funds at Year 0, the owner contribution and the bank loan schedule.
B3: ="Scenario: "&Assumptions!$D$11&" | BDT '000 unless stated" -> Scenario: Base case | BDT '000 unless stated
B4: Financial year | C4: Unit | D4: Opening | E4: ="FY"&(Assumptions!$D$7+E5-1)&"-"&TEXT(MOD(Assumptions!$D$7+E5,100),"00") -> FY2026-27 | F4: ="FY"&(Assumptions!$D$7+F5-1)&"-"&TEXT(MOD(Assumptions!$D$7+F5,100),"00") -> FY2027-28 | G4: ="FY"&(Assumptions!$D$7+G5-1)&"-"&TEXT(MOD(Assumptions!$D$7+G5,100),"00") -> FY2028-29 | H4: ="FY"&(Assumptions!$D$7+H5-1)&"-"&TEXT(MOD(Assumptions!$D$7+H5,100),"00") -> FY2029-30 | I4: ="FY"&(Assumptions!$D$7+I5-1)&"-"&TEXT(MOD(Assumptions!$D$7+I5,100),"00") -> FY2030-31
D5: 0 | E5: 1 | F5: 2 | G5: 3 | H5: 4 | I5: 5
B7: Uses of funds (Year 0)
B8: Land and ponds | C8: BDT | D8: ='FA Schedule'!D8+'FA Schedule'!D9 -> 20915783
B9: Buildings and overhead tank | C9: BDT | D9: ='FA Schedule'!D10+'FA Schedule'!D11 -> 19764147
B10: Equipment, vehicles, furniture and fixtures | C10: BDT | D10: ='FA Schedule'!D12+'FA Schedule'!D13+'FA Schedule'!D14 -> 5112312.5
B11: Fixed assets (project cost) | C11: BDT | D11: =SUM(D8:D10) -> 45792242
B12: Opening cash for Year 1 working capital | C12: BDT | D12: ='Working Capital'!E15 -> 2419945.3
B13: Total uses | C13: BDT | D13: =D11+D12 -> 48212188
B15: Sources of funds (Year 0)
B16: Bank term loan | C16: BDT | D16: =Assumptions!$D$41*D11 -> 22896121
B17: Owner equity | C17: BDT | D17: =D13-D16 -> 25316066
B18: Total sources | C18: BDT | D18: =D16+D17 -> 48212188
B19: Bank loan as % of total uses | C19: % | D19: =D16/D18 -> 0.47490318
B20: Owner contribution as % of total uses | C20: % | D20: =D17/D18 -> 0.52509682
B22: Financial year | C22: Unit | D22: Opening | E22: ="FY"&(Assumptions!$D$7+E23-1)&"-"&TEXT(MOD(Assumptions!$D$7+E23,100),"00") -> FY2026-27 | F22: ="FY"&(Assumptions!$D$7+F23-1)&"-"&TEXT(MOD(Assumptions!$D$7+F23,100),"00") -> FY2027-28 | G22: ="FY"&(Assumptions!$D$7+G23-1)&"-"&TEXT(MOD(Assumptions!$D$7+G23,100),"00") -> FY2028-29 | H22: ="FY"&(Assumptions!$D$7+H23-1)&"-"&TEXT(MOD(Assumptions!$D$7+H23,100),"00") -> FY2029-30 | I22: ="FY"&(Assumptions!$D$7+I23-1)&"-"&TEXT(MOD(Assumptions!$D$7+I23,100),"00") -> FY2030-31
D23: 0 | E23: 1 | F23: 2 | G23: 3 | H23: 4 | I23: 5
B24: Term loan schedule
B25: Repayment share of the loan | C25: % | E25: =IF(AND(E$23>Assumptions!$D$43,E$23<=Assumptions!$D$42),1/(Assumptions!$D$42-Assumptions!$D$43),0) -> 0 | F25: =IF(AND(F$23>Assumptions!$D$43,F$23<=Assumptions!$D$42),1/(Assumptions!$D$42-Assumptions!$D$43),0) -> 0.25 | G25: =IF(AND(G$23>Assumptions!$D$43,G$23<=Assumptions!$D$42),1/(Assumptions!$D$42-Assumptions!$D$43),0) -> 0.25 | H25: =IF(AND(H$23>Assumptions!$D$43,H$23<=Assumptions!$D$42),1/(Assumptions!$D$42-Assumptions!$D$43),0) -> 0.25 | I25: =IF(AND(I$23>Assumptions!$D$43,I$23<=Assumptions!$D$42),1/(Assumptions!$D$42-Assumptions!$D$43),0) -> 0.25
B26: Opening balance | C26: BDT | E26: =D29 -> 22896121 | F26: =E29 -> 22896121 | G26: =F29 -> 17172091 | H26: =G29 -> 11448061 | I26: =H29 -> 5724030.3
B27: Drawdown | C27: BDT | D27: =D16 -> 22896121
B28: Repayment | C28: BDT | E28: =E25*$D16 -> 0 | F28: =F25*$D16 -> 5724030.3 | G28: =G25*$D16 -> 5724030.3 | H28: =H25*$D16 -> 5724030.3 | I28: =I25*$D16 -> 5724030.3
B29: Closing balance | C29: BDT | D29: =D27 -> 22896121 | E29: =E26+E27-E28 -> 22896121 | F29: =F26+F27-F28 -> 17172091 | G29: =G26+G27-G28 -> 11448061 | H29: =H26+H27-H28 -> 5724030.3 | I29: =I26+I27-I28 -> 0
B31: Interest rate (loan rate plus scenario add-on) | C31: % | E31: =Assumptions!$D$40+Assumptions!$G$18 -> 0.12 | F31: =Assumptions!$D$40+Assumptions!$G$18 -> 0.12 | G31: =Assumptions!$D$40+Assumptions!$G$18 -> 0.12 | H31: =Assumptions!$D$40+Assumptions!$G$18 -> 0.12 | I31: =Assumptions!$D$40+Assumptions!$G$18 -> 0.12
B32: Interest (on opening balance) | C32: BDT | E32: =E26*E31 -> 2747534.5 | F32: =F26*F31 -> 2747534.5 | G32: =G26*G31 -> 2060650.9 | H32: =H26*H31 -> 1373767.3 | I32: =I26*I31 -> 686883.63
B33: Total debt service (interest + repayment) | C33: BDT | E33: =E32+E28 -> 2747534.5 | F33: =F32+F28 -> 8471564.8 | G33: =G32+G28 -> 7784681.2 | H33: =H32+H28 -> 7097797.5 | I33: =I32+I28 -> 6410913.9
B35: Interest on opening balance. The loan funds fixed assets only; the owner funds the rest.

Sheet Income Statement
B1: Projected Income Statement
B2: Farming and hatchery revenue and costs, with depreciation shown below EBITDA and interest on the bank loan. Costs are negative.
B3: ="Scenario: "&Assumptions!$D$11&" | BDT '000 unless stated" -> Scenario: Base case | BDT '000 unless stated
B4: Financial year | C4: Unit | D4: Opening | E4: ="FY"&(Assumptions!$D$7+E5-1)&"-"&TEXT(MOD(Assumptions!$D$7+E5,100),"00") -> FY2026-27 | F4: ="FY"&(Assumptions!$D$7+F5-1)&"-"&TEXT(MOD(Assumptions!$D$7+F5,100),"00") -> FY2027-28 | G4: ="FY"&(Assumptions!$D$7+G5-1)&"-"&TEXT(MOD(Assumptions!$D$7+G5,100),"00") -> FY2028-29 | H4: ="FY"&(Assumptions!$D$7+H5-1)&"-"&TEXT(MOD(Assumptions!$D$7+H5,100),"00") -> FY2029-30 | I4: ="FY"&(Assumptions!$D$7+I5-1)&"-"&TEXT(MOD(Assumptions!$D$7+I5,100),"00") -> FY2030-31
D5: 0 | E5: 1 | F5: 2 | G5: 3 | H5: 4 | I5: 5
B7: Revenue
B8: Hatchery | C8: BDT | E8: =Operations!E12 -> 9400000 | F8: =Operations!F12 -> 26880000 | G8: =Operations!G12 -> 42832125 | H8: =Operations!H12 -> 57881250 | I8: =Operations!I12 -> 49106453
B9: Farming | C9: BDT | E9: =Operations!E15 -> 2680000 | F9: =Operations!F15 -> 22837500 | G9: =Operations!G15 -> 23979375 | H9: =Operations!H15 -> 25178344 | I9: =Operations!I15 -> 26437261
B10: Total revenue | C10: BDT | E10: =SUM(E8:E9) -> 12080000 | F10: =SUM(F8:F9) -> 49717500 | G10: =SUM(G8:G9) -> 66811500 | H10: =SUM(H8:H9) -> 83059594 | I10: =SUM(I8:I9) -> 75543713
B11: Revenue growth | C11: % | F11: =IFERROR(F10/E10-1,0) -> 3.1156871 | G11: =IFERROR(G10/F10-1,0) -> 0.3438226 | H11: =IFERROR(H10/G10-1,0) -> 0.24319307 | I11: =IFERROR(I10/H10-1,0) -> -0.090487805
B13: Cost of sales
B14: Feed | C14: BDT | E14: =-Operations!E30 -> -5160084 | F14: =-Operations!F30 -> -15067721 | G14: =-Operations!G30 -> -19558720 | H14: =-Operations!H30 -> -20536657 | I14: =-Operations!I30 -> -21563489
B15: Broodstock and fingerlings | C15: BDT | E15: =-Operations!E33 -> -925000 | F15: =-Operations!F33 -> -1532500 | G15: =-Operations!G33 -> -1750000 | H15: =-Operations!H33 -> -1750000 | I15: =-Operations!I33 -> -1750000
B16: Hormone | C16: BDT | E16: =-Operations!E34 -> -1600000 | F16: =-Operations!F34 -> -4000000 | G16: =-Operations!G34 -> -6400000 | H16: =-Operations!H34 -> -6400000 | I16: =-Operations!I34 -> -6400000
B17: Factory overheads | C17: BDT | E17: =-Operations!E36 -> -996250 | F17: =-Operations!F36 -> -1962125 | G17: =-Operations!G36 -> -2067381.2 | H17: =-Operations!H36 -> -2178615.3 | I17: =-Operations!I36 -> -2296197.6
B18: Total cost of sales | C18: BDT | E18: =SUM(E14:E17) -> -8681334 | F18: =SUM(F14:F17) -> -22562346 | G18: =SUM(G14:G17) -> -29776102 | H18: =SUM(H14:H17) -> -30865272 | I18: =SUM(I14:I17) -> -32009687
B19: Gross profit | C19: BDT | E19: =E10+E18 -> 3398666 | F19: =F10+F18 -> 27155154 | G19: =G10+G18 -> 37035398 | H19: =H10+H18 -> 52194322 | I19: =I10+I18 -> 43534027
B20: Gross margin | C20: % | E20: =IFERROR(E19/E10,0) -> 0.28134652 | F20: =IFERROR(F19/F10,0) -> 0.54618906 | G20: =IFERROR(G19/G10,0) -> 0.5543267 | H20: =IFERROR(H19/H10,0) -> 0.62839607 | I20: =IFERROR(I19/I10,0) -> 0.57627597
B22: Operating expenses
B23: Administrative | C23: BDT | E23: =-Operations!E46 -> -1166550 | F23: =-Operations!F46 -> -1855665 | G23: =-Operations!G46 -> -1957635.8 | H23: =-Operations!H46 -> -2066148.8 | I23: =-Operations!I46 -> -2181675.6
B24: Marketing | C24: BDT | E24: =-Operations!E37 -> -188000 | F24: =-Operations!F37 -> -537600 | G24: =-Operations!G37 -> -856642.5 | H24: =-Operations!H37 -> -1157625 | I24: =-Operations!I37 -> -982129.05
B25: Selling | C25: BDT | E25: =-Operations!E38 -> -752000 | F25: =-Operations!F38 -> -2150400 | G25: =-Operations!G38 -> -3426570 | H25: =-Operations!H38 -> -4630500 | I25: =-Operations!I38 -> -3928516.2
B26: Distribution | C26: BDT | E26: =-Operations!E47 -> -500000 | F26: =-Operations!F47 -> -500000 | G26: =-Operations!G47 -> -500000 | H26: =-Operations!H47 -> -500000 | I26: =-Operations!I47 -> -500000
B27: Total operating expenses | C27: BDT | E27: =SUM(E23:E26) -> -2606550 | F27: =SUM(F23:F26) -> -5043665 | G27: =SUM(G23:G26) -> -6740848.2 | H27: =SUM(H23:H26) -> -8354273.8 | I27: =SUM(I23:I26) -> -7592320.9
B28: EBITDA | C28: BDT | E28: =E19+E27 -> 792115.99 | F28: =F19+F27 -> 22111489 | G28: =G19+G27 -> 30294550 | H28: =H19+H27 -> 43840048 | I28: =I19+I27 -> 35941706
B29: EBITDA margin | C29: % | E29: =IFERROR(E28/E10,0) -> 0.065572516 | F29: =IFERROR(F28/F10,0) -> 0.44474259 | G29: =IFERROR(G28/G10,0) -> 0.45343317 | H29: =IFERROR(H28/H10,0) -> 0.52781438 | I29: =IFERROR(I28/I10,0) -> 0.47577362
B30: Depreciation | C30: BDT | E30: =-'FA Schedule'!E24 -> -3098877.2 | F30: =-'FA Schedule'!F24 -> -3098877.2 | G30: =-'FA Schedule'!G24 -> -3298877.2 | H30: =-'FA Schedule'!H24 -> -3298877.2 | I30: =-'FA Schedule'!I24 -> -3298877.2
B31: EBIT | C31: BDT | E31: =E28+E30 -> -2306761.2 | F31: =F28+F30 -> 19012612 | G31: =G28+G30 -> 26995673 | H31: =H28+H30 -> 40541171 | I31: =I28+I30 -> 32642828
B32: Interest on term loan | C32: BDT | E32: =-Funding!E32 -> -2747534.5 | F32: =-Funding!F32 -> -2747534.5 | G32: =-Funding!G32 -> -2060650.9 | H32: =-Funding!H32 -> -1373767.3 | I32: =-Funding!I32 -> -686883.63
B33: Profit before tax | C33: BDT | E33: =E31+E32 -> -5054295.7 | F33: =F31+F32 -> 16265078 | G33: =G31+G32 -> 24935022 | H33: =H31+H32 -> 39167404 | I33: =I31+I32 -> 31955945
B34: Income tax | C34: BDT | E34: =-E43*Assumptions!$D$39 -> 0 | F34: =-F43*Assumptions!$D$39 -> -3082965.1 | G34: =-G43*Assumptions!$D$39 -> -6857131 | H34: =-H43*Assumptions!$D$39 -> -10771036 | I34: =-I43*Assumptions!$D$39 -> -8787884.8
B35: Net profit after tax | C35: BDT | E35: =E33+E34 -> -5054295.7 | F35: =F33+F34 -> 13182113 | G35: =G33+G34 -> 18077891 | H35: =H33+H34 -> 28396368 | I35: =I33+I34 -> 23168060
B36: Net margin | C36: % | E36: =IFERROR(E35/E10,0) -> -0.41840196 | F36: =IFERROR(F35/F10,0) -> 0.2651403 | G36: =IFERROR(G35/G10,0) -> 0.27058053 | H36: =IFERROR(H35/H10,0) -> 0.34187944 | I36: =IFERROR(I35/I10,0) -> 0.30668416
B38: Tax loss carried forward
B39: Tax loss, opening | C39: BDT | E39: 0 | F39: =E42 -> 5054295.7 | G39: =F42 -> 0 | H39: =G42 -> 0 | I39: =H42 -> 0
B40: Loss used against profit | C40: BDT | E40: =MIN(E39,MAX(E33,0)) -> 0 | F40: =MIN(F39,MAX(F33,0)) -> 5054295.7 | G40: =MIN(G39,MAX(G33,0)) -> 0 | H40: =MIN(H39,MAX(H33,0)) -> 0 | I40: =MIN(I39,MAX(I33,0)) -> 0
B41: Loss added | C41: BDT | E41: =MAX(-E33,0) -> 5054295.7 | F41: =MAX(-F33,0) -> 0 | G41: =MAX(-G33,0) -> 0 | H41: =MAX(-H33,0) -> 0 | I41: =MAX(-I33,0) -> 0
B42: Tax loss, closing | C42: BDT | E42: =E39-E40+E41 -> 5054295.7 | F42: =F39-F40+F41 -> 0 | G42: =G39-G40+G41 -> 0 | H42: =H39-H40+H41 -> 0 | I42: =I39-I40+I41 -> 0
B43: Taxable profit | C43: BDT | E43: =MAX(E33,0)-E40 -> 0 | F43: =MAX(F33,0)-F40 -> 11210782 | G43: =MAX(G33,0)-G40 -> 24935022 | H43: =MAX(H33,0)-H40 -> 39167404 | I43: =MAX(I33,0)-I40 -> 31955945

Sheet Cash Flow
B1: Projected Cash Flow Statement
B2: Indirect method. This single statement drives the balance sheet; owner funding and dividends are decided here.
B3: ="Scenario: "&Assumptions!$D$11&" | BDT '000 unless stated" -> Scenario: Base case | BDT '000 unless stated
B4: Financial year | C4: Unit | D4: Opening | E4: ="FY"&(Assumptions!$D$7+E5-1)&"-"&TEXT(MOD(Assumptions!$D$7+E5,100),"00") -> FY2026-27 | F4: ="FY"&(Assumptions!$D$7+F5-1)&"-"&TEXT(MOD(Assumptions!$D$7+F5,100),"00") -> FY2027-28 | G4: ="FY"&(Assumptions!$D$7+G5-1)&"-"&TEXT(MOD(Assumptions!$D$7+G5,100),"00") -> FY2028-29 | H4: ="FY"&(Assumptions!$D$7+H5-1)&"-"&TEXT(MOD(Assumptions!$D$7+H5,100),"00") -> FY2029-30 | I4: ="FY"&(Assumptions!$D$7+I5-1)&"-"&TEXT(MOD(Assumptions!$D$7+I5,100),"00") -> FY2030-31
D5: 0 | E5: 1 | F5: 2 | G5: 3 | H5: 4 | I5: 5
B7: Operating activities
B8: Net profit after tax | C8: BDT | E8: ='Income Statement'!E35 -> -5054295.7 | F8: ='Income Statement'!F35 -> 13182113 | G8: ='Income Statement'!G35 -> 18077891 | H8: ='Income Statement'!H35 -> 28396368 | I8: ='Income Statement'!I35 -> 23168060
B9: Add: depreciation | C9: BDT | E9: =-'Income Statement'!E30 -> 3098877.2 | F9: =-'Income Statement'!F30 -> 3098877.2 | G9: =-'Income Statement'!G30 -> 3298877.2 | H9: =-'Income Statement'!H30 -> 3298877.2 | I9: =-'Income Statement'!I30 -> 3298877.2
B10: Increase in receivables | C10: BDT | E10: =-('Working Capital'!E12-'Working Capital'!D12) -> -992876.71 | F10: =-('Working Capital'!F12-'Working Capital'!E12) -> -3093493.2 | G10: =-('Working Capital'!G12-'Working Capital'!F12) -> -1404986.3 | H10: =-('Working Capital'!H12-'Working Capital'!G12) -> -1335459.8 | I10: =-('Working Capital'!I12-'Working Capital'!H12) -> 617743.59
B11: Increase in inventory | C11: BDT | E11: =-('Working Capital'!E13-'Working Capital'!D13) -> -2140602.9 | F11: =-('Working Capital'!F13-'Working Capital'!E13) -> -3422715.2 | G11: =-('Working Capital'!G13-'Working Capital'!F13) -> -1778734.4 | H11: =-('Working Capital'!H13-'Working Capital'!G13) -> -268562.49 | I11: =-('Working Capital'!I13-'Working Capital'!H13) -> -282184.54
B12: Increase in payables | C12: BDT | E12: ='Working Capital'!E14-'Working Capital'!D14 -> 713534.3 | F12: ='Working Capital'!F14-'Working Capital'!E14 -> 1140905.1 | G12: ='Working Capital'!G14-'Working Capital'!F14 -> 592911.47 | H12: ='Working Capital'!H14-'Working Capital'!G14 -> 89520.829 | I12: ='Working Capital'!I14-'Working Capital'!H14 -> 94061.514
B13: Cash flow from operations | C13: BDT | E13: =SUM(E8:E12) -> -4375363.9 | F13: =SUM(F8:F12) -> 10905687 | G13: =SUM(G8:G12) -> 18785959 | H13: =SUM(H8:H12) -> 30180743 | I13: =SUM(I8:I12) -> 26896558
B15: Investing activities
B16: Capital expenditure | C16: BDT | D16: =-'FA Schedule'!D15 -> -45792242 | E16: =-'FA Schedule'!E15 -> 0 | F16: =-'FA Schedule'!F15 -> -5003000 | G16: =-'FA Schedule'!G15 -> 0 | H16: =-'FA Schedule'!H15 -> 0 | I16: =-'FA Schedule'!I15 -> 0
B17: Cash flow from investing | C17: BDT | D17: =D16 -> -45792242 | E17: =E16 -> 0 | F17: =F16 -> -5003000 | G17: =G16 -> 0 | H17: =H16 -> 0 | I17: =I16 -> 0
B19: Financing activities
B20: Term loan drawdown | C20: BDT | D20: =Funding!D27 -> 22896121 | E20: 0 | F20: 0 | G20: 0 | H20: 0 | I20: 0
B21: Term loan repayment | C21: BDT | E21: =-Funding!E28 -> 0 | F21: =-Funding!F28 -> -5724030.3 | G21: =-Funding!G28 -> -5724030.3 | H21: =-Funding!H28 -> -5724030.3 | I21: =-Funding!I28 -> -5724030.3
B22: Owner equity injected | C22: BDT | D22: =Funding!D17 -> 25316066 | E22: =MAX(0,Assumptions!$D$44-E25) -> 2455418.5 | F22: =MAX(0,Assumptions!$D$44-F25) -> 0 | G22: =MAX(0,Assumptions!$D$44-G25) -> 0 | H22: =MAX(0,Assumptions!$D$44-H25) -> 0 | I22: =MAX(0,Assumptions!$D$44-I25) -> 0
B23: Dividends paid to owner | C23: BDT | E23: =-MAX(0,MIN(Assumptions!$D$45*MAX(E8,0)*IF(D34+E8>0,1,0),E25+E22-Assumptions!$D$44)) -> 0 | F23: =-MAX(0,MIN(Assumptions!$D$45*MAX(F8,0)*IF(E34+F8>0,1,0),F25+F22-Assumptions!$D$44)) -> -178656.35 | G23: =-MAX(0,MIN(Assumptions!$D$45*MAX(G8,0)*IF(F34+G8>0,1,0),G25+G22-Assumptions!$D$44)) -> -10846735 | H23: =-MAX(0,MIN(Assumptions!$D$45*MAX(H8,0)*IF(G34+H8>0,1,0),H25+H22-Assumptions!$D$44)) -> -17037821 | I23: =-MAX(0,MIN(Assumptions!$D$45*MAX(I8,0)*IF(H34+I8>0,1,0),I25+I22-Assumptions!$D$44)) -> -13900836
B24: Cash flow from financing | C24: BDT | D24: =SUM(D20:D23) -> 48212188 | E24: =SUM(E20:E23) -> 2455418.5 | F24: =SUM(F20:F23) -> -5902686.6 | G24: =SUM(G20:G23) -> -16570765 | H24: =SUM(H20:H23) -> -22761851 | I24: =SUM(I20:I23) -> -19624866
B25: Cash before owner funding and dividends (memo) | C25: BDT | E25: =D30+E13+E17+E20+E21 -> -1955418.5 | F25: =E30+F13+F17+F20+F21 -> 678656.35 | G25: =F30+G13+G17+G20+G21 -> 13561929 | H25: =G30+H13+H17+H20+H21 -> 27171907 | I25: =H30+I13+I17+I20+I21 -> 31306614
B27: Cash position
B28: Net change in cash | C28: BDT | D28: =D13+D17+D24 -> 2419945.3 | E28: =E13+E17+E24 -> -1919945.3 | F28: =F13+F17+F24 -> 0 | G28: =G13+G17+G24 -> 2215194 | H28: =H13+H17+H24 -> 7418892.6 | I28: =I13+I17+I24 -> 7271691.5
B29: Opening cash | C29: BDT | D29: 0 | E29: =D30 -> 2419945.3 | F29: =E30 -> 500000 | G29: =F30 -> 500000 | H29: =G30 -> 2715194 | I29: =H30 -> 10134087
B30: Closing cash | C30: BDT | D30: =D28+D29 -> 2419945.3 | E30: =E28+E29 -> 500000 | F30: =F28+F29 -> 500000 | G30: =G28+G29 -> 2715194 | H30: =H28+H29 -> 10134087 | I30: =I28+I29 -> 17405778
B32: Owner account (memo)
B33: Owner equity invested, cumulative | C33: BDT | D33: =D22 -> 25316066 | E33: =D33+E22 -> 27771485 | F33: =E33+F22 -> 27771485 | G33: =F33+G22 -> 27771485 | H33: =G33+H22 -> 27771485 | I33: =H33+I22 -> 27771485
B34: Retained earnings, closing | C34: BDT | D34: 0 | E34: =D34+E8+E23 -> -5054295.7 | F34: =E34+F8+F23 -> 7949160.6 | G34: =F34+G8+G23 -> 15180317 | H34: =G34+H8+H23 -> 26538864 | I34: =H34+I8+I23 -> 35806088
B36: Cash Flow Generated (before loan repayment, owner funding and dividends)
B37: EBITDA | C37: BDT | E37: ='Income Statement'!E28 -> 792115.99 | F37: ='Income Statement'!F28 -> 22111489 | G37: ='Income Statement'!G28 -> 30294550 | H37: ='Income Statement'!H28 -> 43840048 | I37: ='Income Statement'!I28 -> 35941706
B38: Interest on term loan | C38: BDT | E38: ='Income Statement'!E32 -> -2747534.5 | F38: ='Income Statement'!F32 -> -2747534.5 | G38: ='Income Statement'!G32 -> -2060650.9 | H38: ='Income Statement'!H32 -> -1373767.3 | I38: ='Income Statement'!I32 -> -686883.63
B39: Income tax | C39: BDT | E39: ='Income Statement'!E34 -> 0 | F39: ='Income Statement'!F34 -> -3082965.1 | G39: ='Income Statement'!G34 -> -6857131 | H39: ='Income Statement'!H34 -> -10771036 | I39: ='Income Statement'!I34 -> -8787884.8
B40: Working capital changes | C40: BDT | E40: =SUM(E41:E43) -> -2419945.3 | F40: =SUM(F41:F43) -> -5375303.3 | G40: =SUM(G41:G43) -> -2590809.2 | H40: =SUM(H41:H43) -> -1514501.4 | I40: =SUM(I41:I43) -> 429620.56
B41: Inventory | C41: BDT | E41: =E11 -> -2140602.9 | F41: =F11 -> -3422715.2 | G41: =G11 -> -1778734.4 | H41: =H11 -> -268562.49 | I41: =I11 -> -282184.54
B42: Receivable | C42: BDT | E42: =E10 -> -992876.71 | F42: =F10 -> -3093493.2 | G42: =G10 -> -1404986.3 | H42: =H10 -> -1335459.8 | I42: =I10 -> 617743.59
B43: Payable | C43: BDT | E43: =E12 -> 713534.3 | F43: =F12 -> 1140905.1 | G43: =G12 -> 592911.47 | H43: =H12 -> 89520.829 | I43: =I12 -> 94061.514
B44: Capital expenditure | C44: BDT | E44: =E16 -> 0 | F44: =F16 -> -5003000 | G44: =G16 -> 0 | H44: =H16 -> 0 | I44: =I16 -> 0
B45: Cash Flow Generated | C45: BDT | E45: =E37+E38+E39+E40+E44 -> -4375363.9 | F45: =F37+F38+F39+F40+F44 -> 5902686.6 | G45: =G37+G38+G39+G40+G44 -> 18785959 | H45: =H37+H38+H39+H40+H44 -> 30180743 | I45: =I37+I38+I39+I40+I44 -> 26896558
B46: Cash flow from operations + investing (reconciliation) | C46: BDT | E46: =E13+E17 -> -4375363.9 | F46: =F13+F17 -> 5902686.6 | G46: =G13+G17 -> 18785959 | H46: =H13+H17 -> 30180743 | I46: =I13+I17 -> 26896558
B47: Difference (should be zero) | C47: BDT | E47: =E45-E46 -> 0 | F47: =F45-F46 -> 0 | G47: =G45-G46 -> 0 | H47: =H45-H46 -> 0 | I47: =I45-I46 -> 0
B50: Direct method (memo)
B51: Cash receipts from customers | C51: BDT | E51: ='Income Statement'!E10+E10 -> 11087123 | F51: ='Income Statement'!F10+F10 -> 46624007 | G51: ='Income Statement'!G10+G10 -> 65406514 | H51: ='Income Statement'!H10+H10 -> 81724134 | I51: ='Income Statement'!I10+I10 -> 76161457
B52: Cash paid to suppliers for cost of sales | C52: BDT | E52: ='Income Statement'!E18+E11+E12 -> -10108403 | F52: ='Income Statement'!F18+F11+F12 -> -24844156 | G52: ='Income Statement'!G18+G11+G12 -> -30961925 | H52: ='Income Statement'!H18+H11+H12 -> -31044313 | I52: ='Income Statement'!I18+I11+I12 -> -32197810
B53: Cash paid for operating expenses | C53: BDT | E53: ='Income Statement'!E27 -> -2606550 | F53: ='Income Statement'!F27 -> -5043665 | G53: ='Income Statement'!G27 -> -6740848.2 | H53: ='Income Statement'!H27 -> -8354273.8 | I53: ='Income Statement'!I27 -> -7592320.9
B54: Cash from operations before interest and tax | C54: BDT | E54: =SUM(E51:E53) -> -1627829.3 | F54: =SUM(F51:F53) -> 16736186 | G54: =SUM(G51:G53) -> 27703741 | H54: =SUM(H51:H53) -> 42325547 | I54: =SUM(I51:I53) -> 36371326
B55: Interest paid | C55: BDT | E55: ='Income Statement'!E32 -> -2747534.5 | F55: ='Income Statement'!F32 -> -2747534.5 | G55: ='Income Statement'!G32 -> -2060650.9 | H55: ='Income Statement'!H32 -> -1373767.3 | I55: ='Income Statement'!I32 -> -686883.63
B56: Income tax paid | C56: BDT | E56: ='Income Statement'!E34 -> 0 | F56: ='Income Statement'!F34 -> -3082965.1 | G56: ='Income Statement'!G34 -> -6857131 | H56: ='Income Statement'!H34 -> -10771036 | I56: ='Income Statement'!I34 -> -8787884.8
B57: Cash flow from operations (direct method) | C57: BDT | E57: =SUM(E54:E56) -> -4375363.9 | F57: =SUM(F54:F56) -> 10905687 | G57: =SUM(G54:G56) -> 18785959 | H57: =SUM(H54:H56) -> 30180743 | I57: =SUM(I54:I56) -> 26896558
B58: Capital expenditure | C58: BDT | E58: =E16 -> 0 | F58: =F16 -> -5003000 | G58: =G16 -> 0 | H58: =H16 -> 0 | I58: =I16 -> 0
B59: Cash Flow Generated (direct method) | C59: BDT | E59: =E57+E58 -> -4375363.9 | F59: =F57+F58 -> 5902686.6 | G59: =G57+G58 -> 18785959 | H59: =H57+H58 -> 30180743 | I59: =I57+I58 -> 26896558
B60: Difference from the indirect method (should be zero) | C60: BDT | E60: =E59-E45 -> 0 | F60: =F59-F45 -> 0 | G60: =G59-G45 -> 0 | H60: =H59-H45 -> 0 | I60: =I59-I45 -> 0

Sheet Balance Sheet
B1: Projected Balance Sheet
B2: Year-end positions. Share capital is the cumulative owner investment; the term loan comes from the Funding sheet.
B3: ="Scenario: "&Assumptions!$D$11&" | BDT '000 unless stated" -> Scenario: Base case | BDT '000 unless stated
B4: Financial year | C4: Unit | D4: Opening | E4: ="FY"&(Assumptions!$D$7+E5-1)&"-"&TEXT(MOD(Assumptions!$D$7+E5,100),"00") -> FY2026-27 | F4: ="FY"&(Assumptions!$D$7+F5-1)&"-"&TEXT(MOD(Assumptions!$D$7+F5,100),"00") -> FY2027-28 | G4: ="FY"&(Assumptions!$D$7+G5-1)&"-"&TEXT(MOD(Assumptions!$D$7+G5,100),"00") -> FY2028-29 | H4: ="FY"&(Assumptions!$D$7+H5-1)&"-"&TEXT(MOD(Assumptions!$D$7+H5,100),"00") -> FY2029-30 | I4: ="FY"&(Assumptions!$D$7+I5-1)&"-"&TEXT(MOD(Assumptions!$D$7+I5,100),"00") -> FY2030-31
D5: 0 | E5: 1 | F5: 2 | G5: 3 | H5: 4 | I5: 5
B7: Assets
B8: Fixed assets, net book value | C8: BDT | D8: ='FA Schedule'!D32 -> 45792242 | E8: ='FA Schedule'!E32 -> 42693365 | F8: ='FA Schedule'!F32 -> 44597488 | G8: ='FA Schedule'!G32 -> 41298611 | H8: ='FA Schedule'!H32 -> 37999733 | I8: ='FA Schedule'!I32 -> 34700856
B9: Trade receivables | C9: BDT | D9: ='Working Capital'!D12 -> 0 | E9: ='Working Capital'!E12 -> 992876.71 | F9: ='Working Capital'!F12 -> 4086369.9 | G9: ='Working Capital'!G12 -> 5491356.2 | H9: ='Working Capital'!H12 -> 6826815.9 | I9: ='Working Capital'!I12 -> 6209072.3
B10: Inventory | C10: BDT | D10: ='Working Capital'!D13 -> 0 | E10: ='Working Capital'!E13 -> 2140602.9 | F10: ='Working Capital'!F13 -> 5563318.1 | G10: ='Working Capital'!G13 -> 7342052.5 | H10: ='Working Capital'!H13 -> 7610615 | I10: ='Working Capital'!I13 -> 7892799.5
B11: Cash | C11: BDT | D11: ='Cash Flow'!D30 -> 2419945.3 | E11: ='Cash Flow'!E30 -> 500000 | F11: ='Cash Flow'!F30 -> 500000 | G11: ='Cash Flow'!G30 -> 2715194 | H11: ='Cash Flow'!H30 -> 10134087 | I11: ='Cash Flow'!I30 -> 17405778
B12: Total assets | C12: BDT | D12: =SUM(D8:D11) -> 48212188 | E12: =SUM(E8:E11) -> 46326845 | F12: =SUM(F8:F11) -> 54747176 | G12: =SUM(G8:G11) -> 56847213 | H12: =SUM(H8:H11) -> 62571251 | I12: =SUM(I8:I11) -> 66208506
B14: Liabilities
B15: Trade payables | C15: BDT | D15: ='Working Capital'!D14 -> 0 | E15: ='Working Capital'!E14 -> 713534.3 | F15: ='Working Capital'!F14 -> 1854439.4 | G15: ='Working Capital'!G14 -> 2447350.8 | H15: ='Working Capital'!H14 -> 2536871.7 | I15: ='Working Capital'!I14 -> 2630933.2
B16: Term loan (bank) | C16: BDT | D16: =Funding!D29 -> 22896121 | E16: =Funding!E29 -> 22896121 | F16: =Funding!F29 -> 17172091 | G16: =Funding!G29 -> 11448061 | H16: =Funding!H29 -> 5724030.3 | I16: =Funding!I29 -> 0
B17: Total liabilities | C17: BDT | D17: =D15+D16 -> 22896121 | E17: =E15+E16 -> 23609655 | F17: =F15+F16 -> 19026530 | G17: =G15+G16 -> 13895411 | H17: =H15+H16 -> 8260901.9 | I17: =I15+I16 -> 2630933.2
B19: Owner equity
B20: Share capital (owner investment) | C20: BDT | D20: ='Cash Flow'!D33 -> 25316066 | E20: ='Cash Flow'!E33 -> 27771485 | F20: ='Cash Flow'!F33 -> 27771485 | G20: ='Cash Flow'!G33 -> 27771485 | H20: ='Cash Flow'!H33 -> 27771485 | I20: ='Cash Flow'!I33 -> 27771485
B21: Retained earnings | C21: BDT | D21: ='Cash Flow'!D34 -> 0 | E21: ='Cash Flow'!E34 -> -5054295.7 | F21: ='Cash Flow'!F34 -> 7949160.6 | G21: ='Cash Flow'!G34 -> 15180317 | H21: ='Cash Flow'!H34 -> 26538864 | I21: ='Cash Flow'!I34 -> 35806088
B22: Total owner equity | C22: BDT | D22: =D20+D21 -> 25316066 | E22: =E20+E21 -> 22717189 | F22: =F20+F21 -> 35720646 | G22: =G20+G21 -> 42951802 | H22: =H20+H21 -> 54310349 | I22: =I20+I21 -> 63577573
B23: Total liabilities and equity | C23: BDT | D23: =D17+D22 -> 48212188 | E23: =E17+E22 -> 46326845 | F23: =F17+F22 -> 54747176 | G23: =G17+G22 -> 56847213 | H23: =H17+H22 -> 62571251 | I23: =I17+I22 -> 66208506
B25: Balance check (assets less liabilities and equity) | C25: BDT | D25: =ROUND(D12-D23,0) -> 0 | E25: =ROUND(E12-E23,0) -> 0 | F25: =ROUND(F12-F23,0) -> 0 | G25: =ROUND(G12-G23,0) -> 0 | H25: =ROUND(H12-H23,0) -> 0 | I25: =ROUND(I12-I23,0) -> 0

Sheet Segment Analysis
B1: Segment Analysis: Hatchery and Farming
B2: Revenue, cost and profit of each business, using the assumed allocation (70% hatchery / 30% farming for shared cost, depreciation and interest).
B3: ="Scenario: "&Assumptions!$D$11&" | BDT '000 unless stated" -> Scenario: Base case | BDT '000 unless stated
B4: Financial year | C4: Unit | D4: Opening | E4: ="FY"&(Assumptions!$D$7+E5-1)&"-"&TEXT(MOD(Assumptions!$D$7+E5,100),"00") -> FY2026-27 | F4: ="FY"&(Assumptions!$D$7+F5-1)&"-"&TEXT(MOD(Assumptions!$D$7+F5,100),"00") -> FY2027-28 | G4: ="FY"&(Assumptions!$D$7+G5-1)&"-"&TEXT(MOD(Assumptions!$D$7+G5,100),"00") -> FY2028-29 | H4: ="FY"&(Assumptions!$D$7+H5-1)&"-"&TEXT(MOD(Assumptions!$D$7+H5,100),"00") -> FY2029-30 | I4: ="FY"&(Assumptions!$D$7+I5-1)&"-"&TEXT(MOD(Assumptions!$D$7+I5,100),"00") -> FY2030-31
D5: 0 | E5: 1 | F5: 2 | G5: 3 | H5: 4 | I5: 5
B7: Hatchery
B8: Revenue | C8: BDT | E8: =Operations!E12 -> 9400000 | F8: =Operations!F12 -> 26880000 | G8: =Operations!G12 -> 42832125 | H8: =Operations!H12 -> 57881250 | I8: =Operations!I12 -> 49106453
B9: Direct costs (feed, stock, hormone) | C9: BDT | E9: =-(Operations!E28+Operations!E31+Operations!E34) -> -4005084 | F9: =-(Operations!F28+Operations!F31+Operations!F34) -> -10295221 | G9: =-(Operations!G28+Operations!G31+Operations!G34) -> -16946970 | H9: =-(Operations!H28+Operations!H31+Operations!H34) -> -17445319 | I9: =-(Operations!I28+Operations!I31+Operations!I34) -> -17968585
B10: Factory overheads | C10: BDT | E10: =-(Assumptions!$D$59*Operations!E36) -> -697375 | F10: =-(Assumptions!$D$59*Operations!F36) -> -1373487.5 | G10: =-(Assumptions!$D$59*Operations!G36) -> -1447166.9 | H10: =-(Assumptions!$D$59*Operations!H36) -> -1525030.7 | I10: =-(Assumptions!$D$59*Operations!I36) -> -1607338.3
B11: Gross profit | C11: BDT | E11: =SUM(E8:E10) -> 4697541 | F11: =SUM(F8:F10) -> 15211292 | G11: =SUM(G8:G10) -> 24437988 | H11: =SUM(H8:H10) -> 38910900 | I11: =SUM(I8:I10) -> 29530529
B12: Gross margin | C12: % | E12: =IFERROR(E11/E8,0) -> 0.4997384 | F12: =IFERROR(F11/F8,0) -> 0.56589628 | G12: =IFERROR(G11/G8,0) -> 0.57055277 | H12: =IFERROR(H11/H8,0) -> 0.67225397 | I12: =IFERROR(I11/I8,0) -> 0.60135741
B13: Administrative | C13: BDT | E13: =-(Assumptions!$D$59*Operations!E46) -> -816585 | F13: =-(Assumptions!$D$59*Operations!F46) -> -1298965.5 | G13: =-(Assumptions!$D$59*Operations!G46) -> -1370345 | H13: =-(Assumptions!$D$59*Operations!H46) -> -1446304.2 | I13: =-(Assumptions!$D$59*Operations!I46) -> -1527172.9
B14: Marketing, selling and distribution | C14: BDT | E14: =-(Operations!E37+Operations!E38+Operations!E47) -> -1440000 | F14: =-(Operations!F37+Operations!F38+Operations!F47) -> -3188000 | G14: =-(Operations!G37+Operations!G38+Operations!G47) -> -4783212.5 | H14: =-(Operations!H37+Operations!H38+Operations!H47) -> -6288125 | I14: =-(Operations!I37+Operations!I38+Operations!I47) -> -5410645.3
B15: EBITDA | C15: BDT | E15: =E11+E13+E14 -> 2440956 | F15: =F11+F13+F14 -> 10724326 | G15: =G11+G13+G14 -> 18284430 | H15: =H11+H13+H14 -> 31176471 | I15: =I11+I13+I14 -> 22592711
B16: Depreciation | C16: BDT | E16: =-(Assumptions!$D$59*'FA Schedule'!E24) -> -2169214 | F16: =-(Assumptions!$D$59*'FA Schedule'!F24) -> -2169214 | G16: =-(Assumptions!$D$59*'FA Schedule'!G24) -> -2309214 | H16: =-(Assumptions!$D$59*'FA Schedule'!H24) -> -2309214 | I16: =-(Assumptions!$D$59*'FA Schedule'!I24) -> -2309214
B17: Interest | C17: BDT | E17: =-(Assumptions!$D$59*Funding!E32) -> -1923274.2 | F17: =-(Assumptions!$D$59*Funding!F32) -> -1923274.2 | G17: =-(Assumptions!$D$59*Funding!G32) -> -1442455.6 | H17: =-(Assumptions!$D$59*Funding!H32) -> -961637.09 | I17: =-(Assumptions!$D$59*Funding!I32) -> -480818.54
B18: Profit before tax | C18: BDT | E18: =E15+E16+E17 -> -1651532.2 | F18: =F15+F16+F17 -> 6631838.3 | G18: =G15+G16+G17 -> 14532760 | H18: =H15+H16+H17 -> 27905620 | I18: =I15+I16+I17 -> 19802678
B19: EBITDA margin | C19: % | E19: =IFERROR(E15/E8,0) -> 0.25967617 | F19: =IFERROR(F15/F8,0) -> 0.39897048 | G19: =IFERROR(G15/G8,0) -> 0.4268859 | H19: =IFERROR(H15/H8,0) -> 0.53862816 | I19: =IFERROR(I15/I8,0) -> 0.46007622
B21: Farming
B22: Revenue | C22: BDT | E22: =Operations!E15 -> 2680000 | F22: =Operations!F15 -> 22837500 | G22: =Operations!G15 -> 23979375 | H22: =Operations!H15 -> 25178344 | I22: =Operations!I15 -> 26437261
B23: Direct costs (feed, stock, hormone) | C23: BDT | E23: =-(Operations!E29+Operations!E32) -> -3680000 | F23: =-(Operations!F29+Operations!F32) -> -10305000 | G23: =-(Operations!G29+Operations!G32) -> -10761750 | H23: =-(Operations!H29+Operations!H32) -> -11241338 | I23: =-(Operations!I29+Operations!I32) -> -11744904
B24: Factory overheads | C24: BDT | E24: =-(Assumptions!$D$60*Operations!E36) -> -298875 | F24: =-(Assumptions!$D$60*Operations!F36) -> -588637.5 | G24: =-(Assumptions!$D$60*Operations!G36) -> -620214.38 | H24: =-(Assumptions!$D$60*Operations!H36) -> -653584.59 | I24: =-(Assumptions!$D$60*Operations!I36) -> -688859.27
B25: Gross profit | C25: BDT | E25: =SUM(E22:E24) -> -1298875 | F25: =SUM(F22:F24) -> 11943862 | G25: =SUM(G22:G24) -> 12597411 | H25: =SUM(H22:H24) -> 13283422 | I25: =SUM(I22:I24) -> 14003497
B26: Gross margin | C26: % | E26: =IFERROR(E25/E22,0) -> -0.48465485 | F26: =IFERROR(F25/F22,0) -> 0.52299343 | G26: =IFERROR(G25/G22,0) -> 0.52534358 | H26: =IFERROR(H25/H22,0) -> 0.52757329 | I26: =IFERROR(I25/I22,0) -> 0.5296879
B27: Administrative | C27: BDT | E27: =-(Assumptions!$D$60*Operations!E46) -> -349965 | F27: =-(Assumptions!$D$60*Operations!F46) -> -556699.5 | G27: =-(Assumptions!$D$60*Operations!G46) -> -587290.73 | H27: =-(Assumptions!$D$60*Operations!H46) -> -619844.64 | I27: =-(Assumptions!$D$60*Operations!I46) -> -654502.68
B28: Marketing, selling and distribution | C28: BDT | E28: =-(0) -> 0 | F28: =-(0) -> 0 | G28: =-(0) -> 0 | H28: =-(0) -> 0 | I28: =-(0) -> 0
B29: EBITDA | C29: BDT | E29: =E25+E27+E28 -> -1648840 | F29: =F25+F27+F28 -> 11387163 | G29: =G25+G27+G28 -> 12010120 | H29: =H25+H27+H28 -> 12663577 | I29: =I25+I27+I28 -> 13348995
B30: Depreciation | C30: BDT | E30: =-(Assumptions!$D$60*'FA Schedule'!E24) -> -929663.16 | F30: =-(Assumptions!$D$60*'FA Schedule'!F24) -> -929663.16 | G30: =-(Assumptions!$D$60*'FA Schedule'!G24) -> -989663.16 | H30: =-(Assumptions!$D$60*'FA Schedule'!H24) -> -989663.16 | I30: =-(Assumptions!$D$60*'FA Schedule'!I24) -> -989663.16
B31: Interest | C31: BDT | E31: =-(Assumptions!$D$60*Funding!E32) -> -824260.36 | F31: =-(Assumptions!$D$60*Funding!F32) -> -824260.36 | G31: =-(Assumptions!$D$60*Funding!G32) -> -618195.27 | H31: =-(Assumptions!$D$60*Funding!H32) -> -412130.18 | I31: =-(Assumptions!$D$60*Funding!I32) -> -206065.09
B32: Profit before tax | C32: BDT | E32: =E29+E30+E31 -> -3402763.5 | F32: =F29+F30+F31 -> 9633239.5 | G32: =G29+G30+G31 -> 10402261 | H32: =H29+H30+H31 -> 11261784 | I32: =I29+I30+I31 -> 12153266
B33: EBITDA margin | C33: % | E33: =IFERROR(E29/E22,0) -> -0.61523881 | F33: =IFERROR(F29/F22,0) -> 0.49861688 | G33: =IFERROR(G29/G22,0) -> 0.50085208 | H33: =IFERROR(H29/H22,0) -> 0.50295512 | I33: =IFERROR(I29/I22,0) -> 0.50493108
B35: Summary: revenue, cost and profit by segment
B36: Hatchery: revenue | C36: BDT | E36: =E8 -> 9400000 | F36: =F8 -> 26880000 | G36: =G8 -> 42832125 | H36: =H8 -> 57881250 | I36: =I8 -> 49106453
B37: Hatchery: total cost (all costs including depreciation and interest) | C37: BDT | E37: =E18-E8 -> -11051532 | F37: =F18-F8 -> -20248162 | G37: =G18-G8 -> -28299365 | H37: =H18-H8 -> -29975630 | I37: =I18-I8 -> -29303774
B38: Hatchery: profit before tax | C38: BDT | E38: =E18 -> -1651532.2 | F38: =F18 -> 6631838.3 | G38: =G18 -> 14532760 | H38: =H18 -> 27905620 | I38: =I18 -> 19802678
B39: Farming: revenue | C39: BDT | E39: =E22 -> 2680000 | F39: =F22 -> 22837500 | G39: =G22 -> 23979375 | H39: =H22 -> 25178344 | I39: =I22 -> 26437261
B40: Farming: total cost (all costs including depreciation and interest) | C40: BDT | E40: =E32-E22 -> -6082763.5 | F40: =F32-F22 -> -13204261 | G40: =G32-G22 -> -13577114 | H40: =H32-H22 -> -13916560 | I40: =I32-I22 -> -14283995
B41: Farming: profit before tax | C41: BDT | E41: =E32 -> -3402763.5 | F41: =F32 -> 9633239.5 | G41: =G32 -> 10402261 | H41: =H32 -> 11261784 | I41: =I32 -> 12153266
B42: Total revenue | C42: BDT | E42: =E36+E39 -> 12080000 | F42: =F36+F39 -> 49717500 | G42: =G36+G39 -> 66811500 | H42: =H36+H39 -> 83059594 | I42: =I36+I39 -> 75543713
B43: Total cost | C43: BDT | E43: =E37+E40 -> -17134296 | F43: =F37+F40 -> -33452422 | G43: =G37+G40 -> -41876478 | H43: =H37+H40 -> -43892190 | I43: =I37+I40 -> -43587769
B44: Total profit before tax | C44: BDT | E44: =E38+E41 -> -5054295.7 | F44: =F38+F41 -> 16265078 | G44: =G38+G41 -> 24935022 | H44: =H38+H41 -> 39167404 | I44: =I38+I41 -> 31955945
B46: Share of total
B47: Hatchery: share of revenue | C47: % | E47: =IFERROR(E36/E42,0) -> 0.7781457 | F47: =IFERROR(F36/F42,0) -> 0.5406547 | G47: =IFERROR(G36/G42,0) -> 0.64108911 | H47: =IFERROR(H36/H42,0) -> 0.69686411 | I47: =IFERROR(I36/I42,0) -> 0.65004023
B48: Farming: share of revenue | C48: % | E48: =IFERROR(E39/E42,0) -> 0.2218543 | F48: =IFERROR(F39/F42,0) -> 0.4593453 | G48: =IFERROR(G39/G42,0) -> 0.35891089 | H48: =IFERROR(H39/H42,0) -> 0.30313589 | I48: =IFERROR(I39/I42,0) -> 0.34995977
B49: Hatchery: share of profit before tax | C49: % | E49: =IFERROR(E38/E44,0) -> 0.32675813 | F49: =IFERROR(F38/F44,0) -> 0.4077348 | G49: =IFERROR(G38/G44,0) -> 0.58282525 | H49: =IFERROR(H38/H44,0) -> 0.71247051 | I49: =IFERROR(I38/I44,0) -> 0.61968684
B50: Farming: share of profit before tax | C50: % | E50: =IFERROR(E41/E44,0) -> 0.67324187 | F50: =IFERROR(F41/F44,0) -> 0.5922652 | G50: =IFERROR(G41/G44,0) -> 0.41717475 | H50: =IFERROR(H41/H44,0) -> 0.28752949 | I50: =IFERROR(I41/I44,0) -> 0.38031316
B52: Capital and return (shared fixed assets split by the hatchery share)
B53: Hatchery: net fixed assets | C53: BDT | D53: =Assumptions!$D$59*'FA Schedule'!D32 -> 32054570 | E53: =Assumptions!$D$59*'FA Schedule'!E32 -> 29885356 | F53: =Assumptions!$D$59*'FA Schedule'!F32 -> 31218241 | G53: =Assumptions!$D$59*'FA Schedule'!G32 -> 28909027 | H53: =Assumptions!$D$59*'FA Schedule'!H32 -> 26599813 | I53: =Assumptions!$D$59*'FA Schedule'!I32 -> 24290599
B54: Farming: net fixed assets | C54: BDT | D54: =Assumptions!$D$60*'FA Schedule'!D32 -> 13737673 | E54: =Assumptions!$D$60*'FA Schedule'!E32 -> 12808010 | F54: =Assumptions!$D$60*'FA Schedule'!F32 -> 13379246 | G54: =Assumptions!$D$60*'FA Schedule'!G32 -> 12389583 | H54: =Assumptions!$D$60*'FA Schedule'!H32 -> 11399920 | I54: =Assumptions!$D$60*'FA Schedule'!I32 -> 10410257
B55: Hatchery: EBIT / net fixed assets | C55: % | E55: =IFERROR((E15+E16)/E53,0) -> 0.0090928133 | F55: =IFERROR((F15+F16)/F53,0) -> 0.2740421 | G55: =IFERROR((G15+G16)/G53,0) -> 0.55260303 | H55: =IFERROR((H15+H16)/H53,0) -> 1.0852428 | I55: =IFERROR((I15+I16)/I53,0) -> 0.83503485
B56: Farming: EBIT / net fixed assets | C56: % | E56: =IFERROR((E29+E30)/E54,0) -> -0.20131958 | F56: =IFERROR((F29+F30)/F54,0) -> 0.781621 | G56: =IFERROR((G29+G30)/G54,0) -> 0.88949374 | H56: =IFERROR((H29+H30)/H54,0) -> 1.0240347 | I56: =IFERROR((I29+I30)/I54,0) -> 1.1872264
B58: Remarks (update with the active scenario)
B59: ="Year 4 profit before tax: hatchery "&TEXT(H38/1000000,"0.0")&" million, farming "&TEXT(H41/1000000,"0.0")&" million (BDT)." -> Year 4 profit before tax: hatchery 27.9 million, farming 11.3 million (BDT).
B60: ="Hatchery brings "&TEXT(H47,"0%")&" of Year 4 revenue and "&TEXT(H49,"0%")&" of profit before tax." -> Hatchery brings 70% of Year 4 revenue and 71% of profit before tax.
B61: ="Farming brings "&TEXT(H48,"0%")&" of revenue and "&TEXT(H50,"0%")&" of profit; in Year 1 farming has only one harvest, so its early loss is expected." -> Farming brings 30% of revenue and 29% of profit; in Year 1 farming has only one harvest, so its early loss is expected.
B62: ="Shared costs, depreciation and interest follow the 70/30 split." -> Shared costs, depreciation and interest follow the 70/30 split.

Sheet Investment Analysis
B1: Investment Analysis
B2: Project cash flow before financing, NPV, IRR and payback. Year 0 is the construction year.
B3: ="Scenario: "&Assumptions!$D$11&" | BDT '000 unless stated" -> Scenario: Base case | BDT '000 unless stated
B4: Financial year | C4: Unit | D4: Opening | E4: ="FY"&(Assumptions!$D$7+E5-1)&"-"&TEXT(MOD(Assumptions!$D$7+E5,100),"00") -> FY2026-27 | F4: ="FY"&(Assumptions!$D$7+F5-1)&"-"&TEXT(MOD(Assumptions!$D$7+F5,100),"00") -> FY2027-28 | G4: ="FY"&(Assumptions!$D$7+G5-1)&"-"&TEXT(MOD(Assumptions!$D$7+G5,100),"00") -> FY2028-29 | H4: ="FY"&(Assumptions!$D$7+H5-1)&"-"&TEXT(MOD(Assumptions!$D$7+H5,100),"00") -> FY2029-30 | I4: ="FY"&(Assumptions!$D$7+I5-1)&"-"&TEXT(MOD(Assumptions!$D$7+I5,100),"00") -> FY2030-31
D5: 0 | E5: 1 | F5: 2 | G5: 3 | H5: 4 | I5: 5
B7: Discount rate: weighted average cost of capital (WACC)
B8: Interest rate on the term loan (before tax) | C8: % | D8: =Assumptions!$D$40 -> 0.12
B9: Corporate income tax rate | C9: % | D9: =Assumptions!$D$39 -> 0.275
B10: Cost of debt after tax = interest x (1 - tax) | C10: % | D10: =D8*(1-D9) -> 0.087
B11: Cost of equity (input on Assumptions) | C11: % | D11: =Assumptions!$D$48 -> 0.2
B12: Bank loan at Year 0 | C12: BDT | D12: =Funding!D16 -> 22896121
B13: Owner equity at Year 0 | C13: BDT | D13: =Funding!D17 -> 25316066
B14: Weight of debt = loan / (loan + equity) | C14: % | D14: =D12/(D12+D13) -> 0.47490318
B15: Weight of equity = equity / (loan + equity) | C15: % | D15: =D13/(D12+D13) -> 0.52509682
B16: WACC = weight of debt x cost of debt + weight of equity x cost of equity | C16: % | D16: =D14*D10+D15*D11 -> 0.14633594 | F16: This rate discounts every cash flow below
B18: Project cash flow (before financing)
B19: EBITDA | C19: BDT | E19: ='Income Statement'!E28 -> 792115.99 | F19: ='Income Statement'!F28 -> 22111489 | G19: ='Income Statement'!G28 -> 30294550 | H19: ='Income Statement'!H28 -> 43840048 | I19: ='Income Statement'!I28 -> 35941706
B20: Tax on operating profit (no financing benefit) | C20: BDT | E20: =-MAX(0,'Income Statement'!E31)*Assumptions!$D$39 -> 0 | F20: =-MAX(0,'Income Statement'!F31)*Assumptions!$D$39 -> -5228468.4 | G20: =-MAX(0,'Income Statement'!G31)*Assumptions!$D$39 -> -7423810 | H20: =-MAX(0,'Income Statement'!H31)*Assumptions!$D$39 -> -11148822 | I20: =-MAX(0,'Income Statement'!I31)*Assumptions!$D$39 -> -8976777.8
B21: Capital expenditure | C21: BDT | D21: ='Cash Flow'!D16 -> -45792242 | E21: ='Cash Flow'!E16 -> 0 | F21: ='Cash Flow'!F16 -> -5003000 | G21: ='Cash Flow'!G16 -> 0 | H21: ='Cash Flow'!H16 -> 0 | I21: ='Cash Flow'!I16 -> 0
B22: Increase in working capital | C22: BDT | E22: =-'Working Capital'!E16 -> -2419945.3 | F22: =-'Working Capital'!F16 -> -5375303.3 | G22: =-'Working Capital'!G16 -> -2590809.2 | H22: =-'Working Capital'!H16 -> -1514501.4 | I22: =-'Working Capital'!I16 -> 429620.56
B23: Project free cash flow | C23: BDT | D23: =SUM(D19:D22) -> -45792242 | E23: =SUM(E19:E22) -> -1627829.3 | F23: =SUM(F19:F22) -> 6504717.8 | G23: =SUM(G19:G22) -> 20279931 | H23: =SUM(H19:H22) -> 31176725 | I23: =SUM(I19:I22) -> 27394548
B24: Cumulative cash flow | C24: BDT | D24: =D23 -> -45792242 | E24: =D24+E23 -> -47420072 | F24: =E24+F23 -> -40915354 | G24: =F24+G23 -> -20635423 | H24: =G24+H23 -> 10541302 | I24: =H24+I23 -> 37935850
B25: Discount factor | C25: x | D25: =1/(1+Assumptions!$D$49)^D$5 -> 1 | E25: =1/(1+Assumptions!$D$49)^E$5 -> 0.87234463 | F25: =1/(1+Assumptions!$D$49)^F$5 -> 0.76098515 | G25: =1/(1+Assumptions!$D$49)^G$5 -> 0.66384131 | H25: =1/(1+Assumptions!$D$49)^H$5 -> 0.5790984 | I25: =1/(1+Assumptions!$D$49)^I$5 -> 0.50517338
B26: Present value of cash flow | C26: BDT | D26: =D23*D25 -> -45792242 | E26: =E23*E25 -> -1420028.2 | F26: =F23*F25 -> 4949993.7 | G26: =G23*G25 -> 13462656 | H26: =H23*H25 -> 18054391 | I26: =I23*I25 -> 13838997
B27: Cumulative present value | C27: BDT | D27: =D26 -> -45792242 | E27: =D27+E26 -> -47212270 | F27: =E27+F26 -> -42262277 | G27: =F27+G26 -> -28799621 | H27: =G27+H26 -> -10745230 | I27: =H27+I26 -> 3093767
B29: Recovery value at the end of Year 5 (land taken at the adjusted value)
B30: Land, ponds and buildings | C30: BDT | I30: =Assumptions!$D$83*(SUM('FA Schedule'!$D8:$I8)*(1+Assumptions!$D$82)+SUM('FA Schedule'!$D9:$I9)+SUM('FA Schedule'!$D10:$I10)) -> 42674622
B31: Equipment, vehicles, furniture and tank | C31: BDT | I31: =Assumptions!$D$87*SUM('FA Schedule'!$D12:$I12)+Assumptions!$D$85*SUM('FA Schedule'!$D13:$I13)+Assumptions!$D$84*SUM('FA Schedule'!$D14:$I14)+Assumptions!$D$86*SUM('FA Schedule'!$D11:$I11) -> 405615.62
B32: Release of working capital | C32: BDT | I32: ='Working Capital'!I15 -> 11470939
B33: Total recovery value | C33: BDT | I33: =SUM(I30:I32) -> 54551176
B34: Project cash flow including recovery | C34: BDT | D34: =D23+D33 -> -45792242 | E34: =E23+E33 -> -1627829.3 | F34: =F23+F33 -> 6504717.8 | G34: =G23+G33 -> 20279931 | H34: =H23+H33 -> 31176725 | I34: =I23+I33 -> 81945725
B36: Investment measures
B37: Discount rate | C37: % | D37: =Assumptions!$D$49 -> 0.14633594
B38: Net present value (5 years, without recovery value) | C38: BDT | D38: =NPV(Assumptions!$D$49,E23:I23)+D23 -> 3093767 | F38: Positive = the project earns more than the required return
B39: Internal rate of return (without recovery value) | C39: % | D39: =IFERROR(IRR(D23:I23),"n/a") -> 0.1657819 | F39: Compare with the discount rate
B40: Modified IRR (finance and reinvestment at loan rate) | C40: % | D40: =IFERROR(MIRR(D23:I23,Assumptions!$D$40,Assumptions!$D$40),"n/a") -> 0.15447268
B41: Profitability index (PV of inflows / investment) | C41: x | D41: =IFERROR(SUM(E26:I26)/-D26,0) -> 1.0675609 | F41: Above 1.0 is favourable
B42: Payback period | C42: years | D42: =IF(COUNTIF(D24:I24,"<0")>5,"> 5",(COUNTIF(D24:I24,"<0")-1)+(-INDEX(D24:I24,COUNTIF(D24:I24,"<0")))/INDEX(D23:I23,COUNTIF(D24:I24,"<0")+1)) -> 3.6618855 | F42: Years until cumulative cash flow turns positive
B43: Discounted payback period | C43: years | D43: =IF(COUNTIF(D27:I27,"<0")>5,"> 5",(COUNTIF(D27:I27,"<0")-1)+(-INDEX(D27:I27,COUNTIF(D27:I27,"<0")))/INDEX(D26:I26,COUNTIF(D27:I27,"<0")+1)) -> 4.7764457
B44: Net present value including recovery value | C44: BDT | D44: =NPV(Assumptions!$D$49,E34:I34)+D34 -> 30651569 | F44: Adds the end-of-Year-5 recovery of assets and working capital
B45: IRR including recovery value | C45: % | D45: =IFERROR(IRR(D34:I34),"n/a") -> 0.29333206
B46: Decision (including recovery value) | D46: =IF(AND(D44>0,ISNUMBER(D45)),IF(D45>Assumptions!$D$49,"ACCEPT: NPV is positive and IRR is above the required return","REVIEW: IRR is below the required return"),"REJECT: NPV is negative") -> ACCEPT: NPV is positive and IRR is above the required return
B47: Note on the 5-year view | D47: ="Without recovery value the 5-year NPV is BDT "&TEXT(D38/1000000,"0.0")&" million and IRR "&IF(ISNUMBER(D39),TEXT(D39,"0.0%"),"n/a")&": value comes from assets and earnings that continue beyond Year 5." -> Without recovery value the 5-year NPV is BDT 3.1 million and IRR 16.6%: value comes from assets and earnings that continue beyond Year 5.

Sheet Owner Returns
B1: Owner Investment and Dividends
B2: How much the owner puts in, and how much the project pays back as dividends.
B3: ="Scenario: "&Assumptions!$D$11&" | BDT '000 unless stated" -> Scenario: Base case | BDT '000 unless stated
B4: Financial year | C4: Unit | D4: Opening | E4: ="FY"&(Assumptions!$D$7+E5-1)&"-"&TEXT(MOD(Assumptions!$D$7+E5,100),"00") -> FY2026-27 | F4: ="FY"&(Assumptions!$D$7+F5-1)&"-"&TEXT(MOD(Assumptions!$D$7+F5,100),"00") -> FY2027-28 | G4: ="FY"&(Assumptions!$D$7+G5-1)&"-"&TEXT(MOD(Assumptions!$D$7+G5,100),"00") -> FY2028-29 | H4: ="FY"&(Assumptions!$D$7+H5-1)&"-"&TEXT(MOD(Assumptions!$D$7+H5,100),"00") -> FY2029-30 | I4: ="FY"&(Assumptions!$D$7+I5-1)&"-"&TEXT(MOD(Assumptions!$D$7+I5,100),"00") -> FY2030-31
D5: 0 | E5: 1 | F5: 2 | G5: 3 | H5: 4 | I5: 5
B7: Owner investment
B8: Initial equity (Year 0) | C8: BDT | D8: ='Cash Flow'!D22 -> 25316066
B9: Further equity injected (to keep minimum cash) | C9: BDT | E9: ='Cash Flow'!E22 -> 2455418.5 | F9: ='Cash Flow'!F22 -> 0 | G9: ='Cash Flow'!G22 -> 0 | H9: ='Cash Flow'!H22 -> 0 | I9: ='Cash Flow'!I22 -> 0
B10: Total owner investment in the year | C10: BDT | D10: =SUM(D8:D9) -> 25316066 | E10: =SUM(E8:E9) -> 2455418.5 | F10: =SUM(F8:F9) -> 0 | G10: =SUM(G8:G9) -> 0 | H10: =SUM(H8:H9) -> 0 | I10: =SUM(I8:I9) -> 0
B11: Owner investment, cumulative | C11: BDT | D11: =D10 -> 25316066 | E11: =D11+E10 -> 27771485 | F11: =E11+F10 -> 27771485 | G11: =F11+G10 -> 27771485 | H11: =G11+H10 -> 27771485 | I11: =H11+I10 -> 27771485
B13: Dividends
B14: Net profit after tax | C14: BDT | E14: ='Income Statement'!E35 -> -5054295.7 | F14: ='Income Statement'!F35 -> 13182113 | G14: ='Income Statement'!G35 -> 18077891 | H14: ='Income Statement'!H35 -> 28396368 | I14: ='Income Statement'!I35 -> 23168060
B15: Dividends paid to owner | C15: BDT | E15: =-'Cash Flow'!E23 -> 0 | F15: =-'Cash Flow'!F23 -> 178656.35 | G15: =-'Cash Flow'!G23 -> 10846735 | H15: =-'Cash Flow'!H23 -> 17037821 | I15: =-'Cash Flow'!I23 -> 13900836
B16: Payout ratio (dividend / net profit) | C16: % | E16: =IF(E14>0,E15/E14,0) -> 0 | F16: =IF(F14>0,F15/F14,0) -> 0.013552938 | G16: =IF(G14>0,G15/G14,0) -> 0.6 | H16: =IF(H14>0,H15/H14,0) -> 0.6 | I16: =IF(I14>0,I15/I14,0) -> 0.6
B17: Dividends, cumulative | C17: BDT | E17: =E15 -> 0 | F17: =E17+F15 -> 178656.35 | G17: =F17+G15 -> 11025391 | H17: =G17+H15 -> 28063211 | I17: =H17+I15 -> 41964048
B18: Cumulative dividends as % of owner investment | C18: % | E18: =E17/E11 -> 0 | F18: =F17/F11 -> 0.006433086 | G18: =G17/G11 -> 0.39700401 | H18: =H17/H11 -> 1.0105045 | I18: =I17/I11 -> 1.511048
B19: Dividend yield on owner investment | C19: % | E19: =E15/E11 -> 0 | F19: =F15/F11 -> 0.006433086 | G19: =G15/G11 -> 0.39057092 | H19: =H15/H11 -> 0.61350053 | I19: =I15/I11 -> 0.50054349
B20: Retained earnings, closing | C20: BDT | D20: ='Balance Sheet'!D21 -> 0 | E20: ='Balance Sheet'!E21 -> -5054295.7 | F20: ='Balance Sheet'!F21 -> 7949160.6 | G20: ='Balance Sheet'!G21 -> 15180317 | H20: ='Balance Sheet'!H21 -> 26538864 | I20: ='Balance Sheet'!I21 -> 35806088
B21: Owner equity (book value), closing | C21: BDT | D21: ='Balance Sheet'!D22 -> 25316066 | E21: ='Balance Sheet'!E22 -> 22717189 | F21: ='Balance Sheet'!F22 -> 35720646 | G21: ='Balance Sheet'!G22 -> 42951802 | H21: ='Balance Sheet'!H22 -> 54310349 | I21: ='Balance Sheet'!I22 -> 63577573
B23: Owner cash flows and returns
B24: Free cash flow to equity (after debt service, before dividends) | C24: BDT | E24: ='Cash Flow'!E13+'Cash Flow'!E17+'Cash Flow'!E21 -> -4375363.9 | F24: ='Cash Flow'!F13+'Cash Flow'!F17+'Cash Flow'!F21 -> 178656.35 | G24: ='Cash Flow'!G13+'Cash Flow'!G17+'Cash Flow'!G21 -> 13061929 | H24: ='Cash Flow'!H13+'Cash Flow'!H17+'Cash Flow'!H21 -> 24456713 | I24: ='Cash Flow'!I13+'Cash Flow'!I17+'Cash Flow'!I21 -> 21172527
B25: Owner cash flow: dividends only | C25: BDT | D25: =-D10 -> -25316066 | E25: =E15-E9 -> -2455418.5 | F25: =F15-F9 -> 178656.35 | G25: =G15-G9 -> 10846735 | H25: =H15-H9 -> 17037821 | I25: =I15-I9 -> 13900836
B26: Owner cash flow including book equity at end of Year 5 | C26: BDT | D26: =D25 -> -25316066 | E26: =E25 -> -2455418.5 | F26: =F25 -> 178656.35 | G26: =G25 -> 10846735 | H26: =H25 -> 17037821 | I26: =I25+I21 -> 77478409
B28: Summary for the owner
B29: Total invested by the owner | C29: BDT | D29: =I11 -> 27771485
B30: Total dividends received in 5 years | C30: BDT | D30: =I17 -> 41964048
B31: Dividends as % of owner investment | C31: % | D31: =D30/D29 -> 1.511048
B32: Owner equity at end of Year 5 (book value) | C32: BDT | D32: =I21 -> 63577573
B33: Dividends plus equity value, as multiple of investment | C33: x | D33: =(D30+D32)/D29 -> 3.8003593
B34: Owner IRR on dividends only | C34: % | D34: =IFERROR(IRR(D25:I25),"n/a") -> 0.11021278
B35: Owner IRR including book equity at end of Year 5 | C35: % | D35: =IFERROR(IRR(D26:I26),"n/a") -> 0.34750685
B37: ="The owner invests BDT "&TEXT(D29/1000000,"0.0")&" million and receives BDT "&TEXT(D30/1000000,"0.0")&" million in dividends over 5 years ("&TEXT(D31,"0%")&" of the investment). Book equity at the end of Year 5 is BDT "&TEXT(D32/1000000,"0.0")&" million." -> The owner invests BDT 27.8 million and receives BDT 42.0 million in dividends over 5 years (151% of the investment). Book equity at the end of Year 5 is BDT 63.6 million.
B40: The IRR on dividends only is low in a 5-year view because most of the value sits in the assets.

Sheet Loan Analysis
B1: Loan Analysis for the Bank
B2: What a lender checks before sanctioning a term loan: repayment capacity, leverage, security and a benchmark scorecard.
B3: ="Scenario: "&Assumptions!$D$11&" | BDT '000 unless stated" -> Scenario: Base case | BDT '000 unless stated
B4: Financial year | C4: Unit | D4: Opening | E4: ="FY"&(Assumptions!$D$7+E5-1)&"-"&TEXT(MOD(Assumptions!$D$7+E5,100),"00") -> FY2026-27 | F4: ="FY"&(Assumptions!$D$7+F5-1)&"-"&TEXT(MOD(Assumptions!$D$7+F5,100),"00") -> FY2027-28 | G4: ="FY"&(Assumptions!$D$7+G5-1)&"-"&TEXT(MOD(Assumptions!$D$7+G5,100),"00") -> FY2028-29 | H4: ="FY"&(Assumptions!$D$7+H5-1)&"-"&TEXT(MOD(Assumptions!$D$7+H5,100),"00") -> FY2029-30 | I4: ="FY"&(Assumptions!$D$7+I5-1)&"-"&TEXT(MOD(Assumptions!$D$7+I5,100),"00") -> FY2030-31
D5: 0 | E5: 1 | F5: 2 | G5: 3 | H5: 4 | I5: 5
B7: Repayment capacity
B8: EBITDA | C8: BDT | E8: ='Income Statement'!E28 -> 792115.99 | F8: ='Income Statement'!F28 -> 22111489 | G8: ='Income Statement'!G28 -> 30294550 | H8: ='Income Statement'!H28 -> 43840048 | I8: ='Income Statement'!I28 -> 35941706
B9: Less: income tax paid | C9: BDT | E9: ='Income Statement'!E34 -> 0 | F9: ='Income Statement'!F34 -> -3082965.1 | G9: ='Income Statement'!G34 -> -6857131 | H9: ='Income Statement'!H34 -> -10771036 | I9: ='Income Statement'!I34 -> -8787884.8
B10: Less: increase in working capital | C10: BDT | E10: =-'Working Capital'!E16 -> -2419945.3 | F10: =-'Working Capital'!F16 -> -5375303.3 | G10: =-'Working Capital'!G16 -> -2590809.2 | H10: =-'Working Capital'!H16 -> -1514501.4 | I10: =-'Working Capital'!I16 -> 429620.56
B11: Cash flow available for debt service (CFADS) | C11: BDT | E11: =SUM(E8:E10) -> -1627829.3 | F11: =SUM(F8:F10) -> 13653221 | G11: =SUM(G8:G10) -> 20846610 | H11: =SUM(H8:H10) -> 31554511 | I11: =SUM(I8:I10) -> 27583441
B12: Interest | C12: BDT | E12: =Funding!E32 -> 2747534.5 | F12: =Funding!F32 -> 2747534.5 | G12: =Funding!G32 -> 2060650.9 | H12: =Funding!H32 -> 1373767.3 | I12: =Funding!I32 -> 686883.63
B13: Principal repayment | C13: BDT | E13: =Funding!E28 -> 0 | F13: =Funding!F28 -> 5724030.3 | G13: =Funding!G28 -> 5724030.3 | H13: =Funding!H28 -> 5724030.3 | I13: =Funding!I28 -> 5724030.3
B14: Total debt service | C14: BDT | E14: =E12+E13 -> 2747534.5 | F14: =F12+F13 -> 8471564.8 | G14: =G12+G13 -> 7784681.2 | H14: =H12+H13 -> 7097797.5 | I14: =I12+I13 -> 6410913.9
B15: Debt Service Coverage Ratio (DSCR) = CFADS / debt service | C15: x | E15: =IF(E14>0,E11/E14,"n/a") -> -0.5924691 | F15: =IF(F14>0,F11/F14,"n/a") -> 1.6116528 | G15: =IF(G14>0,G11/G14,"n/a") -> 2.6779015 | H15: =IF(H14>0,H11/H14,"n/a") -> 4.4456764 | I15: =IF(I14>0,I11/I14,"n/a") -> 4.3025755
B16: Interest cover (EBIT / interest) | C16: x | E16: =IF(E12>0,'Income Statement'!E31/E12,"n/a") -> -0.83957496 | F16: =IF(F12>0,'Income Statement'!F31/F12,"n/a") -> 6.9198811 | G16: =IF(G12>0,'Income Statement'!G31/G12,"n/a") -> 13.100556 | H16: =IF(H12>0,'Income Statement'!H31/H12,"n/a") -> 29.510946 | I16: =IF(I12>0,'Income Statement'!I31/I12,"n/a") -> 47.523084
B17: EBITDA / interest | C17: x | E17: =IF(E12>0,E8/E12,"n/a") -> 0.28830065 | F17: =IF(F12>0,F8/F12,"n/a") -> 8.0477567 | G17: =IF(G12>0,G8/G12,"n/a") -> 14.701447 | H17: =IF(H12>0,H8/H12,"n/a") -> 31.912282 | I17: =IF(I12>0,I8/I12,"n/a") -> 52.325756
B18: Debt Service Coverage Ratio in repayment years (used in the scorecard) | C18: x | E18: =IF(E13>0,E15,"") | F18: =IF(F13>0,F15,"") -> 1.6116528 | G18: =IF(G13>0,G15,"") -> 2.6779015 | H18: =IF(H13>0,H15,"") -> 4.4456764 | I18: =IF(I13>0,I15,"") -> 4.3025755
B19: Interest cover in repayment years (used in the scorecard) | C19: x | E19: =IF(E13>0,E16,"") | F19: =IF(F13>0,F16,"") -> 6.9198811 | G19: =IF(G13>0,G16,"") -> 13.100556 | H19: =IF(H13>0,H16,"") -> 29.510946 | I19: =IF(I13>0,I16,"") -> 47.523084
B20: Year 1 is a ramp-up year with interest only (grace period); lenders test cover from the first repayment year.
B22: Leverage and security
B23: Term loan outstanding, closing | C23: BDT | D23: =Funding!D29 -> 22896121 | E23: =Funding!E29 -> 22896121 | F23: =Funding!F29 -> 17172091 | G23: =Funding!G29 -> 11448061 | H23: =Funding!H29 -> 5724030.3 | I23: =Funding!I29 -> 0
B24: Debt to equity | C24: x | D24: =IFERROR(D23/'Balance Sheet'!D22,0) -> 0.90441069 | E24: =IFERROR(E23/'Balance Sheet'!E22,0) -> 1.0078765 | F24: =IFERROR(F23/'Balance Sheet'!F22,0) -> 0.48073294 | G24: =IFERROR(G23/'Balance Sheet'!G22,0) -> 0.26653272 | H24: =IFERROR(H23/'Balance Sheet'!H22,0) -> 0.10539484 | I24: =IFERROR(I23/'Balance Sheet'!I22,0) -> 0
B25: Debt to EBITDA | C25: x | E25: =IF(E8>0,E23/E8,"n/a") -> 28.905011 | F25: =IF(F8>0,F23/F8,"n/a") -> 0.77661393 | G25: =IF(G8>0,G23/G8,"n/a") -> 0.37789175 | H25: =IF(H8>0,H23/H8,"n/a") -> 0.13056624 | I25: =IF(I8>0,I23/I8,"n/a") -> 0
B26: Fixed assets (net book value) / loan | C26: x | D26: =IF(D23>0,'FA Schedule'!D32/D23,"n/a") -> 2 | E26: =IF(E23>0,'FA Schedule'!E32/E23,"n/a") -> 1.8646549 | F26: =IF(F23>0,'FA Schedule'!F32/F23,"n/a") -> 2.5970913 | G26: =IF(G23>0,'FA Schedule'!G32/G23,"n/a") -> 3.6074766 | H26: =IF(H23>0,'FA Schedule'!H32/H23,"n/a") -> 6.6386325 | I26: =IF(I23>0,'FA Schedule'!I32/I23,"n/a") -> n/a
B27: Security value after forced-sale discount | C27: BDT | D27: ='FA Schedule'!D34*(1-Assumptions!$D$56) -> 29759947 | E27: ='FA Schedule'!E34*(1-Assumptions!$D$56) -> 29759947 | F27: ='FA Schedule'!F34*(1-Assumptions!$D$56) -> 33512197 | G27: ='FA Schedule'!G34*(1-Assumptions!$D$56) -> 33512197 | H27: ='FA Schedule'!H34*(1-Assumptions!$D$56) -> 33512197 | I27: ='FA Schedule'!I34*(1-Assumptions!$D$56) -> 33512197
B28: Collateral cover (security / loan outstanding) | C28: x | D28: =IF(D23>0,D27/D23,"n/a") -> 1.2997812 | E28: =IF(E23>0,E27/E23,"n/a") -> 1.2997812 | F28: =IF(F23>0,F27/F23,"n/a") -> 1.9515502 | G28: =IF(G23>0,G27/G23,"n/a") -> 2.9273253 | H28: =IF(H23>0,H27/H23,"n/a") -> 5.8546506 | I28: =IF(I23>0,I27/I23,"n/a") -> n/a
B29: Current ratio (receivables + inventory + cash) / (payables + loan due next year) | C29: x | E29: =IFERROR(('Balance Sheet'!E9+'Balance Sheet'!E10+'Balance Sheet'!E11)/('Balance Sheet'!E15+Funding!F28),0) -> 0.56441836 | F29: =IFERROR(('Balance Sheet'!F9+'Balance Sheet'!F10+'Balance Sheet'!F11)/('Balance Sheet'!F15+Funding!G28),0) -> 1.3392794 | G29: =IFERROR(('Balance Sheet'!G9+'Balance Sheet'!G10+'Balance Sheet'!G11)/('Balance Sheet'!G15+Funding!H28),0) -> 1.9028121 | H29: =IFERROR(('Balance Sheet'!H9+'Balance Sheet'!H10+'Balance Sheet'!H11)/('Balance Sheet'!H15+Funding!I28),0) -> 2.9744352 | I29: =IFERROR(('Balance Sheet'!I9+'Balance Sheet'!I10+'Balance Sheet'!I11)/('Balance Sheet'!I15+0),0) -> 11.975846
B30: Current ratio in repayment years (used in the scorecard) | C30: x | E30: =IF(E13>0,E29,"") | F30: =IF(F13>0,F29,"") -> 1.3392794 | G30: =IF(G13>0,G29,"") -> 1.9028121 | H30: =IF(H13>0,H29,"") -> 2.9744352 | I30: =IF(I13>0,I29,"") -> 11.975846
B31: Loan life cover ratio, Year 1 view (PV of CFADS / loan) | C31: x | E31: =NPV(Funding!E31,E11:I11)/D23 -> 2.6193999
B33: Credit scorecard against bank benchmarks
B34: Criterion | D34: Benchmark | E34: Actual | F34: Result
B35: Minimum Debt Service Coverage Ratio (DSCR) in repayment years | D35: =Assumptions!$D$50 -> 1.25 | E35: =MIN(E18:I18) -> 1.6116528 | F35: =IF(E35>=D35+0.000001,"PASS","FAIL") -> PASS
B36: Average Debt Service Coverage Ratio (DSCR) in repayment years | D36: =Assumptions!$D$50 -> 1.25 | E36: =AVERAGE(E18:I18) -> 3.2594516 | F36: =IF(E36>=D36+0.000001,"PASS","FAIL") -> PASS
B37: Minimum interest cover in repayment years (EBIT / interest) | D37: =Assumptions!$D$51 -> 2 | E37: =MIN(E19:I19) -> 6.9198811 | F37: =IF(E37>=D37+0.000001,"PASS","FAIL") -> PASS
B38: Debt to equity at drawdown | D38: =Assumptions!$D$52 -> 2 | E38: =D24 -> 0.90441069 | F38: =IF(E38<=D38+0.000001,"PASS","FAIL") -> PASS
B39: Collateral cover at drawdown | D39: =Assumptions!$D$53 -> 1.25 | E39: =D28 -> 1.2997812 | F39: =IF(E39>=D39+0.000001,"PASS","FAIL") -> PASS
B40: Owner contribution to total uses | D40: =Assumptions!$D$55 -> 0.3 | E40: =Funding!D20 -> 0.52509682 | F40: =IF(E40>=D40+0.000001,"PASS","FAIL") -> PASS
B41: Minimum current ratio in repayment years | D41: =Assumptions!$D$54 -> 1.2 | E41: =MIN(E30:I30) -> 1.3392794 | F41: =IF(E41>=D41+0.000001,"PASS","FAIL") -> PASS
B42: Loan fully repaid within tenor | D42: 0 | E42: =I23 -> 0 | F42: =IF(E42<=D42+0.000001,"PASS","FAIL") -> PASS
B43: Benchmarks met | C43: count | D43: =COUNTIF(F35:F42,"PASS") -> 8 | E43: =ROWS(F35:F42) -> 8
B44: =IF(D43=E43,"Result: the project meets all 8 lending benchmarks in the "&Assumptions!$D$11&".","Result: "&D43&" of "&E43&" benchmarks met in the "&Assumptions!$D$11&". Review the FAIL lines before sanction.") -> Result: the project meets all 8 lending benchmarks in the Base case.
B46: The five Cs of credit
B47: Capacity: Repayment from cash flow | D47: ="Minimum Debt Service Coverage Ratio "&TEXT(E35,"0.00")&"x; average "&TEXT(E36,"0.00")&"x against a covenant of "&TEXT(D35,"0.00")&"x" -> Minimum Debt Service Coverage Ratio 1.61x; average 3.26x against a covenant of 1.25x
B48: Capital: Owner stake in the project | D48: ="Owner puts in "&TEXT(E40,"0%")&" of total uses (benchmark "&TEXT(D40,"0%")&")" -> Owner puts in 53% of total uses (benchmark 30%)
B49: Collateral: Security for the lender | D49: ="Land, ponds and buildings after a "&TEXT(Assumptions!$D$56,"0%")&" discount cover the loan "&TEXT(E39,"0.00")&"x" -> Land, ponds and buildings after a 25% discount cover the loan 1.30x
B50: Conditions: Stress behaviour | D50: See the Scenarios and Sensitivity sheets
B51: Character: Promoter track record | D51: Assessed by the bank outside this model: experience, credit history and management team

Sheet Ratios
B1: Ratio Analysis
B2: Profitability, liquidity, leverage, coverage and efficiency, year by year.
B3: ="Scenario: "&Assumptions!$D$11&" | BDT '000 unless stated" -> Scenario: Base case | BDT '000 unless stated
B4: Financial year | C4: Unit | D4: Opening | E4: ="FY"&(Assumptions!$D$7+E5-1)&"-"&TEXT(MOD(Assumptions!$D$7+E5,100),"00") -> FY2026-27 | F4: ="FY"&(Assumptions!$D$7+F5-1)&"-"&TEXT(MOD(Assumptions!$D$7+F5,100),"00") -> FY2027-28 | G4: ="FY"&(Assumptions!$D$7+G5-1)&"-"&TEXT(MOD(Assumptions!$D$7+G5,100),"00") -> FY2028-29 | H4: ="FY"&(Assumptions!$D$7+H5-1)&"-"&TEXT(MOD(Assumptions!$D$7+H5,100),"00") -> FY2029-30 | I4: ="FY"&(Assumptions!$D$7+I5-1)&"-"&TEXT(MOD(Assumptions!$D$7+I5,100),"00") -> FY2030-31
D5: 0 | E5: 1 | F5: 2 | G5: 3 | H5: 4 | I5: 5
B7: Profitability
B8: Gross margin | C8: % | E8: ='Income Statement'!E20 -> 0.28134652 | F8: ='Income Statement'!F20 -> 0.54618906 | G8: ='Income Statement'!G20 -> 0.5543267 | H8: ='Income Statement'!H20 -> 0.62839607 | I8: ='Income Statement'!I20 -> 0.57627597
B9: EBITDA margin | C9: % | E9: ='Income Statement'!E29 -> 0.065572516 | F9: ='Income Statement'!F29 -> 0.44474259 | G9: ='Income Statement'!G29 -> 0.45343317 | H9: ='Income Statement'!H29 -> 0.52781438 | I9: ='Income Statement'!I29 -> 0.47577362
B10: EBIT margin | C10: % | E10: =IFERROR('Income Statement'!E31/'Income Statement'!E10,0) -> -0.19095705 | F10: =IFERROR('Income Statement'!F31/'Income Statement'!F10,0) -> 0.38241288 | G10: =IFERROR('Income Statement'!G31/'Income Statement'!G10,0) -> 0.40405728 | H10: =IFERROR('Income Statement'!H31/'Income Statement'!H10,0) -> 0.48809739 | I10: =IFERROR('Income Statement'!I31/'Income Statement'!I10,0) -> 0.43210516
B11: Net profit margin | C11: % | E11: ='Income Statement'!E36 -> -0.41840196 | F11: ='Income Statement'!F36 -> 0.2651403 | G11: ='Income Statement'!G36 -> 0.27058053 | H11: ='Income Statement'!H36 -> 0.34187944 | I11: ='Income Statement'!I36 -> 0.30668416
B12: Return on equity (net profit / closing equity) | C12: % | E12: =IFERROR('Income Statement'!E35/'Balance Sheet'!E22,0) -> -0.22248772 | F12: =IFERROR('Income Statement'!F35/'Balance Sheet'!F22,0) -> 0.36903344 | G12: =IFERROR('Income Statement'!G35/'Balance Sheet'!G22,0) -> 0.42088783 | H12: =IFERROR('Income Statement'!H35/'Balance Sheet'!H22,0) -> 0.52285371 | I12: =IFERROR('Income Statement'!I35/'Balance Sheet'!I22,0) -> 0.36440617
B13: Return on capital employed (EBIT / (equity + loan)) | C13: % | E13: =IFERROR('Income Statement'!E31/('Balance Sheet'!E22+'Balance Sheet'!E16),0) -> -0.050572107 | F13: =IFERROR('Income Statement'!F31/('Balance Sheet'!F22+'Balance Sheet'!F16),0) -> 0.35945602 | G13: =IFERROR('Income Statement'!G31/('Balance Sheet'!G22+'Balance Sheet'!G16),0) -> 0.49624524 | H13: =IFERROR('Income Statement'!H31/('Balance Sheet'!H22+'Balance Sheet'!H16),0) -> 0.67529924 | I13: =IFERROR('Income Statement'!I31/('Balance Sheet'!I22+'Balance Sheet'!I16),0) -> 0.51343307
B14: Return on assets (net profit / total assets) | C14: % | E14: =IFERROR('Income Statement'!E35/'Balance Sheet'!E12,0) -> -0.1091008 | F14: =IFERROR('Income Statement'!F35/'Balance Sheet'!F12,0) -> 0.2407816 | G14: =IFERROR('Income Statement'!G35/'Balance Sheet'!G12,0) -> 0.31800839 | H14: =IFERROR('Income Statement'!H35/'Balance Sheet'!H12,0) -> 0.45382452 | I14: =IFERROR('Income Statement'!I35/'Balance Sheet'!I12,0) -> 0.34992573
B16: Liquidity
B17: Current ratio (receivables + inventory + cash) / (payables + loan due next year) | C17: x | E17: ='Loan Analysis'!E29 -> 0.56441836 | F17: ='Loan Analysis'!F29 -> 1.3392794 | G17: ='Loan Analysis'!G29 -> 1.9028121 | H17: ='Loan Analysis'!H29 -> 2.9744352 | I17: ='Loan Analysis'!I29 -> 11.975846
B18: Quick ratio (receivables + cash) / current liabilities | C18: x | E18: =IFERROR(('Balance Sheet'!E9+'Balance Sheet'!E11)/('Balance Sheet'!E15+Funding!F28),0) -> 0.23190085 | F18: =IFERROR(('Balance Sheet'!F9+'Balance Sheet'!F11)/('Balance Sheet'!F15+Funding!G28),0) -> 0.60518417 | G18: =IFERROR(('Balance Sheet'!G9+'Balance Sheet'!G11)/('Balance Sheet'!G15+Funding!H28),0) -> 1.0043039 | H18: =IFERROR(('Balance Sheet'!H9+'Balance Sheet'!H11)/('Balance Sheet'!H15+Funding!I28),0) -> 2.0531538 | I18: =IFERROR(('Balance Sheet'!I9+'Balance Sheet'!I11)/('Balance Sheet'!I15+0),0) -> 8.9758458
B19: Cash balance | C19: BDT | E19: ='Balance Sheet'!E11 -> 500000 | F19: ='Balance Sheet'!F11 -> 500000 | G19: ='Balance Sheet'!G11 -> 2715194 | H19: ='Balance Sheet'!H11 -> 10134087 | I19: ='Balance Sheet'!I11 -> 17405778
B21: Leverage
B22: Debt to equity | C22: x | D22: ='Loan Analysis'!D24 -> 0.90441069 | E22: ='Loan Analysis'!E24 -> 1.0078765 | F22: ='Loan Analysis'!F24 -> 0.48073294 | G22: ='Loan Analysis'!G24 -> 0.26653272 | H22: ='Loan Analysis'!H24 -> 0.10539484 | I22: ='Loan Analysis'!I24 -> 0
B23: Debt to EBITDA | C23: x | E23: ='Loan Analysis'!E25 -> 28.905011 | F23: ='Loan Analysis'!F25 -> 0.77661393 | G23: ='Loan Analysis'!G25 -> 0.37789175 | H23: ='Loan Analysis'!H25 -> 0.13056624 | I23: ='Loan Analysis'!I25 -> 0
B24: Total liabilities to owner equity | C24: x | D24: =IFERROR('Balance Sheet'!D17/'Balance Sheet'!D22,0) -> 0.90441069 | E24: =IFERROR('Balance Sheet'!E17/'Balance Sheet'!E22,0) -> 1.0392859 | F24: =IFERROR('Balance Sheet'!F17/'Balance Sheet'!F22,0) -> 0.53264799 | G24: =IFERROR('Balance Sheet'!G17/'Balance Sheet'!G22,0) -> 0.32351172 | H24: =IFERROR('Balance Sheet'!H17/'Balance Sheet'!H22,0) -> 0.15210548 | I24: =IFERROR('Balance Sheet'!I17/'Balance Sheet'!I22,0) -> 0.041381466
B25: Equity ratio (equity / total assets) | C25: % | D25: =IFERROR('Balance Sheet'!D22/'Balance Sheet'!D12,0) -> 0.52509682 | E25: =IFERROR('Balance Sheet'!E22/'Balance Sheet'!E12,0) -> 0.49036772 | F25: =IFERROR('Balance Sheet'!F22/'Balance Sheet'!F12,0) -> 0.65246554 | G25: =IFERROR('Balance Sheet'!G22/'Balance Sheet'!G12,0) -> 0.75556565 | H25: =IFERROR('Balance Sheet'!H22/'Balance Sheet'!H12,0) -> 0.86797608 | I25: =IFERROR('Balance Sheet'!I22/'Balance Sheet'!I12,0) -> 0.96026291
B27: Coverage
B28: Interest cover (EBIT / interest) | C28: x | E28: ='Loan Analysis'!E16 -> -0.83957496 | F28: ='Loan Analysis'!F16 -> 6.9198811 | G28: ='Loan Analysis'!G16 -> 13.100556 | H28: ='Loan Analysis'!H16 -> 29.510946 | I28: ='Loan Analysis'!I16 -> 47.523084
B29: Debt Service Coverage Ratio (DSCR) | C29: x | E29: ='Loan Analysis'!E15 -> -0.5924691 | F29: ='Loan Analysis'!F15 -> 1.6116528 | G29: ='Loan Analysis'!G15 -> 2.6779015 | H29: ='Loan Analysis'!H15 -> 4.4456764 | I29: ='Loan Analysis'!I15 -> 4.3025755
B31: Efficiency and growth
B32: Asset turnover (revenue / total assets) | C32: x | E32: =IFERROR('Income Statement'!E10/'Balance Sheet'!E12,0) -> 0.26075594 | F32: =IFERROR('Income Statement'!F10/'Balance Sheet'!F12,0) -> 0.90812904 | G32: =IFERROR('Income Statement'!G10/'Balance Sheet'!G12,0) -> 1.1752819 | H32: =IFERROR('Income Statement'!H10/'Balance Sheet'!H12,0) -> 1.3274402 | I32: =IFERROR('Income Statement'!I10/'Balance Sheet'!I12,0) -> 1.1409971
B33: Fixed asset turnover (revenue / net fixed assets) | C33: x | E33: =IFERROR('Income Statement'!E10/'Balance Sheet'!E8,0) -> 0.28294795 | F33: =IFERROR('Income Statement'!F10/'Balance Sheet'!F8,0) -> 1.1148049 | G33: =IFERROR('Income Statement'!G10/'Balance Sheet'!G8,0) -> 1.6177663 | H33: =IFERROR('Income Statement'!H10/'Balance Sheet'!H8,0) -> 2.1857941 | I33: =IFERROR('Income Statement'!I10/'Balance Sheet'!I8,0) -> 2.1769985
B34: Cash conversion cycle | C34: days | E34: ='Working Capital'!E24 -> 90 | F34: ='Working Capital'!F24 -> 90 | G34: ='Working Capital'!G24 -> 90 | H34: ='Working Capital'!H24 -> 90 | I34: ='Working Capital'!I24 -> 90
B35: Revenue growth | C35: % | F35: ='Income Statement'!F11 -> 3.1156871 | G35: ='Income Statement'!G11 -> 0.3438226 | H35: ='Income Statement'!H11 -> 0.24319307 | I35: ='Income Statement'!I11 -> -0.090487805
B36: EBITDA growth | C36: % | F36: =IFERROR('Income Statement'!F28/'Income Statement'!E28-1,0) -> 26.914459 | G36: =IFERROR('Income Statement'!G28/'Income Statement'!F28-1,0) -> 0.37008183 | H36: =IFERROR('Income Statement'!H28/'Income Statement'!G28-1,0) -> 0.44712657 | I36: =IFERROR('Income Statement'!I28/'Income Statement'!H28-1,0) -> -0.18016272

Sheet Scenarios and Risk
B1: Scenarios and Risk
B2: Base, downside and upside results saved from running this model, next to the live result of the active scenario.
B3: ="Active scenario: "&Assumptions!$D$11 -> Active scenario: Base case
B5: Result | C5: Base case | D5: Downside case | E5: Upside case | F5: Live: active scenario
B6: Project NPV, 5 years only | C6: 3093767 | D6: -21790956 | E6: 11134817 | F6: ='Investment Analysis'!D38 -> 3093767
B7: Project NPV including recovery value | C7: 30651569 | D7: 6114245.1 | E7: 38758948 | F7: ='Investment Analysis'!D44 -> 30651569
B8: Project IRR including recovery value | C8: 0.29333206 | D8: 0.17535817 | E8: 0.3298856 | F8: ='Investment Analysis'!D45 -> 0.29333206
B9: Payback (years) | C9: 3.6618855 | D9: > 5 | E9: 3.4242946 | F9: ='Investment Analysis'!D42 -> 3.6618855
B10: Minimum Debt Service Coverage Ratio (DSCR) | C10: 1.6116528 | D10: 0.91878093 | E10: 1.8422662 | F10: ='Loan Analysis'!E35 -> 1.6116528
B11: Average Debt Service Coverage Ratio (DSCR) | C11: 3.2594516 | D11: 1.9266266 | E11: 3.6662717 | F11: ='Loan Analysis'!E36 -> 3.2594516
B12: Minimum interest cover | C12: 6.9198811 | D12: 2.8635119 | E12: 8.0499346 | F12: ='Loan Analysis'!E37 -> 6.9198811
B13: Lending benchmarks met (of 8) | C13: 8 | D13: 6 | E13: 8 | F13: ='Loan Analysis'!D43 -> 8
B14: Total owner investment | C14: 27771485 | D14: 37218739 | E14: 26963713 | F14: ='Owner Returns'!D29 -> 27771485
B15: Total dividends in 5 years | C15: 41964048 | D15: 22516529 | E15: 49835698 | F15: ='Owner Returns'!D30 -> 41964048
B16: Lowest closing cash | C16: 500000 | D16: 500000 | E16: 500000 | F16: =MIN('Balance Sheet'!D11:I11) -> 500000
B17: Scenario definitions (change on the Assumptions sheet):
B18: Selling price | C18: =Assumptions!D14 -> 1 | D18: =Assumptions!E14 -> 0.9 | E18: =Assumptions!F14 -> 1.05
B19: Yield / volume | C19: =Assumptions!D15 -> 1 | D19: =Assumptions!E15 -> 0.85 | E19: =Assumptions!F15 -> 1
B20: Feed price | C20: =Assumptions!D16 -> 1 | D20: =Assumptions!E16 -> 1.1 | E20: =Assumptions!F16 -> 0.95
B21: Capital cost | C21: =Assumptions!D17 -> 1 | D21: =Assumptions!E17 -> 1.1 | E21: =Assumptions!F17 -> 1
B22: Interest add-on (pp) | C22: =Assumptions!D18 -> 0 | D22: =Assumptions!E18 -> 0.02 | E22: =Assumptions!F18 -> 0
B23: Base, downside and upside are saved results. The live column follows the selector on the Assumptions sheet.
B25: Revenue by year
B26: BDT | C26: Year 1 | D26: Year 2 | E26: Year 3 | F26: Year 4 | G26: Year 5
B27: Base case | C27: 12080000 | D27: 49717500 | E27: 66811500 | F27: 83059594 | G27: 75543713
B28: Downside case | C28: 9241200 | D28: 38033888 | E28: 51110798 | F28: 63540589 | G28: 57790941
B29: Upside case | C29: 12684000 | D29: 52203375 | E29: 70152075 | F29: 87212573 | G29: 79320899
B30: Live: active scenario | C30: ='Income Statement'!E10 -> 12080000 | D30: ='Income Statement'!F10 -> 49717500 | E30: ='Income Statement'!G10 -> 66811500 | F30: ='Income Statement'!H10 -> 83059594 | G30: ='Income Statement'!I10 -> 75543713
B31: Year 4 includes the one-time sale of the old broodfish.
B32: EBITDA by year
B33: BDT | C33: Year 1 | D33: Year 2 | E33: Year 3 | F33: Year 4 | G33: Year 5
B34: Base case | C34: 792115.99 | D34: 22111489 | E34: 30294550 | F34: 43840048 | G34: 35941706
B35: Downside case | C35: -962191.05 | D35: 13163153 | E35: 18404326 | F35: 28565428 | G35: 22311491
B36: Upside case | C36: 1607120.2 | D36: 25216351 | E36: 34398900 | F36: 48730454 | G36: 40551534
B37: Live: active scenario | C37: ='Income Statement'!E28 -> 792115.99 | D37: ='Income Statement'!F28 -> 22111489 | E37: ='Income Statement'!G28 -> 30294550 | F37: ='Income Statement'!H28 -> 43840048 | G37: ='Income Statement'!I28 -> 35941706
B39: Net profit after tax by year
B40: BDT | C40: Year 1 | D40: Year 2 | E40: Year 3 | F40: Year 4 | G40: Year 5
B41: Base case | C41: -5054295.7 | D41: 13182113 | E41: 18077891 | F41: 28396368 | G41: 23168060
B42: Downside case | C42: -7777398.1 | D42: 6347945.5 | E42: 9253128.7 | F42: 16844245 | G42: 12927559
B43: Upside case | C43: -4239291.5 | D43: 15209011 | E43: 21053545 | F43: 31941912 | G43: 26510185
B44: Live: active scenario | C44: ='Income Statement'!E35 -> -5054295.7 | D44: ='Income Statement'!F35 -> 13182113 | E44: ='Income Statement'!G35 -> 18077891 | F44: ='Income Statement'!H35 -> 28396368 | G44: ='Income Statement'!I35 -> 23168060
B46: Risk register
B47: Risk | C47: Likelihood | D47: Impact | E47: Where it shows | H47: Mitigation
B48: Fish disease and high mortality | C48: Medium | D48: High | E48: Yield factor; Farming survival | H48: Water quality instruments, microscope and regular health checks; staged stocking
B49: Feed price rise above plan | C49: High | D49: High | E49: Feed price factor; Sensitivity | H49: Bulk purchase, feed contracts; feed is the largest cost line (the plan already adds a yearly increase)
B50: Fall in fish or fry selling price | C50: Medium | D50: High | E50: Price factor; Sensitivity | H50: Spread sales across buyers; hatchery and farming diversify income
B51: Yearly selling price increase not achieved | C51: Medium | D51: High | E51: Price increase a year; Sensitivity | H51: The plan adds a yearly price increase; test lower increases on the Sensitivity sheet and sign longer-term supply contracts
B52: Salary and administrative costs rise faster than plan | C52: Medium | D52: Medium | E52: Salary and administrative increase a year | H52: Review the yearly increase on the Assumptions sheet; link pay rises to results
B53: Farming and hatchery depend on one site | C53: Low | D53: High | E53: Not modelled; insurance | H53: Disease, flood or power failure hits both units: insurance, generator (in asset list), site biosecurity
B54: Delay in harvest or fry output | C54: Medium | D54: Medium | E54: Farming and Hatchery calendars | H54: Cycle planning; hatchery shed capacity for steady fry supply
B55: Interest rate increase | C55: Medium | D55: Medium | E55: Interest add-on; Debt Service Coverage Ratio | H55: Fixed-rate or capped loan; keep minimum cash reserve
B56: Capital cost overrun | C56: Medium | D56: Medium | E56: Capital cost factor | H56: Fixed-price civil contracts; contingency (5% on equipment is already included)
B57: Land value falls | C57: Low | D57: Medium | E57: Land value change (Assumptions) | H57: Land is already taken 10% below cost when the project value is recovered
B58: Receivable delays | C58: Medium | D58: Medium | E58: Working Capital tab | H58: Credit limits; advance on bulk orders

Sheet Sensitivity and Break-even
B1: Sensitivity and Break-even
B2: Each row changes one thing against the base case. Break-even is live.
B3: ="Active scenario: "&Assumptions!$D$11 -> Active scenario: Base case
B5: One-way sensitivities (saved results)
B6: Case | C6: NPV incl. recovery | D6: NPV, 5 years only | E6: IRR incl. recovery | F6: Minimum DSCR | G6: Benchmarks met
B7: Base case | C7: 30651569 | D7: 3093767 | E7: 0.29333206 | F7: 1.6116528 | G7: 8
B8: Selling price -10% | C8: 18419975 | D8: -8837324.6 | E8: 0.23674778 | F8: 1.2818508 | G8: 8
B9: Selling price +10% | C9: 42875273 | D9: 15017209 | E9: 0.34744765 | F9: 1.9414549 | G9: 8
B10: Volume (yield) -20% | C10: 18335160 | D10: -8126428 | E10: 0.23767021 | F10: 1.3357356 | G10: 7
B11: Volume (yield) -10% | C11: 24498565 | D11: -2511633.8 | E11: 0.26609297 | F11: 1.4736942 | G11: 8
B12: Feed price +10% | C12: 26665113 | D12: -1060357.5 | E12: 0.27460158 | F12: 1.4802281 | G12: 8
B13: Capital cost +10% | C13: 29161379 | D13: 320321.09 | E13: 0.27956344 | F13: 1.5460193 | G13: 8
B14: Interest rate +2 percentage points | C14: 30651569 | D14: 3093767 | E14: 0.29333206 | F14: 1.5572091 | G14: 8
B15: No yearly price increase (0%) | C15: 17745059 | D15: -9256621 | E15: 0.23660318 | F15: 1.4429651 | G15: 8
B16: Land recovery value 20% below cost | C16: 29637025 | D16: 3093767 | E16: 0.28957704 | F16: 1.6116528 | G16: 8
B17: Cost of equity 25% | C17: 23584964 | D17: -1022776.5 | E17: 0.29333206 | F17: 1.6116528 | G17: 8
B19: Project NPV incl. recovery: selling price change (down) against feed price change (across)
B20: Price change \ Feed change | C20: -10% | D20: +0% | E20: +10% | F20: +20%
B21: -20% | C21: 10164618 | D21: 6180437.5 | E21: 2198331.7 | F21: -1781711.9
B22: -10% | C22: 22406347 | D22: 18419975 | E22: 14435681 | F22: 10453454
B23: +0% | C23: 34640107 | D23: 30651569 | E23: 26665113 | F23: 22680727
B24: +10% | C24: 46865952 | D24: 42875273 | E24: 38886680 | F24: 34900160
B25: +20% | C25: 58979055 | D25: 55091142 | E25: 51100437 | F25: 47111809
B27: These are pasted results of model runs. They do not update when inputs change.
B29: Financial year | C29: Unit | D29: Opening | E29: ="FY"&(Assumptions!$D$7+E30-1)&"-"&TEXT(MOD(Assumptions!$D$7+E30,100),"00") -> FY2026-27 | F29: ="FY"&(Assumptions!$D$7+F30-1)&"-"&TEXT(MOD(Assumptions!$D$7+F30,100),"00") -> FY2027-28 | G29: ="FY"&(Assumptions!$D$7+G30-1)&"-"&TEXT(MOD(Assumptions!$D$7+G30,100),"00") -> FY2028-29 | H29: ="FY"&(Assumptions!$D$7+H30-1)&"-"&TEXT(MOD(Assumptions!$D$7+H30,100),"00") -> FY2029-30 | I29: ="FY"&(Assumptions!$D$7+I30-1)&"-"&TEXT(MOD(Assumptions!$D$7+I30,100),"00") -> FY2030-31
D30: 0 | E30: 1 | F30: 2 | G30: 3 | H30: 4 | I30: 5
B31: Break-even (live)
B32: Revenue | C32: BDT | F32: ='Income Statement'!F10 -> 49717500 | G32: ='Income Statement'!G10 -> 66811500 | H32: ='Income Statement'!H10 -> 83059594 | I32: ='Income Statement'!I10 -> 75543713
B33: Variable costs (direct costs, variable overheads, marketing, selling) | C33: BDT | F33: =Operations!F39 -> 25250346 | G33: =Operations!G39 -> 34059314 | H33: =Operations!H39 -> 36653397 | I33: =Operations!I39 -> 36920332
B34: Contribution margin | C34: % | F34: =IFERROR(1-F33/F32,0) -> 0.49212359 | G34: =IFERROR(1-G33/G32,0) -> 0.49021779 | H34: =IFERROR(1-H33/H32,0) -> 0.55870965 | I34: =IFERROR(1-I33/I32,0) -> 0.51127194
B35: Fixed cash costs (administrative, distribution) | C35: BDT | F35: =Operations!F48 -> 2355665 | G35: =Operations!G48 -> 2457635.8 | H35: =Operations!H48 -> 2566148.8 | I35: =Operations!I48 -> 2681675.6
B36: Depreciation and interest | C36: BDT | F36: ='FA Schedule'!F24+Funding!F32 -> 5846411.7 | G36: ='FA Schedule'!G24+Funding!G32 -> 5359528.1 | H36: ='FA Schedule'!H24+Funding!H32 -> 4672644.5 | I36: ='FA Schedule'!I24+Funding!I32 -> 3985760.8
B37: Break-even revenue (profit = 0) | C37: BDT | F37: =IFERROR((F35+F36)/F34,0) -> 16666701 | G37: =IFERROR((G35+G36)/G34,0) -> 15946308 | H37: =IFERROR((H35+H36)/H34,0) -> 12956270 | I37: =IFERROR((I35+I36)/I34,0) -> 13040881
B38: Margin of safety (revenue above break-even) | C38: % | F38: =IFERROR(1-F37/F32,0) -> 0.66477194 | G38: =IFERROR(1-G37/G32,0) -> 0.7613239 | H38: =IFERROR(1-H37/H32,0) -> 0.84401236 | I38: =IFERROR(1-I37/I32,0) -> 0.82737305
B39: Cash break-even revenue (covers cash costs and debt service) | C39: BDT | F39: =IFERROR((F35+Funding!F33)/F34,0) -> 22001038 | G39: =IFERROR((G35+Funding!G33)/G34,0) -> 20893401 | H39: =IFERROR((H35+Funding!H33)/H34,0) -> 17296902 | I39: =IFERROR((I35+Funding!I33)/I34,0) -> 17784253
B40: Revenue fall the project can absorb before cash break-even | C40: % | F40: =IFERROR(1-F39/F32,0) -> 0.55747899 | G40: =IFERROR(1-G39/G32,0) -> 0.68727837 | H40: =IFERROR(1-H39/H32,0) -> 0.79175311 | I40: =IFERROR(1-I39/I32,0) -> 0.76458329
B42: Years 2 to 5 (Year 1 is a part year). Uses the active scenario; tax and working capital are ignored.

Sheet Checks
B1: Model Integrity Checks
B2: Every line should read OK. ERROR means a link or an input needs attention.
B3: ="Active scenario: "&Assumptions!$D$11 -> Active scenario: Base case
B4: Check | C4: Result
B5: Balance sheet balances in every year | C5: =IF(SUMPRODUCT(ABS('Balance Sheet'!D25:I25))<1,"OK","ERROR") -> OK
B6: Sources of funds equal uses of funds | C6: =IF(ABS(Funding!D18-Funding!D13)<1,"OK","ERROR") -> OK
B7: Term loan is fully repaid by the end of the tenor | C7: =IF(AND(Funding!I29<1,ABS(SUM(Funding!E28:I28)-Funding!D16)<1),"OK","ERROR") -> OK
B8: Retained earnings equal cumulative profit less dividends | C8: =IF(ABS('Balance Sheet'!I21-SUM('Income Statement'!E35:I35)-SUM('Cash Flow'!E23:I23))<1,"OK","ERROR") -> OK
B9: Tax loss balance is never negative | C9: =IF(MIN('Income Statement'!E42:I42)>=0,"OK","ERROR") -> OK
B10: Net book value of fixed assets is never negative | C10: =IF(MIN('FA Schedule'!D30:I30)>=-0.5,"OK","ERROR") -> OK
B11: Segment profit before tax adds up to the Income Statement | C11: =IF(SUMPRODUCT(ABS('Segment Analysis'!E44:I44-'Income Statement'!E33:I33))<1,"OK","ERROR") -> OK
B12: Segment revenue adds up to the Income Statement | C12: =IF(SUMPRODUCT(ABS('Segment Analysis'!E42:I42-'Income Statement'!E10:I10))<1,"OK","ERROR") -> OK
B13: Month-wise revenue adds up to the annual revenue on the Farming and Hatchery sheets | C13: =IF((ABS(Farming!I69-Farming!D60)+ABS(Hatchery!I67-Hatchery!D56)+ABS(Farming!V69-Farming!G60)+ABS(Hatchery!V67-Hatchery!G56)+ABS(Farming!AI69-Farming!J60)+ABS(Hatchery!AI67-Hatchery!J56)+ABS(Farming!AV69-Farming!M60)+ABS(Hatchery!AV67-Hatchery!M56))<1,"OK","ERROR") -> OK
B14: Asset list total equals Year 0 capital expenditure (when capital factor is 1) | C14: =IF(IF(Assumptions!$G$17<>1,TRUE(),ABS('FA Schedule'!E84-'FA Schedule'!D15)<1),"OK","ERROR") -> OK
B15: Operations revenue equals Farming plus Hatchery revenue (Year 2, after scenario factors) | C15: =IF(ABS(Operations!F16-(Farming!G60+Hatchery!G56)*Assumptions!$G$14*Assumptions!$G$15)<1,"OK","ERROR") -> OK
B16: Cash Flow Generated on the Cash Flow sheet reconciles to operations plus investing in every year | C16: =IF(SUMPRODUCT(ABS('Cash Flow'!E47:I47))<1,"OK","ERROR") -> OK
B17: Direct method cash flow equals the indirect method in every year | C17: =IF(SUMPRODUCT(ABS('Cash Flow'!E60:I60))<1,"OK","ERROR") -> OK
B18: Hatchery share is between 0% and 100% | C18: =IF(AND(Assumptions!$D$59>=0,Assumptions!$D$59<=1),"OK","ERROR") -> OK
B19: Dividends never exceed profit after tax | C19: =IF(SUMPRODUCT(--(-'Cash Flow'!E23:I23>(('Income Statement'!E35:I35>0)*'Income Statement'!E35:I35)+1))=0,"OK","ERROR") -> OK
B21: Overall model status | C21: =IF(COUNTIF(C5:C19,"OK")=15,"ALL OK","CHECK") -> ALL OK
B23: Information (not integrity checks)
B24: Owner equity injected after Year 0 to keep minimum cash (BDT) | C24: =SUM('Cash Flow'!E22:I22) -> 2455418.5
B25: Lending benchmarks met | C25: ='Loan Analysis'!D43&" of "&'Loan Analysis'!E43 -> 8 of 8
